Workbook

Sheet IP_BS Raw
A1: Balance Sheet | C1: Yearly
E2: 2021 | F2: 2022 | G2: 2023 | H2: 2024 | I2: 2025
A3: Trạng thái kiểm toán | C3: Audit Status
A4: Công ty Kiểm toán | C4: Audit Firm
A5: Loại Ý kiến Kiểm toán | C5: Audit Opinion Type
A6: TÀI SẢN NGẮN HẠN | C6: CURRENT ASSETS | E6: 1134580036184 | F6: 623158641225 | G6: 947639699363 | H6: 1305306889451 | I6: 1870935494083
A7: Tiền và tương đương tiền | C7: Cash and cash equivalents | E7: 4321225874 | F7: 26473013864 | G7: 8461339357 | H7: 136236074178 | I7: 288524181242
A8: Tiền | C8: Cash | E8: 4321225874 | F8: 22373013864 | G8: 4261339357 | H8: 125344482100 | I8: 167000000000
A9: Các khoản tương đương tiền | C9: Cash equivalents | F9: 4100000000 | G9: 4200000000 | H9: 10891592078
A10: Giá trị thuần đầu tư ngắn hạn | C10: Short-term investments | E10: 4900000000 | F10: 50000000 | G10: 230000000 | H10: 1230000000 | I10: 164600000000
A11: Đầu tư ngắn hạn | C11: Short-term investments
A12: Dự phòng đầu tư ngắn hạn | C12: Provision for diminution
A13: Đầu tư nắm giữ đến ngày đáo hạn | C13: Held-to-maturity investment | E13: 4900000000 | F13: 50000000 | G13: 230000000 | H13: 1230000000 | I13: 164600000000
A14: Các khoản phải thu | C14: Accounts receivable | E14: 1059557585612 | F14: 541296932112 | G14: 845395421575 | H14: 1101930451740 | I14: 1305199947643
A15: Phải thu khách hàng | C15: Trade accounts receivable | E15: 117379744019 | F15: 161650767393 | G15: 239558303914 | H15: 351157857253 | I15: 539420115084
A16: Trả trước người bán | C16: Prepayments to suppliers | E16: 217954579335 | F16: 82005142464 | G16: 80957663203 | H16: 353377447486 | I16: 369672191130
A17: Phải thu nội bộ | C17: Intercompany receivables
A18: Phải thu về XDCB | C18: Construction contract in progress receivables
A19: Phải thu về cho vay ngắn hạn | C19: Short-term loans receivables | E19: 1915829000 | F19: 164433231206 | G19: 266334265625 | H19: 355269960018
A20: Phải thu khác | C20: Other receivables | E20: 757590749230 | F20: 209178378379 | G20: 340356202385 | H20: 113140517320 | I20: 161724203814
A21: Dự phòng nợ khó đòi | C21: Provision for doubtful debts | E21: -35283315972 | F21: -75970587330 | G21: -81811013552 | H21: -71015330337 | I21: -21679830385
A22: Tài sản thiếu chờ xử lý | C22: Shortage of current assets waiting for solution
A23: Hàng tồn kho, ròng | C23: Inventories, Net | E23: 30723500694 | F23: 15511002401 | G23: 29168608393 | H23: 40804852414 | I23: 97855839839
A24: Hàng tồn kho | C24: Inventories | E24: 96101925885 | F24: 75467022274 | G24: 63724327379 | H24: 40804852414 | I24: 97855839839
A25: Dự phòng giảm giá HTK | C25: Provision for decline in inventories | E25: -65378425191 | F25: -59956019873 | G25: -34555718986 | H25: -34555718986
A26: Tài sản lưu động khác | C26: Other current assets | E26: 35077724004 | F26: 39827692848 | G26: 64384330038 | H26: 25105511119 | I26: 14755525359
A27: Chi phí trả trước ngắn hạn | C27: Short-term prepayments | E27: 17929095329 | F27: 27938305891 | G27: 50416954766 | H27: 15054268237 | I27: 9851906402
A28: Thuế GTGT được khấu trừ | C28: VAT to be claimed | E28: 17043590290 | F28: 11733669810 | G28: 13954750488 | H28: 10019963592 | I28: 4872339667
A29: Phải thu thuế khác | C29: Other taxes receivable | E29: 105038385 | F29: 155717147 | G29: 12624784 | H29: 31279290 | I29: 31279290
A30: Giao dịch mua bán lại trái phiếu chính phủ | C30: Government bonds purchased for resale
A31: Tài sản lưu động khác | C31: Other current assets
A32: TÀI SẢN DÀI HẠN | C32: LONG-TERM ASSETS | E32: 237702799766 | F32: 617819241835 | G32: 912758343006 | H32: 1207562711144 | I32: 925445778563
A33: Phải thu dài hạn | C33: Long-term trade receivables | E33: 42966607789 | F33: 368503496695 | G33: 389469485495 | H33: 477290973579 | I33: 223233334800
A34: Phải thu khách hàng dài hạn | C34: Long-term trade receivables from customers | H34: 24000000000 | I34: 24000000000
A35: Trả trước người bán dài hạn | C35: Long-term prepayments to suppliers
A36: Vốn kinh doanh ở các đơn vị trực thuộc | C36: Paid-in capital in wholly-owned subsidiaries
A37: Phải thu nội bộ dài hạn | C37: Long-term intercompany receivables
A38: Phải thu về cho vay dài hạn | C38: Long-term loans receivables | E38: 39090075288 | F38: 119000000000 | G38: 44329575396 | H38: 10990000000 | I38: 19890000000
A39: Phải thu dài hạn khác | C39: Other long-term receivables | E39: 3876532501 | F39: 249503496695 | G39: 345139910099 | H39: 442300973579 | I39: 203343334800
A40: Dự phòng phải thu dài hạn | C40: Provision for doubtful LT receivable
A41: Tài sản cố định | C41: Fixed assets | E41: 30899153002 | F41: 12227445584 | G41: 86305316088 | H41: 208544841945 | I41: 223327926322
A42: GTCL TSCĐ hữu hình | C42: Tangible fixed assets | E42: 2921208332 | F42: 1915044232 | G42: 1324037529 | H42: 10300656939 | I42: 5452363066
A43: Nguyên giá TSCĐ hữu hình | C43: Cost | E43: 19645497072 | F43: 32063148590 | G43: 14438805810 | H43: 16097844675 | I43: 12681738494
A44: Khấu hao lũy kế TSCĐ hữu hình | C44: Accumulated depreciation | E44: -16724288740 | F44: -30148104358 | G44: -13114768281 | H44: -5797187736 | I44: -7229375428
A45: GTCL Tài sản thuê tài chính | C45: Finance lease assets
A46: Nguyên giá tài sản thuê tài chính | C46: Cost
A47: Khấu hao lũy kế tài sản thuê tài chính | C47: Accumulated depreciation
A48: GTCL tài sản cố định vô hình | C48: Intangible fixed assets | E48: 27977944670 | F48: 10312401352 | G48: 84981278559 | H48: 198244185006 | I48: 217875563256
A49: Nguyên giá TSCĐ vô hình | C49: Cost | E49: 37281440657 | F49: 19053507540 | G49: 102179503617 | H49: 243416211684 | I49: 310113732544
A50: Khấu khao lũy kế TSCĐ vô hình | C50: Accumulated depreciation | E50: -9303495987 | F50: -8741106188 | G50: -17198225058 | H50: -45172026678 | I50: -92238169288
A51: Xây dựng cơ bản dở dang (trước 2015) | C51: Construction in progress (before 2015)
A52: Giá trị ròng tài sản đầu tư | C52: Investment properties
A53: Nguyên giá tài sản đầu tư | C53: Cost
A54: Khấu hao lũy kế tài sản đầu tư | C54: Accumulated depreciation
A55: Tài sản dở dang dài hạn | C55: Long-term incomplete assets | E55: 5086363637 | F55: 22565454545 | G55: 13367018518 | H55: 63162748821 | I55: 57177622222
A56: Chi phí sản xuất, kinh doanh dở dang dài hạn | C56: Long-term cost of work in progress
A57: Xây dựng cơ bản dở dang | C57: Construction in progress | E57: 5086363637 | F57: 22565454545 | G57: 13367018518 | H57: 63162748821 | I57: 57177622222
A58: Đầu tư dài hạn | C58: Long-term investments | E58: 133341086382 | F58: 140347514642 | G58: 383408540098 | H58: 111178423767 | I58: 124915632725
A59: Đầu tư vào các công ty con | C59: Investments in subsidiaries
A60: Đầu tư vào các công ty liên kết | C60: Investments in associates | E60: 131583461382 | F60: 132247514642 | G60: 348572994312 | H60: 103807419542 | I60: 124915632725
A61: Đầu tư dài hạn khác | C61: Other long-term investments | E61: 9615625000 | F61: 17715625000 | G61: 46002910277 | H61: 19715625000 | I61: 11615625000
A62: Dự phòng giảm giá đầu tư dài hạn | C62: Provision for long-term investments | E62: -7858000000 | F62: -9615625000 | G62: -11167364491 | H62: -12344620775 | I62: -11615625000
A63: Đầu tư nắm giữ đến ngày đáo hạn | C63: Held-to-maturity investment
A64: Lợi thế thương mại (trước 2015) | C64: Good will (before 2015)
A65: Tài sản dài hạn khác | C65: Other long-term assets | E65: 25409588956 | F65: 74175330369 | G65: 40207982807 | H65: 347385723032 | I65: 296791262494
A66: Trả trước dài hạn | C66: Long-term prepayments | E66: 9225278708 | F66: 3220915857 | G66: 1484504008 | H66: 42009118834 | I66: 25606498943
A67: Thuế thu nhập hoãn lại phải thu | C67: Deferred income tax assets | E67: 0 | G67: 7895844762 | H67: 3513354336 | I67: 1331876134
A68: Thiết bị, vật tư, phụ tùng thay thế dài hạn | C68: Long-term equipment, material and spare parts
A69: Các tài sản dài hạn khác | C69: Other long-term assets
A70: Lợi thế thương mại | C70: Good will | E70: 16184310248 | F70: 70954414512 | G70: 30827634037 | H70: 301863249862 | I70: 269852887417
A71: TỔNG CỘNG TÀI SẢN | C71: TOTAL ASSETS | E71: 1372282835950 | F71: 1240977883060 | G71: 1860398042369 | H71: 2512869600595 | I71: 2796381272646
A72: NỢ PHẢI TRẢ | C72: LIABILITIES | E72: 494579526697 | F72: 334197703328 | G72: 477098903310 | H72: 1012991101726 | I72: 675630266168
A73: Nợ ngắn hạn | C73: Current liabilities | E73: 403533140176 | F73: 315495843209 | G73: 408623646511 | H73: 962985040933 | I73: 630726249783
A74: Phải trả người bán | C74: Trade accounts payable | E74: 87325315040 | F74: 83181799835 | G74: 98153102705 | H74: 137590758890 | I74: 149093578776
A75: Người mua trả tiền trước | C75: Advances from customers | E75: 10531972357 | F75: 6405918023 | G75: 29155365881 | H75: 13959803176 | I75: 945762696
A76: Thuế và các khoản phải trả Nhà nước | C76: Taxes and other payable to State Budget | E76: 44788657390 | F76: 42048654493 | G76: 32330181730 | H76: 40757934104 | I76: 28279825499
A77: Phải trả người lao động | C77: Payable to employees | E77: 14530928335 | F77: 4685853174 | G77: 5107804827 | H77: 14383857602 | I77: 13995873114
A78: Chi phí phải trả | C78: Accrued expenses | E78: 56813526262 | F78: 18755981834 | G78: 27448675197 | H78: 78176209568 | I78: 81109306439
A79: Phải trả nội bộ | C79: Intercompany payables
A80: Phải trả về xây dựng cơ bản | C80: Construction contract in progress payables
A81: Doanh thu chưa thực hiện ngắn hạn | C81: Short-term unrealized revenue
A82: Phải trả khác | C82: Other payables | E82: 58740650313 | F82: 66099828450 | G82: 45075825259 | H82: 147901263340 | I82: 50179527970
A83: Vay ngắn hạn | C83: Short-term borrowings | E83: 130796216812 | F83: 94317807400 | G83: 171352690912 | H83: 527364096445 | I83: 304271257481
A84: Dự phòng các khoản phải trả ngắn hạn | C84: Provision for ST liabilities
A85: Quỹ khen thưởng, phúc lợi | C85: Bonus and welfare funds | E85: 5873667 | F85: 0 | H85: 2851117808 | I85: 2851117808
A86: Quỹ bình ổn giá | C86: Price stabilization fund
A87: Giao dịch mua bán lại trái phiếu chính phủ | C87: Government bonds purchased for resale
A88: Nợ dài hạn | C88: Long-term liabilities | E88: 91046386521 | F88: 18701860119 | G88: 68475256799 | H88: 50006060793 | I88: 44904016385
A89: Phải trả nhà cung cấp dài hạn | C89: Long-term trade payables
A90: Người mua trả tiền trước dài hạn | C90: Long-term advances from customers
A91: Chi phí phải trả dài hạn | C91: Long-term accrued expenses
A92: Phải trả nội bộ về vốn kinh doanh | C92: Intra-company payables for operating capital received
A93: Phải trả nội bộ dài hạn | C93: Long-term intercompany payables
A94: Doanh thu chưa thực hiên | C94: Deferred revenue
A95: Phải trả dài hạn khác | C95: Other long-term payables | E95: 0 | F95: 87600000 | G95: 0
A96: Vay dài hạn | C96: Long-term borrowings | E96: 71000000000 | F96: 1000000000 | G96: 39014432856 | H96: 50006060793 | I96: 36866802037
A97: Trái phiếu chuyển đổi | C97: Convertible bonds
A98: Cổ phiếu ưu đãi | C98: Preferred shares
A99: Thuế thu nhập hoãn lại phải trả | C99: Deferred income tax liabilities | E99: 20046386521 | F99: 17614260119 | G99: 29460823943 | H99: 0 | I99: 8037214348
A100: Dự phòng trợ cấp thôi việc | C100: Provision for severance allowances
...

Sheet IP_BS Raw (Q)
A1: Balance Sheet | C1: Yearly
E2: Q1/2023 | F2: Q2/2023 | G2: Q3/2023 | H2: Q4/2023 | I2: Q1/2024 | J2: Q2/2024 | K2: Q3/2024 | L2: Q4/2024 | M2: Q1/2025 | N2: Q2/2025
A3: Trạng thái kiểm toán | C3: Audit Status
A4: Công ty Kiểm toán | C4: Audit Firm
A5: Loại Ý kiến Kiểm toán | C5: Audit Opinion Type
A6: TÀI SẢN NGẮN HẠN | C6: CURRENT ASSETS | E6: 1409037526271 | F6: 1155329892754 | G6: 1241097341198 | H6: 1338882873206 | I6: 1534930595272 | J6: 3551337411765 | K6: 2273841866477 | L6: 1811557308602 | M6: 2184149555149 | N6: 2856221396120
A7: Tiền và tương đương tiền | C7: Cash and cash equivalents | E7: 562194548070 | F7: 330747178714 | G7: 308834851881 | H7: 370506274358 | I7: 556699581545 | J7: 655668705735 | K7: 600764730236 | L7: 546631384396 | M7: 883423559831 | N7: 676759173937
A8: Tiền | C8: Cash | E8: 325223629254 | F8: 150633485436 | G8: 136084851881 | H8: 135606274358 | I8: 384898581545 | J8: 336085705735 | K8: 471309730236 | L8: 340111384396 | M8: 393723559831 | N8: 325290173937
A9: Các khoản tương đương tiền | C9: Cash equivalents | E9: 236970918816 | F9: 180113693278 | G9: 172750000000 | H9: 234900000000 | I9: 171801000000 | J9: 319583000000 | K9: 129455000000 | L9: 206520000000 | M9: 489700000000 | N9: 351469000000
A10: Giá trị thuần đầu tư ngắn hạn | C10: Short-term investments | E10: 111367439500 | F10: 264148000000 | G10: 413826714686 | H10: 425016299943 | I10: 469863293757 | J10: 51883578552 | K10: 968931033587 | L10: 806333297341 | M10: 853380702240 | N10: 1721383996451
A11: Đầu tư ngắn hạn | C11: Short-term investments | E11: 0 | F11: 0 | G11: 0 | H11: 0 | I11: 215461708500 | J11: 29683578552 | K11: 712541033587 | L11: 546648172508 | M11: 692356007368 | N11: 1404542928928
A12: Dự phòng đầu tư ngắn hạn | C12: Provision for diminution | E12: 0 | F12: 0 | G12: 0 | H12: 0 | I12: 0 | J12: 0 | K12: 0 | L12: -26064875167 | M12: -11125305128 | N12: -2308932477
A13: Đầu tư nắm giữ đến ngày đáo hạn | C13: Held-to-maturity investment | E13: 111367439500 | F13: 264148000000 | G13: 413826714686 | H13: 425016299943 | I13: 254401585257 | J13: 22200000000 | K13: 256390000000 | L13: 285750000000 | M13: 172150000000 | N13: 319150000000
A14: Các khoản phải thu | C14: Accounts receivable | E14: 599456379288 | F14: 434425753404 | G14: 431391845888 | H14: 459992517275 | I14: 421918186662 | J14: 2744767483791 | K14: 606625885186 | L14: 354874936762 | M14: 336164556041 | N14: 348420871459
A15: Phải thu khách hàng | C15: Trade accounts receivable | E15: 171444908546 | F15: 204039063759 | G15: 229796518541 | H15: 205263011710 | I15: 206694904252 | J15: 306664694204 | K15: 255299695231 | L15: 236744183566 | M15: 229779044357 | N15: 263793638340
A16: Trả trước người bán | C16: Prepayments to suppliers | E16: 7495345183 | F16: 6851897276 | G16: 12131486755 | H16: 13578690375 | I16: 25025462752 | J16: 22298904863 | K16: 36925090068 | L16: 18808589913 | M16: 26804944326 | N16: 18346837122
A17: Phải thu nội bộ | C17: Intercompany receivables | E17: 0 | F17: 0 | G17: 0 | H17: 0 | I17: 0 | J17: 0 | K17: 0 | L17: 0 | M17: 0 | N17: 0
... A97: Trái phiếu chuyển đổi | C97: Convertible bonds | E97: 0 | F97: 0 | G97: 0 | H97: 0 | I97: 0 | J97: 0 | K97: 0 | L97: 0 | M97: 0 | N97: 0
A98: Cổ phiếu ưu đãi | C98: Preferred shares
A99: Thuế thu nhập hoãn lại phải trả | C99: Deferred income tax liabilities | E99: 30858278235 | F99: 30635575473 | G99: 30635575473 | H99: 30412872712 | I99: 30412872712 | J99: 30190169950 | K99: 30190169950 | L99: 530378777454 | M99: 524109383529 | N99: 517134453438
A100: Dự phòng trợ cấp thôi việc | C100: Provision for severance allowances | E100: 0 | F100: 0 | G100: 0 | H100: 0 | I100: 0 | J100: 0 | K100: 0 | L100: 0 | M100: 0 | N100: 0
A101: Dự phòng các khoản công nợ dài hạn | C101: Provision for long-term liabilities | E101: 1005061631 | F101: 904958500 | G101: 904958500 | H101: 3176036942 | I101: 2827286942 | J101: 2827286942 | K101: 2267636942 | L101: 2529636942 | M101: 2232636942 | N101: 1465836942
A102: Quỹ phát triển khoa học công nghệ | C102: Technology-science development fund | E102: 0 | F102: 0 | G102: 0 | H102: 0 | I102: 0 | J102: 0 | K102: 0 | L102: 0 | M102: 0 | N102: 0
A103: VỐN CHỦ SỞ HỮU | C103: OWNER'S EQUITY | E103: 3041381520419 | F103: 3173978566040 | G103: 3222730828695 | H103: 3296823080450 | I103: 3336799929686 | J103: 4655479522764 | K103: 4598804958115 | L103: 4896115718281 | M103: 5124410473113 | N103: 5070117701416
A104: Vốn và các quỹ | C104: Capital and reserves | E104: 3041381520419 | F104: 3173978566040 | G104: 3222730828695 | H104: 3296823080450 | I104: 3336799929686 | J104: 4655479522764 | K104: 4598804958115 | L104: 4896115718281 | M104: 5124410473113 | N104: 5070117701416
A105: Vốn góp | C105: Paid-in capital | E105: 1212693970000 | F105: 1212693970000 | G105: 1333956420000 | H105: 1333956420000 | I105: 1333956420000 | J105: 2667912840000 | K105: 2867968190000 | L105: 2867968190000 | M105: 2995008190000 | N105: 3743703620000
A106: Cổ phiếu phổ thông | C106: Common shares | E106: 1212693970000 | F106: 1212693970000 | G106: 1333956420000 | H106: 1333956420000 | I106: 1333956420000 | J106: 2667912840000 | K106: 2867968190000 | L106: 2867968190000 | M106: 2995008190000 | N106: 3743703620000
A107: Cổ phiếu ưu đãi | C107: Preferred shares | E107: 0 | F107: 0 | G107: 0 | H107: 0 | I107: 0 | J107: 0 | K107: 0 | L107: 0 | M107: 0 | N107: 0
A108: Thặng dư vốn cổ phần | C108: Share premium | E108: 39403521246 | F108: 39403521246 | G108: 39403521246 | H108: 39403521246 | I108: 39403521246 | J108: 39403521246 | K108: 39497521246 | L108: 39497521246 | M108: 39497521246 | N108: 94000000
A109: Quyền chọn chuyển đổi trái phiếu | C109: Conversion options on convertible bonds | E109: 0 | F109: 0 | G109: 0 | H109: 0 | I109: 0 | J109: 0 | K109: 0 | L109: 0 | M109: 0 | N109: 0
A110: Vốn khác | C110: Owner's other capital | E110: 0 | F110: 1382700000 | G110: 0 | H110: 0 | I110: 1382700000 | J110: 1382700000 | K110: 1382700000 | L110: 1382700000 | M110: 1382700000 | N110: 1382700000
... A127: TỔNG CỘNG NGUỒN VỐN | C127: TOTAL RESOURCES | E127: 4420567058149 | F127: 5140761457358 | G127: 5171270660639 | H127: 5186553390197 | I127: 5334073124051 | J127: 6488631865645 | K127: 7311823905729 | L127: 7795129594538 | M127: 8212295180692 | N127: 8775088048296
A129: Backing test
A130: Tổng tài sản & nguồn vốn | C130: Total Asset or Resources | E130: =(E71-E127) -> 0 | F130: =(F71-F127) -> 0 | G130: =(G71-G127) -> 0 | H130: =(H71-H127) -> 0 | I130: =(I71-I127) -> 0 | J130: =(J71-J127) -> 0 | K130: =(K71-K127) -> 0 | L130: =(L71-L127) -> 0 | ... N130: =(N71-N127) -> 0
A131: Tài sản ngắn hạn | C131: Current asset | E131: =E6-E7-E10-E14-E23-E26 -> 0 | F131: =F6-F7-F10-F14-F23-F26 -> 0 | G131: =G6-G7-G10-G14-G23-G26 -> 0 | H131: =H6-H7-H10-H14-H23-H26 -> 0 | I131: =I6-I7-I10-I14-I23-I26 -> 0 | J131: =J6-J7-J10-J14-J23-J26 -> 0 | K131: =K6-K7-K10-K14-K23-K26 -> 0 | L131: =L6-L7-L10-L14-L23-L26 -> 0 | ... N131: =N6-N7-N10-N14-N23-N26 -> 0
A132: Tài sản dài hạn | C132: Non-Current asset | E132: =E32-E33-E41-E52-E55-E58-E64-E65 -> 0 | F132: =F32-F33-F41-F52-F55-F58-F64-F65 -> 0 | G132: =G32-G33-G41-G52-G55-G58-G64-G65 -> 0 | H132: =H32-H33-H41-H52-H55-H58-H64-H65 -> 0 | I132: =I32-I33-I41-I52-I55-I58-I64-I65 -> 0 | J132: =J32-J33-J41-J52-J55-J58-J64-J65 -> 0 | K132: =K32-K33-K41-K52-K55-K58-K64-K65 -> 0 | L132: =L32-L33-L41-L52-L55-L58-L64-L65 -> 0 | ... N132: =N32-N33-N41-N52-N55-N58-N64-N65 -> 0
A133: Tổng tài sản & nguồn vốn | C133: Total asset | E133: =E71-E32-E6 -> 0 | F133: =F71-F32-F6 -> 0 | G133: =G71-G32-G6 -> 0 | H133: =H71-H32-H6 -> 0 | I133: =I71-I32-I6 -> 0 | J133: =J71-J32-J6 -> 0 | K133: =K71-K32-K6 -> 0 | L133: =L71-L32-L6 -> 0 | ... N133: =N71-N32-N6 -> 0
A134: Nguồn vốn ngắn hạn | C134: Current liabilities | E134: =E73-SUM(E74:E87) -> 0 | F134: =F73-SUM(F74:F87) -> 0 | G134: =G73-SUM(G74:G87) -> 0 | H134: =H73-SUM(H74:H87) -> 0 | I134: =I73-SUM(I74:I87) -> 0 | J134: =J73-SUM(J74:J87) -> 0 | K134: =K73-SUM(K74:K87) -> 0 | L134: =L73-SUM(L74:L87) -> 0 | ... N134: =N73-SUM(N74:N87) -> 0
A135: Nguồn vốn dài hạn | C135: Non-Current liabilities | E135: =E88-SUM(E89:E102) -> 0 | F135: =F88-SUM(F89:F102) -> 0 | G135: =G88-SUM(G89:G102) -> 0 | H135: =H88-SUM(H89:H102) -> 0 | I135: =I88-SUM(I89:I102) -> 0 | J135: =J88-SUM(J89:J102) -> 0 | K135: =K88-SUM(K89:K102) -> 0 | L135: =L88-SUM(L89:L102) -> 0 | ... N135: =N88-SUM(N89:N102) -> 0
A136: Tổng nguồn vốn | C136: Total Liabilities | E136: =E72-E73-E88 -> 0 | F136: =F72-F73-F88 -> 0 | G136: =G72-G73-G88 -> 0 | H136: =H72-H73-H88 -> 0 | I136: =I72-I73-I88 -> 0 | J136: =J72-J73-J88 -> 0 | K136: =K72-K73-K88 -> 0 | L136: =L72-L73-L88 -> 0 | ... N136: =N72-N73-N88 -> 0

Sheet IP_IS Raw
A1: Income Statement | C1: Yearly
E2: ='IP_BS Raw'!E2 -> 2021 | F2: ='IP_BS Raw'!F2 -> 2022 | G2: ='IP_BS Raw'!G2 -> 2023 | H2: ='IP_BS Raw'!H2 -> 2024 | I2: ='IP_BS Raw'!I2 -> 2025
A3: Trạng thái kiểm toán | C3: Audit Status
A4: Công ty Kiểm toán | C4: Audit Firm
A5: Loại Ý kiến Kiểm toán | C5: Audit Opinion Type
A6: Doanh thu bán hàng và cung cấp dịch vụ | C6: Sales | E6: 1082183356214 | F6: 317854901716 | G6: 414366625633 | H6: 1026485549969 | I6: 1639453759799
A7: Các khoản giảm trừ doanh thu | C7: Sales deductions | E7: -2675562836 | F7: -3730595402 | G7: -2699840733 | H7: -390681797 | I7: -390681797
A8: Doanh thu thuần | C8: Net sales | E8: 1079507793378 | F8: 314124306314 | G8: 411666784900 | H8: 1026094868172 | I8: 1639063078002
A9: Giá vốn hàng bán | C9: Cost of sales | E9: -1045382703416 | F9: -209645620562 | G9: -296480952992 | H9: -855243703997 | I9: -1424028369399
A10: Lợi nhuận gộp về bán hàng và cung cấp dịch vụ | C10: Gross Profit | E10: 34125089962 | F10: 104478685752 | G10: 115185831908 | H10: 170851164175 | I10: 215034708603
A11: Doanh thu hoạt động tài chính | C11: Financial income | E11: 423849348595 | F11: 47340388199 | G11: 43586401680 | H11: 191906506913 | I11: 120349183176
A12: Chi phí tài chính | C12: Financial expenses | E12: -28037984463 | F12: -9021747176 | G12: -23482415579 | H12: -51108323960 | I12: -27197709414
A13: Trong đó: Chi phí lãi vay | C13: In which: interest expenses | E13: -21801000846 | F13: -6906877175 | G13: -21505000199 | H13: -28208427529 | I13: -25900554619
A14: Lãi/(lỗ) từ công ty liên doanh | C14: Gain/(loss) from joint ventures | E14: 436847500 | F14: 505897455 | G14: -4853955053 | H14: -15223546244 | I14: -1456928964
A15: Chi phí bán hàng | C15: Selling expenses | E15: -86766850424 | F15: -20658752305 | G15: -14260496293 | H15: -26239808550 | I15: -39335239608
A16: Chi phí quản lý doanh nghiệp | C16: General and admin expenses | E16: -211115902487 | F16: -93384172422 | G16: -66900478155 | H16: -151633232794 | I16: -167762629718
A17: Lãi/(lỗ) từ hoạt động kinh doanh | C17: Operating profit/(loss) | E17: 132490548683 | F17: 29260299503 | G17: 49274888508 | H17: 118552759540 | I17: 99631384075
... A20: Chi phí khác | C20: Other expenses | E20: -34656844781 | F20: -19441769061 | G20: -22149929089 | H20: -9003540240 | I20: -5455043465
A21: Lãi/(lỗ) từ công ty liên doanh | C21: Income from investments in other entities
A22: Lãi/(lỗ) ròng trước thuế | C22: Net accounting profit/(loss) before tax | E22: 98316716307 | F22: 28915008361 | G22: 28924117934 | H22: 110622543863 | I22: 94679495741
A23: Chi phí thuế thu nhập doanh nghiệp | C23: Corporate income tax expenses | E23: -68326484945 | F23: -4024148047 | G23: -2405158607 | H23: 11951746732 | I23: -17278295298
A24: Thuế thu nhập doanh nghiệp – hiện thời | C24: Business income tax - current | E24: -38377310844 | F24: -6456274449 | G24: 1545560455 | H24: -12081916503 | I24: -7059602748
A25: Thuế thu nhập doanh nghiệp – hoãn lại | C25: Business income tax - deferred | E25: -29949174101 | F25: 2432126402 | G25: -3950719062 | H25: 24033663235 | I25: -10218692550
A26: Lãi/(lỗ) thuần sau thuế | C26: Net profit/(loss) after tax | E26: 29990231362 | F26: 24890860314 | G26: 26518959327 | H26: 122574290595 | I26: 77401200443
A27: Lợi ích của cổ đông thiểu số | C27: Minority interests | E27: 140197129432 | F27: 13986873201 | G27: -339748836 | H27: -3133772972 | I27: 839269032
A28: Lợi nhuận của Cổ đông của Công ty mẹ | C28: Attributable to parent company | E28: 19793101930 | F28: 10903987113 | G28: 26858708163 | H28: 125708063567 | I28: 76561931411
A29: Lãi cơ bản trên cổ phiếu (VND) | C29: EPS basic (VND) | E29: =E28/(IPc_Others!$G$50*1000000) -> 103.19547 | F29: =F28/(IPc_Others!$G$50*1000000) -> 56.850216 | G29: =G28/(IPc_Others!$G$50*1000000) -> 140.03349 | H29: =H28/(IPc_Others!$G$50*1000000) -> 655.40526 | I29: =I28/(IPc_Others!$G$50*1000000) -> 399.17163
A30: Lãi trên cổ phiếu pha loãng (VND) | C30: EPS diluted (VND) | E30: =E29 -> 103.19547 | F30: =F29 -> 56.850216 | G30: =G29 -> 140.03349 | H30: =H29 -> 655.40526 | I30: =I29 -> 399.17163
A32: Backing test
A33: Lợi nhuận ròng | C33: Gross profit | E33: =E6+E7+E9-E10 -> 0 | F33: =F6+F7+F9-F10 -> 0 | G33: =G6+G7+G9-G10 -> 0 | H33: =H6+H7+H9-H10 -> 0 | I33: =I6+I7+I9-I10 -> 0
A34: Lợi nhuận khác | C34: Other gain | E34: =E18-E19-E20 -> 0 | F34: =F18-F19-F20 -> 0 | G34: =G18-G19-G20 -> 0 | H34: =H18-H19-H20 -> 0 | I34: =I18-I19-I20 -> 0
A35: Lợi nhuận trước thuế | C35: Earning before tax | E35: =E10+E11+E14+E15+E16+E18+E12-E22 -> 0 | F35: =F10+F11+F14+F15+F16+F18+F12-F22 -> 0 | G35: =G10+G11+G14+G15+G16+G18+G12-G22 -> 0 | H35: =H10+H11+H14+H15+H16+H18+H12-H22 -> 0 | I35: =I10+I11+I14+I15+I16+I18+I12-I22 -> 0
A36: Chi phí thuế TNDN | C36: Tax expenses | E36: =E24+E25-E23 -> 0 | F36: =F24+F25-F23 -> 0 | G36: =G24+G25-G23 -> 0 | H36: =H24+H25-H23 -> 0 | I36: =I24+I25-I23 -> 0
A37: Lợi nhuận sau thuế | C37: Eearning after tax | E37: =E22+E23-E26 -> 0 | F37: =F22+F23-F26 -> 0 | G37: =G22+G23-G26 -> 0 | H37: =H22+H23-H26 -> 0 | I37: =I22+I23-I26 -> 0

Sheet IP_CF Raw
A1: Cashflow statement | C1: Yearly
E2: ='IP_BS Raw'!E2 -> 2021 | F2: ='IP_BS Raw'!F2 -> 2022 | G2: ='IP_BS Raw'!G2 -> 2023 | H2: ='IP_BS Raw'!H2 -> 2024 | I2: ='IP_BS Raw'!I2 -> 2025
A3: Trạng thái kiểm toán | C3: Audit Status
A4: Công ty Kiểm toán | C4: Audit Firm
A5: Loại Ý kiến Kiểm toán | C5: Audit Opinion Type
A6: Lợi nhuận/(lỗ) trước thuế | C6: Net profit/(loss) before tax | E6: 98316716307 | F6: 28915008361 | G6: 28924117934 | H6: 110622543863 | I6: 94679495741
A7: Khấu hao TSCĐ, BĐSĐT và phân bổ lợi thế thương mại | C7: Depreciation, amortization and goodwill amortization | E7: 60873843139 | F7: 11001224837 | G7: 12939753078 | H7: 54824557578 | I7: 83639088776
A8: Chi phí dự phòng | C8: Provisions | E8: 52061632930 | F8: 31178258773 | G8: -18008135174 | H8: 16612904416 | I8: 4165257188
A9: Lãi/lỗ chênh lệch tỷ giá hối đoái do đánh giá lại các khoản mục tiền tệ có gốc ngoại tệ | C9: Unrealized foreign exchange gain/(loss) | E9: 158090446 | F9: 28453361
A10: Lãi/(lỗ) từ thanh lý tài sản cố định | C10: Profit/loss from liquidating fixed assets
A11: (Lãi)/lỗ từ hoạt động đầu tư | C11: Profit/loss from investing activities | E11: -417635142186 | F11: -53646900130 | G11: -27299492204 | H11: -155697273093 | I11: -115880067890
A12: Chi phí lãi vay | C12: Interest expense | E12: 21801000846 | F12: 6906877175 | G12: 21505000199 | H12: 28208427529 | I12: 25900554619
A13: Thu lãi và cổ tức | C13: Interest income and dividend
A14: Các khoản điều chỉnh khác | C14: Other adjustments
A15: Lợi nhuận/(lỗ) từ hoạt động kinh doanh trước những thay đổi vốn lưu động | C15: Operating profit/(loss) before changes in Working Capital | E15: -184423858518 | F15: 24382922377 | G15: 18061243833 | H15: 54571160293 | I15: 92504328434
A16: (Tăng)/giảm các khoản phải thu | C16: (Increase)/decrease in receivables | E16: 57022448497 | F16: -152533901863 | G16: -228497578408 | H16: -84686670798 | I16: -22437035213
A17: (Tăng)/giảm hàng tồn kho | C17: (Increase)/decrease in inventories | E17: 33631958809 | F17: 41310624943 | G17: 11742694895 | H17: -57188071887 | I17: -61641565169
A18: Tăng/(giảm) các khoản phải trả | C18: Increase/(decrease) in payables | E18: -84795032317 | F18: -48903797346 | G18: 59812819534 | H18: 419591062933 | I18: 22306828509
A19: (Tăng)/giảm chi phí trả trước | C19: (Increase)/decrease in prepaid expenses | E19: 114913464323 | F19: -6095619097 | G19: -20742237026 | H19: 43291436246 | I19: 21618297007
A20: (Tăng)/giảm chứng khoán kinh doanh | C20: (Increase)/decrease in trading securities
A21: Tiền lãi vay đã trả | C21: Interest paid | E21: -12842860526 | F21: -12387461394 | G21: -21496776942 | H21: -16714808252 | I21: -36916434814
A22: Thuế thu nhập doanh nghiệp đã nộp | C22: Corporate Income Tax paid | E22: -11906493786 | F22: -11091647373 | G22: -11349753635 | H22: -1436256929 | I22: -8068991896
A23: Tiền thu khác từ hoạt động kinh doanh | C23: Other receipts from operating activities
A24: Tiền chi khác cho hoạt động kinh doanh | C24: Other payments on operating activities
A25: Lưu chuyển tiền tệ ròng từ các hoạt động sản xuất kinh doanh | C25: Net cash inflows/(outflows) from operating activities | E25: -88400373518 | F25: -165318879753 | G25: -192469587749 | H25: 357427851606 | I25: 7365426858
A26: Lưu chuyển tiền thuần từ hoạt động đầu tư | C26: Net cash inflows/(outflows) from investing activities | E26: 11187918086 | F26: 293110077155 | G26: -397144764339 | H26: -613628111128 | I26: -192800335481
A27: Tiền chi để mua sắm, xây dựng TSCĐ và các tài sản dài hạn khác | C27: Purchases of fixed assets and other long term assets | E27: -2911894836 | F27: -262090909 | G27: -85145283539 | H27: -552939817718 | I27: -98219383903
A28: Tiền thu từ thanh lý, nhượng bán TSCĐ và các tài sản dài hạn khác | C28: Proceeds from disposal of fixed assets | E28: 386363636 | F28: 9922527548 | G28: 1818413608 | I28: 5000000000
A29: Tiền chi cho vay, mua các công cụ nợ của đơn vị khác | C29: Loans granted, purchases of debt instruments | E29: -1360000000 | F29: -201466970449 | G29: -146568497700 | H29: -235919838301 | I29: -824373768000
A30: Tiền thu hồi cho vay, bán lại các công cụ nợ của đơn vị khác | C30: Collection of loans, proceeds from sales of debts instruments | E30: 17850000000 | F30: 63856855073 | G30: 119157887885 | H30: 164175766640 | I30: 625589460018
A31: Tiền chi đầu tư góp vốn vào đơn vị khác | C31: Investments in other entities | E31: -10699782467 | F31: -62822640694 | G31: -343361250000 | H31: -205721247708 | I31: -65678431605
A32: Tiền thu hồi đầu tư góp vốn vào đơn vị khác | C32: Proceeds from divestment in other entities | E32: 6624547167 | F32: 438675501792 | G32: 37231370000 | H32: 204627695591 | I32: 118927369388
A33: Tiền thu lãi cho vay, cổ tức và lợi nhuận được chia | C33: Dividends and interest received | E33: 1298684586 | F33: 45206894794 | G33: 19722595407 | H33: 12149330368 | I33: 45954418621
A34: Lưu chuyển tiền thuần từ hoạt động tài chính | C34: Net cash inflows/(outflows) from financing activities | E34: 45121186034 | F34: -105639409412 | G34: 571602677581 | H34: 383974994343 | I34: 337710824236
A35: Tiền thu từ phát hành cổ phiếu, nhận vốn góp của chủ sở hữu | C35: Proceeds from issue of shares | G35: 450000000000 | H35: 1767608500 | I35: 548175451265
A36: Tiền chi trả vốn góp cho các chủ sở hữu, mua lại cổ phiếu của doanh nghiệp đã phát hành | C36: Payments for share returns and repurchases
A37: Tiền thu được các khoản đi vay | C37: Proceeds from loans | E37: 230230900461 | F37: 132137409754 | G37: 564918510949 | H37: 634594718729 | I37: 492421816680
A38: Tiền trả nợ gốc vay | C38: Repayment of loans | E38: -185109714427 | F38: -237776819166 | G38: -443315833368 | H38: -252387332886 | I38: -701603005309
A39: Tiền trả nợ gốc thuê tài chính | C39: Finance lease principal payments
A40: Cổ tức, lợi nhuận đã trả cho chủ sở hữu | C40: Dividends paid | I40: -1283438400
A41: Tiền lãi đã nhận | C41: Interests, dividends, profits received
A42: Lưu chuyển tiền thuần trong kỳ | C42: Net increase in cash and cash equivalents | E42: -32091269398 | F42: 22151787990 | G42: -18011674507 | H42: 127774734821 | I42: 152275915613
A43: Tiền và tương đương tiền đầu kỳ | C43: Cash and cash equivalents at the beginning o period | E43: 36412495272 | F43: 4321225874 | G43: 26473013864 | H43: 8461339357 | I43: 136236074178
A44: Ảnh hưởng của thay đổi tỷ giá hối đoái quy đổi ngoại tệ | C44: Effect of foreign exchange differences | I44: 12191451
A45: Tiền và tương đương tiền cuối kỳ | C45: Cash and cash equivalents at the end of period | E45: 4321225874 | F45: 26473013864 | G45: 8461339357 | H45: 136236074178 | I45: 288524181242
A47: Backing test
A48: Dòng tiền hoạt động trước vốn lưu động | C48: CFO before Working capital | E48: =E15-(E6+SUM(E7:E14)) -> 0 | F48: =F15-(F6+SUM(F7:F14)) -> 0 | G48: =G15-(G6+SUM(G7:G14)) -> 0 | H48: =H15-(H6+SUM(H7:H14)) -> 0 | I48: =I15-(I6+SUM(I7:I14)) -> 0
A49: Dòng tiền hoạt động | C49: Cash Flow of Operation | E49: =E15+SUM(E16:E24)-E25 -> 0 | F49: =F15+SUM(F16:F24)-F25 -> 0 | G49: =G15+SUM(G16:G24)-G25 -> 0 | H49: =H15+SUM(H16:H24)-H25 -> 0 | I49: =I15+SUM(I16:I24)-I25 -> 0
A50: Dòng tiền đầu tư | C50: Cash Flow of Investment | E50: =E26-SUM(E27:E33) -> 0 | F50: =F26-SUM(F27:F33) -> 0 | G50: =G26-SUM(G27:G33) -> 0 | H50: =H26-SUM(H27:H33) -> 0 | I50: =I26-SUM(I27:I33) -> 0
A51: Dòng tiền tài chính | C51: Cash Flow of Financial | E51: =E34-SUM(E35:E41) -> 0 | F51: =F34-SUM(F35:F41) -> 0 | G51: =G34-SUM(G35:G41) -> 0 | H51: =H34-SUM(H35:H41) -> 0 | I51: =I34-SUM(I35:I41) -> 0
A52: Dòng tiền ròng | C52: Net cash flow | E52: =E25+E26+E34-E42 -> 0 | F52: =F25+F26+F34-F42 -> 0 | G52: =G25+G26+G34-G42 -> 0 | H52: =H25+H26+H34-H42 -> 0 | I52: =I25+I26+I34-I42 -> 0
A53: Tiền và các khoản tương đương tiền | C53: Cash and cash equivalent | E53: =E43+E42+E44-E45 -> 0 | F53: =F43+F42+F44-F45 -> 0 | G53: =G43+G42+G44-G45 -> 0 | H53: =H43+H42+H44-H45 -> 0 | I53: =I43+I42+I44-I45 -> 0

Sheet IP_Notes Raw
A1: Financial Notes | C1: Yearly
E2: ='IP_BS Raw'!E2 -> 2021 | F2: ='IP_BS Raw'!F2 -> 2022 | G2: ='IP_BS Raw'!G2 -> 2023 | H2: ='IP_BS Raw'!H2 -> 2024 | I2: ='IP_BS Raw'!I2 -> 2025
A3: Trạng thái kiểm toán | C3: Audit Status
A4: Công ty Kiểm toán | C4: Audit Firm | E4: PWC | F4: PWC | G4: PWC | H4: PWC | I4: PWC
A5: Loại Ý kiến Kiểm toán | C5: Audit Opinion Type
A6: Tiền và tương đương tiền | C6: Cash and cash equivalents | E6: =SUM(E7:E10) -> 1013594183927 | F6: =SUM(F7:F10) -> 360383344706 | G6: =SUM(G7:G10) -> 370506274358 | H6: =SUM(H7:H10) -> 546631384396
A7: Tiền mặt | C7: Cash on hand | E7: 3244275331 | F7: 1920102424 | G7: 2716321651 | H7: 2254810590
A8: Tiền gửi Ngân hàng | C8: Cash in banks | E8: 648427921167 | F8: 78670488857 | G8: 132889952707 | H8: 337856573806
A9: Tiền đang chuyển | C9: Cash in transit
A10: Tiền và tương đương tiền | C10: Cash equivalents | E10: 361921987429 | F10: 279792753425 | G10: 234900000000 | H10: 206520000000
A11: Đầu tư tài chính NH | C11: Short-term investments | E11: =SUM(E12:E17) -> 605103106257 | F11: =SUM(F12:F17) -> 726047961971 | G11: =SUM(G12:G17) -> 1895233763147 | H11: =SUM(H12:H17) -> 1565695561055
A12: Chứng khoán đầu tư ngắn hạn | C12: Short-term securities investments | E12: 0 | F12: 0 | G12: 0 | H12: 546648172508
A13: Đầu tư nắm giữ đến ngày đáo hạn | C13: Held-to-maturity investment | E13: 98700000000 | F13: 239367439500 | G13: 425016299943 | H13: 285750000000
A14: Đầu tư ngắn hạn | C14: Short-term | E14: 0 | F14: 0 | G14: 0 | H14: 0
A15: Đầu tư dài hạn | C15: Long-term | E15: 506248106257 | F15: 486525522471 | G15: 1470062463204 | H15: 759207263714
A16: Đầu tư góp vốn vào đơn vị khác | C16: Other short-term investments | E16: 155000000 | F16: 155000000 | G16: 155000000 | H16: 155000000
A17: Dự phòng giảm giá ĐTNH | C17: Provision for diminution in value of short-term investments | E17: 0 | F17: 0 | G17: 0 | H17: -26064875167
A18: Phải thu ngắn hạn khác | C18: Other Receivables | E18: =SUM(E19:E22) -> 230385593342 | F18: =SUM(F19:F22) -> 552878196157 | G18: =SUM(G19:G22) -> 452823464628 | H18: =SUM(H19:H22) -> 339817693240
A19: Phải thu ngắn hạn của khách hàng | C19: Receivables from customers | E19: 210870194878 | F19: 188497724901 | G19: 205263011710 | H19: 236744183566
A20: Phải thu về cổ tức và lợi nhuận được chia | C20: Interest income | E20: 0 | F20: 0 | G20: 0 | H20: 0
A21: Phải thu người lao động | C21: Receivable from employees | E21: 0 | F21: 0 | G21: 0 | H21: 0
A22: Phải thu khác | C22: Other receivables | E22: 19515398464 | F22: 364380471256 | G22: 247560452918 | H22: 103073509674
A23: Hàng tồn kho | C23: INVENTORIES | E23: =SUM(E24:E32) -> 21111762403 | F23: =SUM(F24:F32) -> 28028085828 | G23: =SUM(G24:G32) -> 29065056002 | H23: =SUM(H24:H32) -> 47470252892
A24: Hàng mua đang đi đường | C24: Goods in transit
A25: Nguyên liệu, vật liệu | C25: Raw materials | E25: 1625309134 | F25: 1213108434 | G25: 3078477109 | H25: 4645504999
A26: Công cụ, dụng cụ | C26: Tools and supplies | E26: 18206378530 | F26: 26814977394 | G26: 25921243401 | H26: 40545685394
A27: Chi phí SX, KD dở dang | C27: Work in progress
A28: Thành phẩm | C28: Finished goods
A29: Hàng hóa | C29: Merchandise inventories | E29: 1280074739 | G29: 65335492 | H29: 2279062499
A30: Hàng gửi đi bán | C30: Goods on consignment
A31: Hàng hoá kho bảo thuế | C31: Goods in bonded warehouses
A32: Hàng hoá bất động sản | C32: Property
A33: Tài sản ngắn hạn khác | C33: Other current assets | E33: =SUM(E34:E37) -> 76753394195 | F33: =SUM(F34:F37) -> 43834422724 | G33: =SUM(G34:G37) -> 57164184694 | H33: =SUM(H34:H37) -> 56247437211
A34: Tạm ứng | C34: Advances | E34: 22926052350 | F34: 43834422724 | G34: 20161906312 | H34: =17693351014 -> 17693351014
A35: Tài sản thiếu chờ xử lý | C35: Lack of assets awaiting handling
A36: Cầm cố, ký quỹ, ký cược NH | C36: Short-term deposits or collateral
A37: Khác | C37: Other | E37: =52585960594+1241381251 -> 53827341845 | G37: =35389709327+1612569055 -> 37002278382 | H37: =35639643041+2914443156 -> 38554086197
A38: Phải thu dài hạn khác | C38: Other long-term receivables | E38: =SUM(E39:E42) -> 2333534000 | F38: =SUM(F39:F42) -> 827194723552 | G38: =SUM(G39:G42) -> 827194723552 | H38: =SUM(H39:H42) -> 3624576352
A39: Ký quỹ, ký cược dài hạn | C39: Long-term deposits or collateral
A40: Các khoản tiền nhận ủy thác | C40: Sums received in Trust
A41: Cho vay không có lãi | C41: Loans without interest
A42: Phải thu dài hạn khác | C42: Others | E42: 2333534000 | F42: 827194723552 | G42: 827194723552 | H42: 3624576352
A43: Nguyên giá TSCĐHH | C43: Tangible fixed assets - Historical Cost | E43: =SUM(E44:E46) -> 2306605647588 | F43: =SUM(F44:F46) -> 2545081398487 | G43: =SUM(G44:G46) -> 2556974350993 | H43: =SUM(H44:H46) -> 4195839269027
A44: Nguyên giá đầu kỳ | C44: Opening Balance | E44: 2247137762457 | F44: 2306605647588 | G44: 2545081398487 | H44: 2556974350993
A45: Tăng trong kỳ | C45: Additions | E45: 90002761955 | F45: =127894097599+127226891567 -> 255120989166 | G45: =17230947818+323439104 -> 17554386922 | H45: =13326958630+1629031022110 -> 1642357980740
A46: Giảm trong kỳ | C46: Decreases | E46: -30534876824 | F46: =-(3017830200+13627408067) -> -16645238267 | G46: -5661434416 | H46: -3493062706
A47: Hao mòn TSCĐHH | C47: Tangible fixed assets - Accumulated depreciation | E47: =SUM(E48:E50) -> 1502119297270 | F47: =SUM(F48:F50) -> 1736585742333 | G47: =SUM(G48:G50) -> 1924198134937 | H47: =SUM(H48:H50) -> 2848393105604
A48: Đầu kỳ | C48: Opening Balance | E48: 1332930506854 | F48: 1502119297270 | G48: 1736585742333 | H48: 1924198134937
A49: Tăng trong kỳ | C49: Additions | E49: 199419138916 | F49: =200722380760+43758161773 -> 244480542533 | G49: =193013451524 -> 193013451524 | H49: =194136380679+731583987955 -> 925720368634
A50: Giảm trong kỳ | C50: Decreases | E50: -30230348500 | F50: -10014097470 | G50: -5401058920 | H50: -1525397967
A51: Nguyên giá TSCĐ TTC | C51: Finance lease assets - Historical Cost | E51: =SUM(E52:E54) -> 0 | F51: =SUM(F52:F54) -> 0 | G51: =SUM(G52:G54) -> 0 | H51: =SUM(H52:H54) -> 0
A52: Nguyên giá đầu kỳ | C52: Opening Balance | E52: 0 | F52: 0 | G52: 0 | H52: 0
A53: Tăng trong kỳ | C53: Additions | E53: 0 | F53: 0 | G53: 0 | H53: 0
A54: Giảm trong kỳ | C54: Decreases | E54: 0 | F54: 0 | G54: 0 | H54: 0
A55: Hao mòn TSCĐ TTC | C55: Finance lease assets - Accumulated depreciation | E55: =SUM(E56:E58) -> 0 | F55: =SUM(F56:F58) -> 0 | G55: =SUM(G56:G58) -> 0 | H55: =SUM(H56:H58) -> 0
A56: Đầu kỳ | C56: Opening Balance | E56: 0 | F56: 0 | G56: 0 | H56: 0
A57: Tăng trong kỳ | C57: Additions | E57: 0 | F57: 0 | G57: 0 | H57: 0
A58: Giảm trong kỳ | C58: Decreases | E58: 0 | F58: 0 | G58: 0 | H58: 0
A59: Nguyên giá TSCĐVH | C59: Intangible fixed assets - Historical Cost | E59: =SUM(E60:E62) -> 21363168750 | F59: =SUM(F60:F62) -> 21654078750 | G59: =SUM(G60:G62) -> 22239958750 | H59: =SUM(H60:H62) -> 2320997600260
A60: Nguyên giá đầu kỳ | C60: Opening Balance | E60: 21436478750 | F60: 21363168750 | G60: 21654078750 | H60: 22239958750
A61: Tăng trong kỳ | C61: Additions | E61: 30000000 | F61: 290910000 | G61: 585880000 | H61: =1937460000+2296820181510 -> 2298757641510
A62: Giảm trong kỳ | C62: Decreases | E62: -103310000
A63: Hao mòn TSCĐVH | C63: Intangible fixed assets - Accumulated amortization | E63: =SUM(E64:E66) -> 14969908208 | F63: =SUM(F64:F66) -> 15774049504 | G63: =SUM(G64:G66) -> 16128123425 | H63: =SUM(H64:H66) -> 61488328794
A64: Đầu kỳ | C64: Opening Balance | E64: 14057999858 | F64: 14969908208 | G64: 15774049504 | H64: 16128123425
A65: Tăng trong kỳ | C65: Additions | E65: 1015218350 | F65: 804141296 | G65: 354073921 | H65: =37797999607+7562205762 -> 45360205369
A66: Giảm trong kỳ | C66: Decreases | E66: -103310000
A67: Đầu tư dài hạn khác | C67: Other long-term investments | E67: =SUM(E68:E72) -> 0 | F67: =SUM(F68:F72) -> 0 | G67: =SUM(G68:G72) -> 0 | H67: =SUM(H68:H72) -> 0
A68: Đầu tư cổ phiếu | C68: Investment in securities
A69: Đầu tư trái phiếu | C69: Investment in bond
A70: Đầu tư tín phiếu, kỳ phiếu | C70: Investments in bills of exchange, treasury bonds
A71: Cho vay dài hạn | C71: Long-term loans
A72: Đầu tư dài hạn khác | C72: Other long-term investments
A73: Vay và nợ ngắn hạn | C73: Short-term loans and liabilities | E73: =SUM(E74:E75) -> 0 | F73: =SUM(F74:F75) -> 208400000000 | G73: =SUM(G74:G75) -> 124986247447 | H73: =SUM(H74:H75) -> 343148948275
A74: Vay ngắn hạn | C74: Short-term loans | F74: 208400000000 | G74: 118835910443 | H74: 299753683804
A75: Vay dài hạn đến hạn trả | C75: Long-term liabilities falling due | G75: 6150337004 | H75: 43395264471
A76: Giá gốc Lợi thế thương mại | C76: Good will - Historical Cost | E76: =SUM(E77:E79) -> 0 | F76: =SUM(F77:F79) -> 4394353039 | G76: =SUM(G77:G79) -> 5294942838 | H76: =SUM(H77:H79) -> 472489016569
A77: Số dư đầu kỳ | C77: Opening Balance | E77: 0 | F77: 4394353039 | G77: 4394353039 | H77: 5294942838
A78: Tăng trong kỳ | C78: Additions | E78: 0 | F78: 0 | G78: 900589799 | H78: 467194073731
A79: Giảm trong kỳ | C79: Decreases | E79: 0 | F79: 0 | G79: 0 | H79: 0
A80: Phân bổ Lũy kế | C80: Good will - Accumulated depreciation | E80: =SUM(E81:E83) -> 0 | F80: =SUM(F81:F83) -> 221523550 | G80: =SUM(G81:G83) -> 725575162 | H80: =SUM(H81:H83) -> 22444746014
A81: Số dư dầu kỳ | C81: Opening Balance | E81: 0 | F81: 221523550 | G81: 221523550 | H81: 725575162
A82: Tăng trong kỳ | C82: Additions | E82: 0 | F82: 0 | G82: 504051612 | H82: 21719170852
A83: Giảm trong kỳ | C83: Decreases | E83: 0 | F83: 0 | G83: 0 | H83: 0
A84: Các khoản phải trả về Thuế | C84: Taxes payable | E84: =SUM(E85:E93) -> 24917570748 | F84: =SUM(F85:F93) -> 24409235577 | G84: =SUM(G85:G93) -> 29317673914 | H84: =SUM(H85:H93) -> 47069114487
A85: Thuế GTGT | C85: Value added tax | E85: 3266188982 | F85: 2036390448 | G85: 3938447162 | H85: 4238320541
A86: Thuế TTĐB | C86: Special Sales Tax (SST)
A87: Thuế XNK | C87: Import-Export tax
A88: Thuế TNDN | C88: Corporate income Tax | E88: 18499730099 | F88: 17661847636 | G88: 21994703344 | H88: 34710371835
A89: Thuế TNCN | C89: Personal Income Tax | E89: 1784325547 | F89: 4710997493 | G89: 3383952071 | H89: 8119850774
A90: Thuế Tài nguyên | C90: Natural Resources Tax
A91: Thuế nhà đất và tiền thuê đất | C91: Housing and land Tax, and land rental
A92: Các loại thuế khác | C92: Other taxes | E92: 1367326120 | G92: 571337 | H92: 571337
A93: Các khoản phí, lệ phí khác | C93: Other fees, charges | E93: 0 | F93: 0 | G93: 0 | H93: 0
A94: Chi phí phải trả | C94: Expenses payable | E94: =SUM(E95:E98) -> 0 | F94: =SUM(F95:F98) -> 0 | G94: =SUM(G95:G98) -> 0 | H94: =SUM(H95:H98) -> 0
A95: Trích trước CP lương nghỉ phép | C95: Advances on salary during the period of taking leave
A96: Chi phí SCL TSCĐ | C96: Expenses for major repair to fixed assets
A97: Chi phí trong thời gian ngừng KD | C97: Expenses during the period of cessation of business activities
A98: Khác | C98: Others
A99: Phải trả phải nộp khác | C99: Other Payables | E99: =SUM(E100:E108) -> 627459338566 | F99: =SUM(F100:F108) -> 55625319941 | G99: =SUM(G100:G108) -> 14271499464 | H99: =SUM(H100:H108) -> 19916673963
A100: Tài sản thừa chờ XL | C100: Surplus assets awaiting handling
...

Sheet IPc_Others
B1: Others Data | C1: YEG VN Equity | D1: =DATE(D2,12,31) -> 44561 | E1: =DATE(E2,12,31) -> 44926 | F1: =DATE(F2,12,29) -> 45289 | G1: =DATE(G2,12,31) -> 45657 | H1: =TODAY()-1 -> 46137 | I1: 12 | J1: 13 | K1: 14 | L1: 15 | M1: 16 | N1: 17 | Q1: Cơ cấu sở hữu & công ty con — YEG
C2: Fields (If Any) | D2: ='IP_BS Raw'!E2 -> 2021 | E2: ='IP_BS Raw'!F2 -> 2022 | F2: ='IP_BS Raw'!G2 -> 2023 | G2: ='IP_BS Raw'!H2 -> 2024 | H2: ='IP_BS Raw'!I2 -> 2025 | I2: =H2+1 -> 2026 | J2: =I2+1 -> 2027 | K2: =J2+1 -> 2028 | L2: =K2+1 -> 2029 | M2: =L2+1 -> 2030 | N2: =M2+1 -> 2031
B3: 1. Market Data | Q3: 1. Cơ cấu sở hữu (Top shareholders)
B4: Market Price (VND) | C4: PX_LAST | D4: 17070 | E4: 13470 | F4: 14160 | G4: 12340 | H4: 9990 | Q4: Cổ đông | R4: Tỷ lệ (%)
B5: 52-Week high (VND) | C5: HIGH_52WEEK | Q5: PYN Elite Fund (Non-Ucits) | R5: 0.0894
B6: 52-Week low (VND) | C6: LOW_52WEEK | Q6: Lê Phương Thảo | R6: 0.0576
B7: 6M avg. daily turnover (VND bn) | C7: 180_DAY_AVERAGE_TURNOVER_AT_TIME | Q7: Chế Đoàn Viên | R7: 0.0499
B8: Shares outstanding (Mil Shares) | C8: EQY_SH_OUT | D8: =D46/1000000 -> 31.279968 | E8: =E46/1000000 -> 31.279968 | F8: =F46/1000000 -> 131.35326 | G8: =G46/1000000 -> 137.00145 | H8: =H46/1000000 -> 191.80203 | I8: =I46/1000000 -> 191.80203 | J8: =J46/1000000 -> 191.80203 | K8: =K46/1000000 -> 191.80203 | ... N8: =N46/1000000 -> 191.80203 | Q8: Nguyễn Viết Cường | R8: 0.0476
B9: Market cap (Mil VND mn) | C9: CUR_MKT_CAP | D9: =D4*D8 -> 533949.05 | E9: =E4*E8 -> 421341.17 | F9: =F4*F8 -> 1859962.2 | G9: =G4*G8 -> 1690597.9 | H9: =H4*H8 -> 1916102.3 | Q9: Đào Phúc Trí | R9: 0.044
B10: State ownership (%) | H10: =1-78.07% -> 0.2193 | Q10: Ancla Asset Limited | R10: 0.043
B11: Foreign ownership (%) | H11: 0.0431 | Q11: Ancla Assets Limited | R11: 0.0324
B12: Free float ratio (%) | C12: EQY_FREE_FLOAT_PCT | Q12: Phạm Minh Tiến | R12: 0.0217
B13: USDVND Curncy | C13: PX_LAST | D13: 23098 | E13: 22826 | F13: 23633 | G13: 24269 | H13: 26526 | Q13: Khác | R13: 0.5839
Q14: Tổng | R14: =SUM(R5:R13) -> 0.9695
B15: 2. Welfare & Dividends
B16: Consolidated Net income | D16: ='IP_IS Raw'!E26 -> 29990231362 | E16: ='IP_IS Raw'!F26 -> 24890860314 | F16: ='IP_IS Raw'!G26 -> 26518959327 | G16: ='IP_IS Raw'!H26 -> 122574290595 | H16: ='IP_IS Raw'!I26 -> 77401200443 | Q16: Phân loại theo quốc tịch
B17: Parent company's Net income | D17: ='IP_IS Raw'!E28 -> 19793101930 | E17: ='IP_IS Raw'!F28 -> 10903987113 | F17: ='IP_IS Raw'!G28 -> 26858708163 | G17: ='IP_IS Raw'!H28 -> 125708063567 | H17: ='IP_IS Raw'!I28 -> 76561931411 | I17: =OD_IS!I21 -> 8.0780515e+10 | J17: =OD_IS!J21 -> 1.0931595e+11 | K17: =OD_IS!K21 -> 1.6130703e+11 | L17: =OD_IS!L21 -> 2.2748232e+11 | M17: =OD_IS!M21 -> 2.85354e+11 | N17: =OD_IS!N21 -> 3.0112271e+11 | Q17: Sở hữu nước ngoài | R17: 0.1227
B18: Appropriation of reserves | D18: =D19+D23 -> 0 | E18: =E19+E23 -> 0 | F18: =F19+F23 -> 0 | G18: =G19+G23 -> 0 | H18: =H19+H23 -> 0 | I18: =I19+I23 -> 0 | J18: =J19+J23 -> 0 | K18: =K19+K23 -> 0 | ... N18: =N19+N23 -> 0 | Q18: Sở hữu khác (trong nước) | R18: 0.8773
B19: Fund inside | D19: =SUM(D20:D22) -> 0 | E19: =SUM(E20:E22) -> 0 | F19: =SUM(F20:F22) -> 0 | G19: =SUM(G20:G22) -> 0 | H19: =SUM(H20:H22) -> 0 | I19: 0 | J19: 0 | K19: 0 | L19: 0 | M19: 0 | N19: 0 | Q19: Tổng | R19: =SUM(R17:R18) -> 1
B20: Investment and development funds | D20: ='IP_BS Raw'!E114 -> 0 | E20: ='IP_BS Raw'!F114 -> 0 | F20: ='IP_BS Raw'!G114 -> 0 | G20: ='IP_BS Raw'!H114 -> 0 | H20: ='IP_BS Raw'!I114 -> 0
B21: Financial reserve funds | D21: ='IP_BS Raw'!E116 -> 0 | E21: ='IP_BS Raw'!F116 -> 0 | F21: ='IP_BS Raw'!G116 -> 0 | G21: ='IP_BS Raw'!H116 -> 0 | H21: ='IP_BS Raw'!I116 -> 0
B22: Other funds | D22: ='IP_BS Raw'!E117+'IP_BS Raw'!E115 -> 0 | E22: ='IP_BS Raw'!F117+'IP_BS Raw'!F115 -> 0 | F22: ='IP_BS Raw'!G117+'IP_BS Raw'!G115 -> 0 | G22: ='IP_BS Raw'!H117+'IP_BS Raw'!H115 -> 0 | H22: ='IP_BS Raw'!I117+'IP_BS Raw'!I115 -> 0 | Q22: 2. Công ty con (9)
B23: Fund outside | D23: =SUM(D24:D25) -> 0 | E23: =SUM(E24:E25) -> 0 | F23: =SUM(F24:F25) -> 0 | G23: =SUM(G24:G25) -> 0 | H23: =SUM(H24:H25) -> 0 | I23: 0 | J23: 0 | K23: 0 | L23: 0 | M23: 0 | N23: 0 | Q23: Đơn vị | R23: Vốn điều lệ (tỷ đ) | S23: Vốn góp (tỷ đ) | T23: Tỷ lệ sở hữu (%)
B24: Bonus and welfare funds | D24: ='IP_BS Raw'!E123 -> 0 | E24: ='IP_BS Raw'!F123 -> 0 | F24: ='IP_BS Raw'!G123 -> 0 | G24: ='IP_BS Raw'!H123 -> 0 | H24: ='IP_BS Raw'!I123 -> 0 | Q24: CTCP YAG Entertainment | R24: 0 | S24: 0 | T24: 1
B25: Other funds | D25: ='IP_BS Raw'!E125+'IP_BS Raw'!E124 -> 0 | E25: ='IP_BS Raw'!F125+'IP_BS Raw'!F124 -> 0 | F25: ='IP_BS Raw'!G125+'IP_BS Raw'!G124 -> 0 | G25: ='IP_BS Raw'!H125+'IP_BS Raw'!H124 -> 0 | H25: ='IP_BS Raw'!I125+'IP_BS Raw'!I124 -> 0 | Q25: CTCP Giải trí Yeah1 | R25: 30.3 | S25: 30 | T25: 0.99
Q26: CTCP Phát triển Thương hiệu Yeah1 | R26: 15.15 | S26: 15 | T26: 0.99
B27: Cash Dividend | E27: =E29+E31 -> 31279968 | F27: =F29+F31 -> 0 | G27: =G29+G31 -> 0 | H27: =H29+H31 -> 68500727 | I27: =I29+I31 -> 68500727 | J27: =J29+J31 -> 68500727 | K27: =K29+K31 -> 68500727 | L27: =L29+L31 -> 68500727 | ... N27: =N29+N31 -> 68500727 | Q27: CTCP Giải trí Rồng | R27: 10.1 | S27: 10 | T27: 0.99
B28: % Payout ratio | E28: =E27/E17 -> 0.0028686725 | F28: =F27/F17 -> 0 | G28: =G27/G17 -> 0 | H28: =H27/H17 -> 0.00089471002 | I28: =I27/I17 -> 0.00084798577 | J28: =J27/J17 -> 0.00062663069 | K28: =K27/K17 -> 0.00042466052 | L28: =L27/L17 -> 0.0003011255 | ... N28: =N27/N17 -> 0.00022748443 | Q28: CTCP NVU | R28: 30 | S28: 29.7 | T28: 0.9
B29: 1st cash dividend | E29: =E38*E30*10 -> 31279968 | F29: =F38*F30*10 -> 0 | G29: =G38*G30*10 -> 0 | H29: =H38*H30*10 -> 68500727 | I29: =I38*I30*10 -> 68500727 | J29: =J38*J30*10 -> 68500727 | K29: =K38*K30*10 -> 68500727 | L29: =L38*L30*10 -> 68500727 | ... N29: =N38*N30*10 -> 68500727 | Q29: CTCP Thương mại Thế giới Phim | R29: 0 | S29: 0 | T29: 0.8
B30: % MP | D30: 0.05 | E30: 0.1 | F30: 0 | G30: 0 | H30: 0.05 | I30: 0.05 | J30: 0.05 | K30: 0.05 | L30: 0.05 | M30: 0.05 | N30: 0.05 | Q30: CTCP Truyền thông Trực tuyến NetLink | R30: 26.3 | S30: 19.99 | T30: 0.76
B31: 2nd cash dividend | E31: =E38*E32*10 -> 0 | F31: =F38*F32*10 -> 0 | G31: =G38*G32*10 -> 0 | H31: =H38*H32*10 -> 0 | I31: =I38*I32*10 -> 0 | J31: =J38*J32*10 -> 0 | K31: =K38*K32*10 -> 0 | L31: =L38*L32*10 -> 0 | ... N31: =N38*N32*10 -> 0 | Q31: CTCP Đầu tư và Sản xuất Phim Yeah1 | R31: 0 | S31: 0 | T31: 0.67
B32: % MP | D32: 0.05 | E32: 0 | F32: 0 | G32: 0 | H32: =G32 -> 0 | I32: =H32 -> 0 | J32: =I32 -> 0 | K32: =J32 -> 0 | L32: =K32 -> 0 | M32: =L32 -> 0 | N32: =M32 -> 0 | Q32: CTCP Truyền thông ON+ | R32: 10 | S32: 5.1 | T32: 0.51
Q33: CTCP Công nghệ Tự động Kolorlife | R33: 3.08 | S33: 1.08 | T33: 0.35 | U33: CT liên kết
B34: Stocks Dividend
B35: % MP of 1st Stocks Dividend | D35: 0 | E35: 0.1 | F35: 0.1 | G35: 0.075 | H35: 0.03 | I35: 0.05 | J35: 0.05 | K35: 0.05 | L35: 0.05 | M35: 0.05 | N35: 0.05
B36: % MP of 2nd Stocks Dividend | D36: 0 | E36: 0 | F36: 0 | G36: 0 | H36: 0 | I36: 0 | J36: 0 | K36: 0 | L36: 0 | M36: 0 | N36: 0
B37: 3. Average shares outstanding
B38: Beginning shares recording (Mil Shares) | E38: ='IP_BS Raw'!E105/10000 -> 31279968 | F38: ='IP_BS Raw'!F105/10000 -> 31279968 | G38: ='IP_BS Raw'!G105/10000 -> 131353264 | H38: ='IP_BS Raw'!H105/10000 -> 137001454 | I38: =H38 -> 137001454 | J38: =I38 -> 137001454 | K38: =J38 -> 137001454 | L38: =K38 -> 137001454 | M38: =L38 -> 137001454 | N38: =M38 -> 137001454
B39: Addition public issue (Mil Shares)
B40: - Phase 1
B41: - Phase 2
B42: - Phase 3
B43: Stock divident in years (Mil Shares)
B44: Bonus shares (Mil Shares) | E44: =55.122+11.023 -> 66.145 | F44: 12.126 | G44: =133.395+20.005 -> 153.4 | H44: =12.704+74.869 -> 87.573
B45: ESOP Shares (Mil Shares)
B46: Ending shares recording (Mil Shares) | D46: ='IP_BS Raw'!E105/10000 -> 31279968 | E46: ='IP_BS Raw'!F105/10000 -> 31279968 | F46: ='IP_BS Raw'!G105/10000 -> 131353264 | G46: ='IP_BS Raw'!H105/10000 -> 137001454 | H46: ='IP_BS Raw'!I105/10000 -> 191802035 | I46: =H46 -> 191802035 | J46: =I46 -> 191802035 | K46: =J46 -> 191802035 | L46: =K46 -> 191802035 | M46: =L46 -> 191802035 | N46: =M46 -> 191802035
B47: Treasury shares (Mil Shares) | D47: ='IP_BS Raw'!E111/10000 -> 0 | E47: ='IP_BS Raw'!F111/10000 -> 0 | F47: ='IP_BS Raw'!G111/10000 -> 0 | G47: ='IP_BS Raw'!H111/10000 -> 0 | H47: ='IP_BS Raw'!I111/10000 -> 0 | I47: =H47 -> 0 | J47: =I47 -> 0 | K47: =J47 -> 0 | L47: =K47 -> 0 | M47: =L47 -> 0 | N47: =M47 -> 0
B48: Average shares outstanding in year | D48: =D46-D47 -> 31279968 | E48: =E46-E47 -> 31279968 | F48: =F46-F47 -> 131353264 | G48: =G46-G47 -> 137001454 | H48: =H46-H47 -> 191802035 | I48: =I46-I47 -> 191802035 | J48: =J46-J47 -> 191802035 | K48: =K46-K47 -> 191802035 | ... N48: =N46-N47 -> 191802035
B49: Bloomberg average shares outsstanding - Basic | C49: ARDR_WEIGHT_AVG_SHARES_BASIC | G49: =191802035/1000000 -> 191.80203
B50: Bloomberg average shares outsstanding - Diluted | C50: ARDR_WEIGHT_AVG_SHARES_DILUTED | G50: =191802035/1000000 -> 191.80203
B53: 4. Company Profile
B55: Tên đầy đủ | C55: Công ty Cổ phần Tập đoàn Yeah1
B56: Mã CK / Sàn | C56: YEG / HOSE
B57: Ngày thành lập | C57: 39060
B58: Ngày đổi tên Yeah1 | C58: 42979
B59: Ngày niêm yết HOSE | C59: 26/06/2018
B60: Vốn điều lệ hiện tại (tỷ VND) | C60: 1918
B62: Lĩnh vực hoạt động chính | C62: Quảng cáo truyền hình; quảng cáo nền tảng kỹ thuật số (Facebook/YouTube/Google); đại lý mua bán quảng cáo & bản quyền nội dung; sản xuất Premium Content (concert, reality show, phim)
B63: Sở hữu kênh truyền hình | C63: 4 kênh pay-TV: Yeah1 TV, Yeah1 Family, iMovie TV, UNI Channel + đại lý cho 16 đài TV
B64: Định hướng chiến lược | C64: Tái cấu trúc: dừng sản xuất phim chiếu rạp (Yeah1 CMG); tập trung Premium Content - concert, reality show (ATVNCG, Chị Đẹp Đạp Gió, Show It All, HAHA Farmer); kênh O&O trên Facebook/YouTube/Google
B65: Show nổi bật 2024-2025 | C65: Anh Trai Vượt Ngàn Chông Gai (ATVNCG) - 2 concert sold out 2024 + 2 concert T6/2025; Chị Đẹp Đạp Gió; Mẹ Siêu Nhân; ATVNCG The Movie (cháy vé 1 phút)
B66: Đối tác chiến lược | C66: Techcombank (đồng đầu tư concert + Show It All); MangoTV TQ (license format Show It All, HAHA Farmer); EY VN (kiểm toán)
B68: Vốn hóa hiện tại (tỷ VND) | C68: =H9/1000 -> 1916.1023
B69: Giá hiện tại (VND/CP) | C69: =H4 -> 9990
B70: SLCP lưu hành (triệu CP) | C70: =H8 -> 191.80203

Sheet PD_Annual Breakdown
B2: Criterials | C2: Unit
D3: ='IP_BS Raw'!E2 -> 2021 | E3: ='IP_BS Raw'!F2 -> 2022 | F3: ='IP_BS Raw'!G2 -> 2023 | G3: ='IP_BS Raw'!H2 -> 2024 | H3: ='IP_BS Raw'!I2 -> 2025
B4: 1. Compose Information
B5: Revenue | C5: (VND) | D5: =SUM(D6:D8) -> 1892131002372 | E5: =SUM(E6:E8) -> 2007397494749 | F5: =SUM(F6:F8) -> 2180945411694 | G5: =SUM(G6:G8) -> 2787912700840 | H5: =SUM(H6:H8) -> 2787912700840
B6: Port Operation Services | C6: (VND) | D6: =943678041239+150369414790 -> 1094047456029 | E6: =974514896630+143274511568 -> 1117789408198 | F6: =1048833291855+134893431608+270288395868 -> 1454015119331 | G6: =1340175286046+148078142904+368565738715 -> 1856819167665 | H6: =1340175286046+148078142904+368565738715 -> 1856819167665
B7: Transportation & Freight Services | C7: (VND) | D7: =455420373236 -> 455420373236 | E7: =461503344777 -> 461503344777 | F7: =339470619876+123101930358 -> 462572550234 | G7: =359937587038+184793287841 -> 544730874879 | H7: =359937587038+184793287841 -> 544730874879
B8: Other | C8: (VND) | D8: =342663173107 -> 342663173107 | E8: =428104741774 -> 428104741774 | F8: =160061235149+104296506980 -> 264357742129 | G8: =302815612715+83547045581 -> 386362658296 | H8: =302815612715+83547045581 -> 386362658296
B9: Revenue reports | C9: (VND) | D9: ='IP_IS Raw'!E8 -> 1079507793378 | E9: ='IP_IS Raw'!F8 -> 314124306314 | F9: ='IP_IS Raw'!G8 -> 411666784900 | G9: ='IP_IS Raw'!H8 -> 1026094868172 | H9: ='IP_IS Raw'!I8 -> 1639063078002
B10: Data errors | D10: =D5-D9 -> 812623208994 | E10: =E5-E9 -> 1693273188435 | F10: =F5-F9 -> 1769278626794 | G10: =G5-G9 -> 1761817832668 | H10: =H5-H9 -> 1148849622838
B11: %YoY | C11: (%) | E11: =E5/D5-1 -> 0.060918875 | F11: =F5/E5-1 -> 0.086454186 | G11: =G5/F5-1 -> 0.27830467 | H11: =H5/G5-1 -> 0
B13: Breakdown proportion | C13: (%) | D13: =D5/D$5 -> 1 | E13: =E5/E$5 -> 1 | F13: =F5/F$5 -> 1 | G13: =G5/G$5 -> 1 | H13: =H5/H$5 -> 1
B14: =B6 -> Port Operation Services | C14: (%) | D14: =D6/D$5 -> 0.57820915 | E14: =E6/E$5 -> 0.55683511 | F14: =F6/F$5 -> 0.66669029 | G14: =G6/G$5 -> 0.66602486 | H14: =H6/H$5 -> 0.66602486
B15: =B7 -> Transportation & Freight Services | C15: (%) | D15: =D7/D$5 -> 0.24069178 | E15: =E7/E$5 -> 0.22990133 | F15: =F7/F$5 -> 0.21209726 | G15: =G7/G$5 -> 0.19539022 | H15: =H7/H$5 -> 0.19539022
B16: =B8 -> Other | C16: (%) | D16: =D8/D$5 -> 0.18109907 | E16: =E8/E$5 -> 0.21326356 | F16: =F8/F$5 -> 0.12121245 | G16: =G8/G$5 -> 0.13858492 | H16: =H8/H$5 -> 0.13858492
B18: Cost of good sold | C18: (VND) | D18: =SUM(D19:D23) -> 1.7929805e+12 | E18: =SUM(E19:E23) -> 2.8568609e+12 | F18: =SUM(F19:F23) -> 3.2104302e+12 | G18: =SUM(G19:G23) -> 3.7044612e+12 | H18: =SUM(H19:H23) -> -1424028369399
B19: Raw Materials cost | C19: (VND) | D19: =D95 -> 5.1229639e+11 | E19: =E95 -> 1.533448e+12 | F19: =F95 -> 1.6318079e+12 | G19: =G95 -> 1.6014146e+12 | H19: =H95 -> -1424028369399
B20: Labor cost | C20: (VND) | D20: =D97 -> 286828460685 | E20: =E97 -> 311382278820 | F20: =F97 -> 368910249822 | G20: =G97 -> 384763275501 | H20: =H97 -> 0
B21: Fixed A depriciation cost | C21: (VND) | D21: =D98 -> 200434357266 | E21: =E98 -> 201526522056 | F21: =F98 -> 193367525445 | G21: =G98 -> 254230428893 | H21: =H98 -> 0
B22: Outsources cost | C22: (VND) | D22: =D99 -> 513905619374 | E22: =E99 -> 562566703743 | F22: =F99 -> 808118369862 | G22: =G99 -> 1198518123985 | H22: =H99 -> 0
B23: Other cost | C23: (VND) | D23: =D100 -> 279515648242 | E23: =E100 -> 247937428273 | F23: =F100 -> 208226148927 | G23: =G100 -> 265534685439 | H23: =H100 -> 0
B25: Breakdown proportion | C25: (%) | D25: =D18/D$18 -> 1 | E25: =E18/E$18 -> 1 | F25: =F18/F$18 -> 1 | G25: =G18/G$18 -> 1 | H25: =H18/H$18 -> 1
B26: Raw Materials cost | C26: (%) | D26: =D19/D$18 -> 0.28572335 | E26: =E19/E$18 -> 0.53675976 | F26: =F19/F$18 -> 0.50828325 | G26: =G19/G$18 -> 0.43229354 | H26: =H19/H$18 -> 1
B27: Labor cost | C27: (%) | D27: =D20/D$18 -> 0.159973 | E27: =E20/E$18 -> 0.10899455 | F27: =F20/F$18 -> 0.11490991 | G27: =G20/G$18 -> 0.10386484 | H27: =H20/H$18 -> 0
B28: Fixed A depriciation cost | C28: (%) | D28: =D21/D$18 -> 0.11178837 | E28: =E21/E$18 -> 0.070541243 | F28: =F21/F$18 -> 0.060231033 | G28: =G21/G$18 -> 0.06862818 | H28: =H21/H$18 -> 0
B29: Outsources cost | C29: (%) | D29: =D22/D$18 -> 0.28662087 | E29: =E22/E$18 -> 0.19691778 | F29: =F22/F$18 -> 0.25171654 | G29: =G22/G$18 -> 0.32353373 | H29: =H22/H$18 -> 0
B30: Other cost | C30: (%) | D30: =D23/D$18 -> 0.15589442 | E30: =E23/E$18 -> 0.086786664 | F30: =F23/F$18 -> 0.064859267 | G30: =G23/G$18 -> 0.071679706 | H30: =H23/H$18 -> 0
B32: Gross profit | C32: (VND) | D32: =D5+D18 -> 3.6851115e+12 | E32: =E5+E18 -> 4.8642584e+12 | F32: =F5+F18 -> 5.3913756e+12 | G32: =G5+G18 -> 6.4923739e+12 | H32: =H5+H18 -> 1363884331441
B33: Data errors | D33: ='IP_IS Raw'!E10-'PD_Annual Breakdown'!D32 -> -3.6509864e+12 | E33: ='IP_IS Raw'!F10-'PD_Annual Breakdown'!E32 -> -4.7597797e+12 | F33: ='IP_IS Raw'!G10-'PD_Annual Breakdown'!F32 -> -5.2761898e+12 | G33: ='IP_IS Raw'!H10-'PD_Annual Breakdown'!G32 -> -6.3215227e+12 | H33: ='IP_IS Raw'!I10-'PD_Annual Breakdown'!H32 -> -1148849622838
B34: %YoY | C34: (%) | E34: =E32/D32-1 -> 0.31997592 | F34: =F32/E32-1 -> 0.10836537 | G34: =G32/F32-1 -> 0.20421472 | H34: =H32/G32-1 -> -0.78992517
B36: Gross Profit Margin | C36: (%) | D36: =D32/D5 -> 1.9475985 | E36: =E32/E5 -> 2.4231665 | F36: =F32/F5 -> 2.472036 | G36: =G32/G5 -> 2.3287579 | H36: =H32/H5 -> 0.48921343
B38: Selling expenses | C38: (VND) | D38: ='IP_IS Raw'!E15 -> -86766850424 | E38: ='IP_IS Raw'!F15 -> -20658752305 | F38: ='IP_IS Raw'!G15 -> -14260496293 | G38: ='IP_IS Raw'!H15 -> -26239808550 | H38: ='IP_IS Raw'!I15 -> -39335239608
B39: As a revenue | C39: (%) | D39: =-D38/D5 -> 0.045856682 | E39: =-E38/E5 -> 0.010291311 | F39: =-F38/F5 -> 0.0065386764 | G39: =-G38/G5 -> 0.0094119907 | H39: =-H38/H5 -> 0.014109208
B41: G&A expenses | C41: (VND) | D41: ='IP_IS Raw'!E16 -> -211115902487 | E41: ='IP_IS Raw'!F16 -> -93384172422 | F41: ='IP_IS Raw'!G16 -> -66900478155 | G41: ='IP_IS Raw'!H16 -> -151633232794 | H41: ='IP_IS Raw'!I16 -> -167762629718
B42: As a revenue | C42: (%) | D42: =-D41/D5 -> 0.11157573 | E42: =-E41/E5 -> 0.04652002 | F42: =-F41/F5 -> 0.03067499 | G42: =-G41/G5 -> 0.05438952 | H42: =-H41/H5 -> 0.060174994
B44: Breakdown operation expenses | C44: (%) | D44: =(D18+D38+D41)/(D$18+D$38+D$41) -> 1 | E44: =(E18+E38+E41)/(E$18+E$38+E$41) -> 1 | F44: =(F18+F38+F41)/(F$18+F$38+F$41) -> 1 | G44: =(G18+G38+G41)/(G$18+G$38+G$41) -> 1 | H44: =(H18+H38+H41)/(H$18+H$38+H$41) -> 1
B45: Total COGS | C45: (%) | D45: =(D18)/(D$18+D$38+D$41) -> 1.1992397 | E45: =(E18)/(E$18+E$38+E$41) -> 1.0415787 | F45: =(F18)/(F$18+F$38+F$41) -> 1.0259361 | G45: =(G18)/(G$18+G$38+G$41) -> 1.0504377 | H45: =(H18)/(H$18+H$38+H$41) -> 0.87303382
B46: Selling Expenses | C46: (%) | D46: =(D38)/(D$18+D$38+D$41) -> -0.058034233 | E46: =(E38)/(E$18+E$38+E$41) -> -0.0075319443 | F46: =(F38)/(F$18+F$38+F$41) -> -0.0045571331 | G46: =(G38)/(G$18+G$38+G$41) -> -0.0074405651 | H46: =(H38)/(H$18+H$38+H$41) -> 0.024115386
B47: GS&A Expenses | C47: (%) | D47: =(D41)/(D$18+D$38+D$41) -> -0.14120542 | E47: =(E41)/(E$18+E$38+E$41) -> -0.034046799 | F47: =(F41)/(F$18+F$38+F$41) -> -0.021378946 | G47: =(G41)/(G$18+G$38+G$41) -> -0.042997148 | H47: =(H41)/(H$18+H$38+H$41) -> 0.10285079
B48: Raw Materials cost | C48: (%) | D48: =(D103)/(D$18+D$38+D$41) -> 0.092634417 | E48: =(E103)/(E$18+E$38+E$41) -> 0.076505383 | F48: =(F103)/(F$18+F$38+F$41) -> 0.055870322 | G48: =(G103)/(G$18+G$38+G$41) -> 0.05013512 | H48: =(H103)/(H$18+H$38+H$41) -> 0
B49: Labor cost | C49: (%) | D49: =(D104)/(D$18+D$38+D$41) -> 0.19184596 | E49: =(E104)/(E$18+E$38+E$41) -> 0.11352641 | F49: =(F104)/(F$18+F$38+F$41) -> 0.11789022 | G49: =(G104)/(G$18+G$38+G$41) -> 0.10910355 | H49: =(H104)/(H$18+H$38+H$41) -> 0
B50: Fixed A depriciation cost | C50: (%) | D50: =(D105)/(D$18+D$38+D$41) -> 0.13406104 | E50: =(E105)/(E$18+E$38+E$41) -> 0.07347426 | F50: =(F105)/(F$18+F$38+F$41) -> 0.061793189 | G50: =(G105)/(G$18+G$38+G$41) -> 0.072089629 | H50: =(H105)/(H$18+H$38+H$41) -> 0
B51: Outsources cost | C51: (%) | D51: =(D106)/(D$18+D$38+D$41) -> 0.34372711 | E51: =(E106)/(E$18+E$38+E$41) -> 0.20510537 | F51: =(F106)/(F$18+F$38+F$41) -> 0.25824508 | G51: =(G106)/(G$18+G$38+G$41) -> 0.33985203 | H51: =(H106)/(H$18+H$38+H$41) -> 0
B52: Other cost | C52: (%) | D52: =(D107)/(D$18+D$38+D$41) -> 0.18695477 | E52: =(E107)/(E$18+E$38+E$41) -> 0.090395144 | F52: =(F107)/(F$18+F$38+F$41) -> 0.066541462 | G52: =(G107)/(G$18+G$38+G$41) -> 0.075295066 | H52: =(H107)/(H$18+H$38+H$41) -> 0
B54: Financial Revenue | C54: (VND) | D54: ='IP_IS Raw'!E11 -> 423849348595 | E54: ='IP_IS Raw'!F11 -> 47340388199 | F54: ='IP_IS Raw'!G11 -> 43586401680 | G54: ='IP_IS Raw'!H11 -> 191906506913 | H54: ='IP_IS Raw'!I11 -> 120349183176
B56: Financial Expenses | C56: (VND) | D56: ='IP_IS Raw'!E12 -> -28037984463 | E56: ='IP_IS Raw'!F12 -> -9021747176 | F56: ='IP_IS Raw'!G12 -> -23482415579 | G56: ='IP_IS Raw'!H12 -> -51108323960 | H56: ='IP_IS Raw'!I12 -> -27197709414
B57: Interest Expenses | C57: (VND) | D57: ='IP_IS Raw'!E13 -> -21801000846 | E57: ='IP_IS Raw'!F13 -> -6906877175 | F57: ='IP_IS Raw'!G13 -> -21505000199 | G57: ='IP_IS Raw'!H13 -> -28208427529 | H57: ='IP_IS Raw'!I13 -> -25900554619
B59: Gain/ loss of joint venture | C59: (VND) | D59: ='IP_IS Raw'!E14 -> 436847500 | E59: ='IP_IS Raw'!F14 -> 505897455 | F59: ='IP_IS Raw'!G14 -> -4853955053 | G59: ='IP_IS Raw'!H14 -> -15223546244 | H59: ='IP_IS Raw'!I14 -> -1456928964
B61: Net other income | C61: (VND) | D61: ='IP_IS Raw'!E18 -> -34173832376 | E61: ='IP_IS Raw'!F18 -> -345291142 | F61: ='IP_IS Raw'!G18 -> -20350770574 | G61: ='IP_IS Raw'!H18 -> -7930215677 | H61: ='IP_IS Raw'!I18 -> -4951888334
B63: Earning before tax (EBT) | C63: (VND) | D63: =D32+D54+D56+D59+D61+D38+D41 -> 3.7493031e+12 | E63: =E32+E54+E56+E59+E61+E38+E41 -> 4.7886947e+12 | F63: =F32+F54+F56+F59+F61+F38+F41 -> 5.3051139e+12 | G63: =G32+G54+G56+G59+G61+G38+G41 -> 6.4321452e+12 | H63: =H32+H54+H56+H59+H61+H38+H41 -> 1243529118579
B64: Data errors | D64: =D63-'IP_IS Raw'!E22 -> 3.6509864e+12 | E64: =E63-'IP_IS Raw'!F22 -> 4.7597797e+12 | F64: =F63-'IP_IS Raw'!G22 -> 5.2761898e+12 | G64: =G63-'IP_IS Raw'!H22 -> 6.3215227e+12 | H64: =H63-'IP_IS Raw'!I22 -> 1148849622838
B65: %YoY | C65: (%) | E65: =E63/D63-1 -> 0.27722262 | F65: =F63/E63-1 -> 0.10784132 | G65: =G63/F63-1 -> 0.21244244 | H65: =H63/G63-1 -> -0.80666961
B67: Corporate tax | C67: (VND) | D67: ='IP_IS Raw'!E23 -> -68326484945 | E67: ='IP_IS Raw'!F23 -> -4024148047 | F67: ='IP_IS Raw'!G23 -> -2405158607 | G67: ='IP_IS Raw'!H23 -> 11951746732 | H67: ='IP_IS Raw'!I23 -> -17278295298
B68: Tax rate | C68: (VND) | D68: =-D67/D63 -> 0.018223783 | E68: =-E67/E63 -> 0.0008403434 | F68: =-F67/F63 -> 0.00045336606 | G68: =-G67/G63 -> -0.0018581276 | H68: =-H67/H63 -> 0.013894564
B70: Earning after tax (EBT) | C70: (VND) | D70: =D63+D67 -> 3.6809766e+12 | E70: =E63+E67 -> 4.7846706e+12 | F70: =F63+F67 -> 5.3027087e+12 | G70: =G63+G67 -> 6.444097e+12 | H70: =H63+H67 -> 1226250823281
B71: Data errors | D71: =D70-'IP_IS Raw'!E26 -> 3.6509864e+12 | E71: =E70-'IP_IS Raw'!F26 -> 4.7597797e+12 | F71: =F70-'IP_IS Raw'!G26 -> 5.2761898e+12 | G71: =G70-'IP_IS Raw'!H26 -> 6.3215227e+12 | H71: =H70-'IP_IS Raw'!I26 -> 1148849622838
B72: %YoY | C72: (%) | E72: =E70/D70-1 -> 0.29983727 | F72: =F70/E70-1 -> 0.10827039 | G72: =G70/F70-1 -> 0.21524627 | H72: =H70/G70-1 -> -0.80970944
B74: 2. Detail
B75: Revenue | C75: (VND) | D75: =IFERROR('IP_IS Raw'!E8,"") -> 1079507793378 | E75: =IFERROR('IP_IS Raw'!F8,"") -> 314124306314 | F75: =IFERROR('IP_IS Raw'!G8,"") -> 411666784900 | G75: =IFERROR('IP_IS Raw'!H8,"") -> 1026094868172 | H75: =IFERROR('IP_IS Raw'!I8,"") -> 1639063078002
B77: 1. Port Operation Services | C77: (VND) | D77: =D6 -> 1094047456029 | E77: =E6 -> 1117789408198 | F77: =F6 -> 1454015119331 | G77: =G6 -> 1856819167665 | H77: =H6 -> 1856819167665
B78: Selling volume
B79: %YoY growth | C79: (%) | E79: =IFERROR(E78/D78-1,"N/A") -> N/A | F79: =IFERROR(F78/E78-1,"N/A") -> N/A | G79: =IFERROR(G78/F78-1,"N/A") -> N/A | H79: =IFERROR(H78/G78-1,"N/A") -> N/A
B80: ASP per unit
B81: %YoY growth | C81: (%) | E81: =IFERROR(E80/D80-1,"N/A") -> N/A | F81: =IFERROR(F80/E80-1,"N/A") -> N/A | G81: =IFERROR(G80/F80-1,"N/A") -> N/A | H81: =IFERROR(H80/G80-1,"N/A") -> N/A
B83: 2. Transportation & Freight Services | C83: (VND) | D83: =D7 -> 455420373236 | E83: =E7 -> 461503344777 | F83: =F7 -> 462572550234 | G83: =G7 -> 544730874879 | H83: =H7 -> 544730874879
B84: Selling volume
B85: %YoY growth | C85: (%) | E85: =IFERROR(E84/D84-1,"N/A") -> N/A | F85: =IFERROR(F84/E84-1,"N/A") -> N/A | G85: =IFERROR(G84/F84-1,"N/A") -> N/A | H85: =IFERROR(H84/G84-1,"N/A") -> N/A
B86: ASP per unit
B87: %YoY growth | C87: (%) | E87: =IFERROR(E86/D86-1,"N/A") -> N/A | F87: =IFERROR(F86/E86-1,"N/A") -> N/A | G87: =IFERROR(G86/F86-1,"N/A") -> N/A | H87: =IFERROR(H86/G86-1,"N/A") -> N/A
B89: 3. Other segment | D89: =D75-D77-D83 -> -469960035887 | E89: =E75-E77-E83 -> -1265168446661 | F89: =F75-F77-F83 -> -1504920884665 | G89: =G75-G77-G83 -> -1375455174372 | H89: =H75-H77-H83 -> -762486964542
B90: %YoY | C90: (%) | E90: =IFERROR(E89/D89-1,"N/A") -> 1.6920767 | F90: =IFERROR(F89/E89-1,"N/A") -> 0.18950238 | G90: =IFERROR(G89/F89-1,"N/A") -> -0.08602825 | H90: =IFERROR(H89/G89-1,"N/A") -> -0.44564754
B92: Actual Cost of good sold | C92: (VND) | D92: ='IP_IS Raw'!E9 -> -1045382703416 | E92: ='IP_IS Raw'!F9 -> -209645620562 | F92: ='IP_IS Raw'!G9 -> -296480952992 | G92: ='IP_IS Raw'!H9 -> -855243703997 | H92: ='IP_IS Raw'!I9 -> -1424028369399
B93: Spread | C93: (VND) | D93: =D92-D94 -> 3.7379889e+11 | E93: =E92-E94 -> 1.3236077e+12 | F93: =F92-F94 -> 1.4569746e+12 | G93: =G92-G94 -> 1.4246087e+12 | H93: =H92-H94 -> -1424028369399
B94: Estimate COGS by segments | C94: (VND) | D94: =SUM(D96:D100)*(-1) -> -1.4191816e+12 | E94: =SUM(E96:E100)*(-1) -> -1.5332533e+12 | F94: =SUM(F96:F100)*(-1) -> -1.7534556e+12 | G94: =SUM(G96:G100)*(-1) -> -2.2798524e+12 | H94: =SUM(H96:H100)*(-1) -> 0
B95: Raw Materials cost_After adjust | C95: (VND) | D95: =D96+D93 -> 5.1229639e+11 | E95: =E96+E93 -> 1.533448e+12 | F95: =F96+F93 -> 1.6318079e+12 | G95: =G96+G93 -> 1.6014146e+12 | H95: =H96+H93 -> -1424028369399
B96: Raw Materials cost | C96: (VND) | D96: =D103-D110-D118 -> 1.3849751e+11 | E96: =E103-E110-E118 -> 2.0984034e+11 | F96: =F103-F110-F118 -> 1.7483328e+11 | G96: =G103-G110-G118 -> 1.7680592e+11 | H96: =H103-H110-H118 -> 0
B97: Labor cost | C97: (VND) | D97: =D104-D111-D119 -> 286828460685 | E97: =E104-E111-E119 -> 311382278820 | F97: =F104-F111-F119 -> 368910249822 | G97: =G104-G111-G119 -> 384763275501 | H97: =H104-H111-H119 -> 0
B98: Fixed A depriciation cost | C98: (VND) | D98: =D105-D112-D120 -> 200434357266 | E98: =E105-E112-E120 -> 201526522056 | F98: =F105-F112-F120 -> 193367525445 | G98: =G105-G112-G120 -> 254230428893 | H98: =H105-H112-H120 -> 0
B99: Outsources cost | C99: (VND) | D99: =D106-D113-D121 -> 513905619374 | E99: =E106-E113-E121 -> 562566703743 | F99: =F106-F113-F121 -> 808118369862 | G99: =G106-G113-G121 -> 1198518123985 | H99: =H106-H113-H121 -> 0
B100: Other cost | C100: (VND) | D100: =D107-D114-D122 -> 279515648242 | E100: =E107-E114-E122 -> 247937428273 | F100: =F107-F114-F122 -> 208226148927 | G100: =G107-G114-G122 -> 265534685439 | H100: =H107-H114-H122 -> 0
B102: Operation expenses | C102: (VND) | D102: =SUM(D103:D107)*(-1) -> -1419181591526 | E102: =SUM(E103:E107)*(-1) -> -1533253274499 | F102: =SUM(F103:F107)*(-1) -> -1753455573655 | G102: =SUM(G103:G107)*(-1) -> -2279852430746 | H102: =SUM(H103:H107)*(-1) -> 0
B103: Raw Materials cost | C103: (VND) | D103: ='IP_Notes Raw'!E158 -> 138497505959 | E103: ='IP_Notes Raw'!F158 -> 209840341607 | F103: ='IP_Notes Raw'!G158 -> 174833279599 | G103: ='IP_Notes Raw'!H158 -> 176805916928 | H103: ='IP_Notes Raw'!I158 -> 0
B104: Labor cost | C104: (VND) | D104: ='IP_Notes Raw'!E159 -> 286828460685 | E104: ='IP_Notes Raw'!F159 -> 311382278820 | F104: ='IP_Notes Raw'!G159 -> 368910249822 | G104: ='IP_Notes Raw'!H159 -> 384763275501 | H104: ='IP_Notes Raw'!I159 -> 0
B105: Fixed A depriciation cost | C105: (VND) | D105: ='IP_Notes Raw'!E160 -> 200434357266 | E105: ='IP_Notes Raw'!F160 -> 201526522056 | F105: ='IP_Notes Raw'!G160 -> 193367525445 | G105: ='IP_Notes Raw'!H160 -> 254230428893 | H105: ='IP_Notes Raw'!I160 -> 0
B106: Outsources cost | C106: (VND) | D106: ='IP_Notes Raw'!E161 -> 513905619374 | E106: ='IP_Notes Raw'!F161 -> 562566703743 | F106: ='IP_Notes Raw'!G161 -> 808118369862 | G106: ='IP_Notes Raw'!H161 -> 1198518123985 | H106: ='IP_Notes Raw'!I161 -> 0
B107: Other cost | C107: (VND) | D107: ='IP_Notes Raw'!E162 -> 279515648242 | E107: ='IP_Notes Raw'!F162 -> 247937428273 | F107: ='IP_Notes Raw'!G162 -> 208226148927 | G107: ='IP_Notes Raw'!H162 -> 265534685439 | H107: ='IP_Notes Raw'!I162 -> 0
B109: Selling expenses | C109: =C102 -> (VND) | D109: ='IP_IS Raw'!E15 -> -86766850424 | E109: ='IP_IS Raw'!F15 -> -20658752305 | F109: ='IP_IS Raw'!G15 -> -14260496293 | G109: ='IP_IS Raw'!H15 -> -26239808550 | H109: ='IP_IS Raw'!I15 -> -39335239608
B110: Raw Materials cost | C110: =C103 -> (VND) | D110: -0.137 | E110: -0.387 | F110: -0.818 | G110: -4.21
B111: Labor cost | C111: =C104 -> (VND)
B112: Fixed A depriciation cost | C112: =C105 -> (VND)
B113: Outsources cost | C113: =C106 -> (VND)
B114: Other cost | C114: =C107 -> (VND)
B115: Warranty reserve | C115: =C108 -> 0
B117: GS&A expenses | C117: =C109 -> (VND) | D117: ='IP_IS Raw'!E16 -> -211115902487 | E117: ='IP_IS Raw'!F16 -> -93384172422 | F117: ='IP_IS Raw'!G16 -> -66900478155 | G117: ='IP_IS Raw'!H16 -> -151633232794 | H117: ='IP_IS Raw'!I16 -> -167762629718
B118: Raw Materials cost | C118: =C110 -> (VND)
B119: Labor cost | C119: =C111 -> (VND)
B120: Fixed A depriciation cost | C120: =C112 -> (VND)
B121: Outsources cost | C121: =C113 -> (VND)
B122: Other cost | C122: =C114 -> (VND)
B123: Provision for doubtful debts | C123: =C115 -> 0
B125: Fixed A depriciation cost (except in COGS)
...

Sheet PD_Operation
B2: PD_Operation — Forecast Drivers | G2: 45291 | H2: =DATE(YEAR(G2),MONTH(G2)+13,0) -> 45657 | I2: =DATE(YEAR(H2),MONTH(H2)+13,0) -> 46022 | J2: =DATE(YEAR(I2),MONTH(I2)+13,0) -> 46387 | K2: =DATE(YEAR(J2),MONTH(J2)+13,0) -> 46752 | L2: =DATE(YEAR(K2),MONTH(K2)+13,0) -> 47118 | M2: =DATE(YEAR(L2),MONTH(L2)+13,0) -> 47483 | N2: =DATE(YEAR(M2),MONTH(M2)+13,0) -> 47848
B3: Item | C3: Unit | D3: =OD_IS!D3 -> 2021 | E3: =OD_IS!E3 -> 2022 | F3: =OD_IS!F3 -> 2023 | G3: =OD_IS!G3 -> 2024 | H3: =OD_IS!H3 -> 2025 | I3: =OD_IS!I3 -> 2026 | J3: =OD_IS!J3 -> 2027 | K3: =OD_IS!K3 -> 2028 | ... N3: =OD_IS!N3 -> 2031
B4: 1. Revenue
B5: Income Statement Drivers | C5: (Thoudsan Units)
B6: Revenue | C6: (VND) | D6: =OD_IS!D4 -> 1079507793378 | E6: =OD_IS!E4 -> 314124306314 | F6: =OD_IS!F4 -> 411666784900 | G6: =OD_IS!G4 -> 1026094868172 | H6: =OD_IS!H4 -> 1639063078002 | I6: =H6*(1+I7) -> 2.130782e+12 | J6: =I6*(1+J7) -> 2.599554e+12 | K6: =J6*(1+K7) -> 2.9894871e+12 | L6: =K6*(1+L7) -> 3.3183307e+12 | M6: =L6*(1+M7) -> 3.5837972e+12 | N6: =M6*(1+N7) -> 3.7629871e+12
B7: Revenue growth % | E7: =E6/D6-1 -> -0.70901154 | F7: =F6/E6-1 -> 0.31052191 | G7: =G6/F6-1 -> 1.4925374 | H7: =H6/G6-1 -> 0.59737967 | I7: 0.3 | J7: 0.22 | K7: 0.15 | L7: 0.11 | M7: 0.08 | N7: 0.05
B8: COGS % of revenue | C8: (%) | D8: =-OD_IS!D5/OD_IS!D4 -> 0.96838829 | E8: =-OD_IS!E5/OD_IS!E4 -> 0.667397 | F8: =-OD_IS!F5/OD_IS!F4 -> 0.72019644 | G8: =-OD_IS!G5/OD_IS!G4 -> 0.83349379 | H8: =-OD_IS!H5/OD_IS!H4 -> 0.86880633 | I8: 0.87 | J8: 0.86 | K8: 0.84 | L8: 0.82 | M8: 0.81 | N8: 0.81
B9: Selling expenses % of revenue | C9: (%) | D9: =-OD_IS!D7/OD_IS!D4 -> 0.080376308 | E9: =-OD_IS!E7/OD_IS!E4 -> 0.065766169 | F9: =-OD_IS!F7/OD_IS!F4 -> 0.034640872 | G9: =-OD_IS!G7/OD_IS!G4 -> 0.025572498 | H9: =-OD_IS!H7/OD_IS!H4 -> 0.023998612 | I9: 0.025 | J9: 0.025 | K9: 0.025 | L9: 0.025 | M9: 0.025 | N9: 0.025
B10: G&A expenses % of revenue | C10: (%) | D10: =-OD_IS!D8/OD_IS!D4 -> 0.19556682 | E10: =-OD_IS!E8/OD_IS!E4 -> 0.29728413 | F10: =-OD_IS!F8/OD_IS!F4 -> 0.16251124 | G10: =-OD_IS!G8/OD_IS!G4 -> 0.14777701 | H10: =-OD_IS!H8/OD_IS!H4 -> 0.10235276 | I10: 0.1 | J10: 0.098 | K10: 0.095 | L10: 0.093 | M10: 0.09 | N10: 0.09
B11: D&A (VND bn) — fixed asset-light | C11: (VND bn) | D11: =OD_CF!D6/OD_IS!D4 -> 0.18567199 | E11: =OD_CF!E6/OD_IS!E4 -> 0.64155023 | F11: =OD_CF!F6/OD_IS!F4 -> 0.46971855 | G11: =OD_CF!G6/OD_IS!G4 -> 0.24776503 | H11: =OD_CF!H6/OD_IS!H4 -> 0 | I11: 250 | J11: =I11*1.05 -> 262.5 | K11: =J11*1.05 -> 275.625 | L11: =K11*1.05 -> 289.40625 | M11: =L11*1.05 -> 303.87656 | N11: =M11*1.05 -> 319.07039
B12: Financial income % of revenue | C12: (%) | D12: =OD_IS!D10/OD_IS!D4 -> 0.39263204 | E12: =OD_IS!E10/OD_IS!E4 -> 0.15070591 | F12: =OD_IS!F10/OD_IS!F4 -> 0.10587787 | G12: =OD_IS!G10/OD_IS!G4 -> 0.18702609 | H12: =OD_IS!H10/OD_IS!H4 -> 0.073425596 | I12: 0.06 | J12: 0.05 | K12: 0.04 | L12: 0.035 | M12: 0.035 | N12: 0.035
B13: Tax rate | C13: (%) | D13: =-OD_IS!D19/OD_IS!D16 -> 0.69496305 | E13: =-OD_IS!E19/OD_IS!E16 -> 0.1391716 | F13: =-OD_IS!F19/OD_IS!F16 -> 0.083154087 | G13: =-OD_IS!G19/OD_IS!G16 -> -0.10081374 | H13: =-OD_IS!H19/OD_IS!H16 -> 0.17342221 | I13: =OD_Valuation!$C$11 -> 0.2 | J13: =OD_Valuation!$C$11 -> 0.2 | K13: =OD_Valuation!$C$11 -> 0.2 | L13: =OD_Valuation!$C$11 -> 0.2 | M13: =OD_Valuation!$C$11 -> 0.2 | N13: =OD_Valuation!$C$11 -> 0.2
B14: % Selling volume/ Capacity | C14: (%)
B15: Balance Sheet / WC Drivers | C15: (%)
B16: Days in AR | C16: (Days) | D16: =365*OD_BS!D8/OD_IS!D4 -> 358.25449 | E16: =365*OD_BS!E8/OD_IS!E4 -> 628.96559 | F16: =365*OD_BS!F8/OD_IS!F4 -> 749.56091 | G16: =365*OD_BS!G8/OD_IS!G4 -> 391.97605 | H16: =365*OD_BS!H8/OD_IS!H4 -> 290.65262 | I16: 120 | J16: 100 | K16: 90 | L16: 80 | M16: 80 | N16: 80
B17: Days in Inventory | C17: (Days) | D17: =-365*OD_BS!D9/OD_IS!D5 -> 10.727246 | E17: =-365*OD_BS!E9/OD_IS!E5 -> 27.005171 | F17: =-365*OD_BS!F9/OD_IS!F5 -> 35.9097 | G17: =-365*OD_BS!G9/OD_IS!G5 -> 17.414652 | H17: =-365*OD_BS!H9/OD_IS!H5 -> 25.081931 | I17: =AVERAGE($G17:$H17) -> 21.248291 | J17: =AVERAGE($G17:$H17) -> 21.248291 | K17: =AVERAGE($G17:$H17) -> 21.248291 | L17: =AVERAGE($G17:$H17) -> 21.248291 | M17: =AVERAGE($G17:$H17) -> 21.248291 | N17: =AVERAGE($G17:$H17) -> 21.248291
B18: Days in AP | C18: (Days) | D18: =-365*OD_BS!D20/OD_IS!D5 -> 30.49002 | E18: =-365*OD_BS!E20/OD_IS!E5 -> 144.82228 | F18: =-365*OD_BS!F20/OD_IS!F5 -> 120.83705 | G18: =-365*OD_BS!G20/OD_IS!G5 -> 58.720838 | H18: =-365*OD_BS!H20/OD_IS!H5 -> 38.214938 | I18: =$H18 -> 38.214938 | J18: =$H18 -> 38.214938 | K18: =$H18 -> 38.214938 | L18: =$H18 -> 38.214938 | M18: =$H18 -> 38.214938 | N18: =$H18 -> 38.214938
B19: Other Current Asset % of revenue | C19: (%) | D19: =OD_BS!D10/OD_IS!D4 -> 0.032494183 | E19: =OD_BS!E10/OD_IS!E4 -> 0.12678959 | F19: =OD_BS!F10/OD_IS!F4 -> 0.15639914 | G19: =OD_BS!G10/OD_IS!G4 -> 0.024467047 | H19: =OD_BS!H10/OD_IS!H4 -> 0.0090024146 | I19: =AVERAGE($G19:$H19) -> 0.016734731 | J19: =AVERAGE($G19:$H19) -> 0.016734731 | K19: =AVERAGE($G19:$H19) -> 0.016734731 | L19: =AVERAGE($G19:$H19) -> 0.016734731 | M19: =AVERAGE($G19:$H19) -> 0.016734731 | N19: =AVERAGE($G19:$H19) -> 0.016734731
B20: Other Current Liab % of revenue | C20: (%) | D20: =OD_BS!D22/OD_IS!D4 -> 0.17175569 | E20: =OD_BS!E22/OD_IS!E4 -> 0.43930455 | F20: =OD_BS!F22/OD_IS!F4 -> 0.33793801 | G20: =OD_BS!G22/OD_IS!G4 -> 0.29045091 | H20: =OD_BS!H22/OD_IS!H4 -> 0.10820902 | I20: =AVERAGE($G20:$H20) -> 0.19932996 | J20: =AVERAGE($G20:$H20) -> 0.19932996 | K20: =AVERAGE($G20:$H20) -> 0.19932996 | L20: =AVERAGE($G20:$H20) -> 0.19932996 | M20: =AVERAGE($G20:$H20) -> 0.19932996 | N20: =AVERAGE($G20:$H20) -> 0.19932996
B21: CapEx % of revenue | C21: (%) | D21: =-OD_CF!D10/OD_IS!D4 -> 0.0026974283 | E21: =-OD_CF!E10/OD_IS!E4 -> 0.00083435412 | F21: =-OD_CF!F10/OD_IS!F4 -> 0.20683059 | G21: =-OD_CF!G10/OD_IS!G4 -> 0.53887787 | H21: =-OD_CF!H10/OD_IS!H4 -> 0.059924103 | I21: 0.06 | J21: 0.05 | K21: 0.04 | L21: 0.04 | M21: 0.04 | N21: 0.04
B22: %YoY growth | C22: (%)
B23: Financing Drivers
B24: Short-term debt (hold flat) | C24: (VND) | D24: =OD_BS!D21 -> 130796216812 | E24: =OD_BS!E21 -> 94317807400 | F24: =OD_BS!F21 -> 171352690912 | G24: =OD_BS!G21 -> 527364096445 | H24: =OD_BS!H21 -> 304271257481 | I24: =$H24 -> 304271257481 | J24: =$H24 -> 304271257481 | K24: =$H24 -> 304271257481 | L24: =$H24 -> 304271257481 | M24: =$H24 -> 304271257481 | N24: =$H24 -> 304271257481
B25: Long-term debt (hold flat) | C25: (VND) | D25: =OD_BS!D24 -> 71000000000 | E25: =OD_BS!E24 -> 1000000000 | F25: =OD_BS!F24 -> 39014432856 | G25: =OD_BS!G24 -> 50006060793 | H25: =OD_BS!H24 -> 36866802037 | I25: =$H25 -> 36866802037 | J25: =$H25 -> 36866802037 | K25: =$H25 -> 36866802037 | L25: =$H25 -> 36866802037 | M25: =$H25 -> 36866802037 | N25: =$H25 -> 36866802037
B26: Dividend payout ratio | C26: (%) | D26: =IFERROR(-OD_CF!D15/OD_IS!D21,0) -> 0 | E26: =IFERROR(-OD_CF!E15/OD_IS!E21,0) -> 0 | F26: =IFERROR(-OD_CF!F15/OD_IS!F21,0) -> 0 | G26: =IFERROR(-OD_CF!G15/OD_IS!G21,0) -> 0 | H26: =IFERROR(-OD_CF!H15/OD_IS!H21,0) -> 0.015584581 | I26: 0 | J26: 0 | K26: 0.05 | L26: 0.1 | M26: 0.15 | N26: 0.2
B27: %YoY growth | C27: (%)
B28: =B10 -> G&A expenses % of revenue | C28: (VND)
B29: %YoY growth | C29: (%)
B30: =B13 -> Tax rate | C30: (VND)
B31: %YoY growth | C31: (%)
B32: %CAGR in the 2018 - 2023 | C32: (%)
B34: 2. COGS
B35: A. Summary data
B36: Absolute data for COGS | C36: (VND)
B37: Raw Materials cost | C37: (VND)
B38: Labor cost | C38: (VND)
B39: Fixed A depriciation cost | C39: (VND)
B40: Outsources cost and other cost | C40: (VND)
B42: Relative data for COGS | C42: (VND)
B43: Raw Materials cost | C43: (VND)
B44: Labor cost | C44: (VND)
B45: Fixed A depriciation cost | C45: (VND)
B46: Outsources cost and other cost | C46: (VND)
B48: B. Detail Breakdown and Forecast
B49: Raw materials cost | C49: (VND)
B50: % Growth YoY | C50: (%)
B51: 1. Sector 1 | C51: (VND)
B52: % Selling volume/ Capacity | C52: (%)
B53: sector 1 world price | C53: (USD/kg)
B54: % Growth YoY | C54: (%)
C55: (USD/kg)
B56: % Growth YoY | C56: (%)
C57: (USD/bbl)
B58: % Growth YoY | C58: (%)
B60: Average growth of sector 1 cost in COGS (Natural : ..%, Raw oil: ..%) | C60: (%)
B61: Average CAGR of Natura Sector 1 in last four year data | C61: (%)
B62: % Sector 1 price CAGR in five years | C62: (%)
B63: % Sector 1 price CAGR in five years | C63: (%)
B64: Growth of Synthentic Rubbers (60-70% Raw oil) | C64: (%)
B66: 2. Sector 2 | C66: (VND)
B67: % Selling volume/ Capacity | C67: (%)
B68: % Growth YoY | C68: (%)
B69: Sector 2 price World Bank | C69: (USD/mt)
B70: % Growth YoY | C70: (%)
C71: (%)
B73: 3. Sector 3 | C73: (VND)
B74: % Selling volume/ Capacity | C74: (%)
B75: % Growth YoY | C75: (%)
B76: World Sector 3 price | C76: (USD/mt)
B77: % Growth YoY | C77: (%)
B79: 4. Others raw materials cost | C79: (VND)
B80: % Selling volume/ Capacity | C80: (%)
B81: % Growth YoY | C81: (%)
B82: %CAGR in the 2017 - 2021 | C82: (%)
B84: Labor cost | C84: (VND)
B85: % As a revenue | C85: (%)
B86: % Growth YoY | C86: (%)
... B89: % Growth YoY | C89: (%)
B91: Depriciation year numbers | C91: 10
B92: Radial depricitiaon factory by year | C92: (VND)
B93: % Growth YoY | C93: (%)
B94: Total Investment in Phase 1 (Fully depreciated) | C94: (VND)
B95: Beginning | C95: (VND)
B96: Deprication by year | C96: (VND)
B97: Ending | C97: (VND)
B98: Total Investment in Phase 2 | C98: (VND)
B99: Beginning | C99: (VND)
B100: Deprication by year | C100: (VND)
B101: Ending | C101: (VND)
B102: Total Investment in Phase 3.1 | C102: (VND)
B103: Beginning | C103: (VND)
... B132: Net other income (expenses) | C132: (VND)

Sheet IPc_WACC and Beta
A1: 1. Input data | K1: 2. Process data | O1: 3. Assumptions
A2: a. Trading data | H2: b. Other data and Process Raw data | K2: a. ERP
A3: Date | B3: VN-Index | D3: YEG | H3: Tickers | I3: Data | K3: Method 1 | L3: ERP VN = ERP US + CRP VN (CDS, có điều chỉnh) | O3: Tickers | P3: Data
B4: Last Price | C4: Change | D4: Last Price | E4: Change | H4: ERP US (Damodaran) | I4: 0.04225 | L4: ERP US | M4: =I4 -> 0.04225 | O4: Risk free rate | P4: 0.042
B5: PX_LAST | C5: (%) | D5: PX_LAST | E5: (%) | H5: Chênh lệch CDS (Damodaran) | I5: 0.0126 | L5: Chên lệch CDS | M5: =I5 -> 0.0126 | O5: Beta (U) | P5: =I9 -> 0.82336143
A6: 46136 | B6: 1853.29 | C6: =(B6-B7)/B7 -> -0.0091265853 | D6: 9990 | E6: =(D6-D7)/D7 -> 0.001002004 | H6: Chênh lệch Moody's Rating (Damodaran) | I6: 0.0283 | L6: Hệ số điều chỉnh | M6: =I11 -> 1.3 | O6: ERP VN | P6: =M16 -> 0.08112
A7: 46135 | B7: 1870.36 | C7: =(B7-B8)/B8 -> 0.0070317127 | D7: 9980 | E7: =(D7-D8)/D8 -> -0.021568627 | H7: ERP VN | I7: 0.0832 | L7: ERP VN | M7: =M4+M5*M6 -> 0.05863 | O7: Current Cost of Equity (Ke) | P7: =P4+P5*P6 -> 0.10879108
A8: 46134 | B8: 1857.3 | C8: =(B8-B9)/B9 -> 0.012991688 | D8: 10200 | E8: =(D8-D9)/D9 -> 0.0049261084 | H8: Thuế suất thuế TNDN | I8: 0.2 | O8: Current Cost of Debt | P8: =OD_IS!H57 -> 0.075923967
A9: 46133 | B9: 1833.48 | C9: =(B9-B10)/B10 -> -0.0019759296 | D9: 10150 | E9: =(D9-D10)/D10 -> -0.0097560976 | H9: Hệ số Beta YEG (SLOPE 1Y) | I9: =SLOPE(E6:E250,C6:C250) -> 0.82336143 | K9: Method 2 | L9: ERP VN = ERP US + CRP VN (Moody's, có điều chỉnh) | O9: Tax rate | P9: 0.2
A10: 46132 | B10: 1837.11 | C10: =(B10-B11)/B11 -> 0.010973107 | D10: 10250 | E10: =(D10-D11)/D11 -> -0.0048543689 | H10: Hệ số D/E in 2024 | I10: =('IP_BS Raw'!H83+'IP_BS Raw'!H96)/'IP_BS Raw'!H103 -> 0.38494462 | L10: ERP US | M10: =I4 -> 0.04225 | O10: Current Cost of Debt after tax (Kd) | P10: =P8*(1-P9) -> 0.060739173
A11: 46129 | B11: 1817.17 | C11: =(B11-B12)/B12 -> -0.001461675 | D11: 10300 | E11: =(D11-D12)/D12 -> 0.0048780488 | H11: Hệ số | I11: 1.3 | L11: Chên lệch Moody's Rating | M11: =I6 -> 0.0283 | O11: D/E | P11: =I10 -> 0.38494462
A12: 46128 | B12: 1819.83 | C12: =(B12-B13)/B13 -> 0.010651709 | D12: 10250 | E12: =(D12-D13)/D13 -> -0.0048543689 | H12: Standard Deviation of VN-Index | I12: =_xlfn.STDEV.S(C6:C250) -> 0.013145251 | L12: Hệ số điều chỉnh | M12: =I11 -> 1.3 | O12: D/(D+E) | P12: =P11/(1+P11) -> 0.27794947
A13: 46127 | B13: 1800.65 | C13: =(B13-B14)/B14 -> 0.014079351 | D13: 10300 | E13: =(D13-D14)/D14 -> -0.019047619 | L13: ERP VN | M13: =M10+M11*M12 -> 0.07904 | O13: Current WACC | P13: =P7*(1-P12)+P12*P10 -> 0.095435078
A14: 46126 | B14: 1775.65 | C14: =(B14-B15)/B15 -> 0.0094885614 | D14: 10500 | E14: =(D14-D15)/D15 -> -0.018691589
A15: 46125 | B15: 1758.96 | C15: =(B15-B16)/B16 -> 0.00512 | D15: 10700 | E15: =(D15-D16)/D16 -> 0.033816425 | K15: Average | L15: MAX of two methods | M15: =MAX(M7,M13) -> 0.07904
A16: 46122 | B16: 1750 | C16: =(B16-B17)/B17 -> 0.0076698068 | D16: 10350 | E16: =(D16-D17)/D17 -> 0.035 | K16: Final | L16: Average of MAX & ERP VN (Damodaran) | M16: =AVERAGE(M15,I7) -> 0.08112
A17: 46121 | B17: 1736.68 | C17: =(B17-B18)/B18 -> -0.011311947 | D17: 10000 | E17: =(D17-D18)/D18 -> -0.0099009901
A18: 46120 | B18: 1756.55 | C18: =(B18-B19)/B19 -> 0.047098728 | D18: 10100 | E18: =(D18-D19)/D19 -> 0.026422764
A19: 46119 | B19: 1677.54 | C19: =(B19-B20)/B20 -> 0.0015223971 | D19: 9840 | E19: =(D19-D20)/D20 -> 0.0051072523
A20: 46118 | B20: 1674.99 | C20: =(B20-B21)/B21 -> -0.0053739816 | D20: 9790 | E20: =(D20-D21)/D21 -> -0.015090543
A21: 46115 | B21: 1684.04 | C21: =(B21-B22)/B22 -> -0.0063605575 | D21: 9940 | E21: =(D21-D22)/D22 -> -0.006
A22: 46114 | B22: 1694.82 | C22: =(B22-B23)/B23 -> -0.0047623801 | D22: 10000 | E22: =(D22-D23)/D23 -> -0.014778325
A23: 46113 | B23: 1702.93 | C23: =(B23-B24)/B24 -> 0.016984276 | D23: 10150 | E23: =(D23-D24)/D24 -> 0.015
A24: 46112 | B24: 1674.49 | C24: =(B24-B25)/B25 -> 0.007187797 | D24: 10000 | E24: =(D24-D25)/D25 -> 0.0050251256
A25: 46111 | B25: 1662.54 | C25: =(B25-B26)/B26 -> -0.006133429 | D25: 9950 | E25: =(D25-D26)/D26 -> -0.0099502488
A26: 46108 | B26: 1672.8 | C26: =(B26-B27)/B27 -> 0.017128473 | D26: 10050 | E26: =(D26-D27)/D27 -> 0.005
A27: 46107 | B27: 1644.63 | C27: =(B27-B28)/B28 -> -0.0081775912 | D27: 10000 | E27: =(D27-D28)/D28 -> -0.0099009901
A28: 46106 | B28: 1658.19 | C28: =(B28-B29)/B29 -> 0.026889278 | D28: 10100 | E28: =(D28-D29)/D29 -> 0.017119839
... A250: 45783 | B250: 1241.95 | C250: =(B250-B251)/B251 -> 0.0015321963 | D250: 11750 | E250: =(D250-D251)/D251 -> -0.0042372881
A251: 45782 | B251: 1240.05 | D251: 11800

Sheet OD_BS
G2: 45291 | H2: =DATE(YEAR(G2),MONTH(G2)+13,0) -> 45657 | I2: =DATE(YEAR(H2),MONTH(H2)+13,0) -> 46022 | J2: =DATE(YEAR(I2),MONTH(I2)+13,0) -> 46387 | K2: =DATE(YEAR(J2),MONTH(J2)+13,0) -> 46752 | L2: =DATE(YEAR(K2),MONTH(K2)+13,0) -> 47118 | M2: =DATE(YEAR(L2),MONTH(L2)+13,0) -> 47483 | N2: =DATE(YEAR(M2),MONTH(M2)+13,0) -> 47848
B3: Items | C3: Unit | D3: ='IP_BS Raw'!E2 -> 2021 | E3: =D3+1 -> 2022 | F3: =E3+1 -> 2023 | G3: =F3+1 -> 2024 | H3: =G3+1 -> 2025 | I3: =H3+1 -> 2026 | J3: =I3+1 -> 2027 | K3: =J3+1 -> 2028 | L3: =K3+1 -> 2029 | ... N3: =M3+1 -> 2031
B4: Total Asset | C4: (VNDbn) | D4: =D5+D11 -> 1388467146198 | E4: =E5+E11 -> 1311932297572 | F4: =F5+F11 -> 1891225676406 | G4: =G5+G11 -> 2814732850457 | H4: =H5+H11 -> 3066234160063 | I4: =I5+I11 -> 2.3703758e+12 | J4: =J5+J11 -> 2.2796022e+12 | K4: =K5+K11 -> 2.1710505e+12 | ... N4: =N5+N11 -> 1.8171291e+12
B5: Current Asset | C5: (VND bn) | D5: =SUM(D6:D10) -> 1134580036184 | E5: =SUM(E6:E10) -> 623158641225 | F5: =SUM(F6:F10) -> 947639699363 | G5: =SUM(G6:G10) -> 1305306889451 | H5: =SUM(H6:H10) -> 1870935494083 | I5: =SUM(I6:I10) -> 1.2972302e+12 | J5: =SUM(J6:J10) -> 1.3389789e+12 | K5: =SUM(K6:K10) -> 1.3864727e+12 | ... N5: =SUM(N6:N10) -> 1.5183e+12
B6: Cash & Equivalents | C6: (VND bn) | D6: ='IP_BS Raw'!E7 -> 4321225874 | E6: ='IP_BS Raw'!F7 -> 26473013864 | F6: ='IP_BS Raw'!G7 -> 8461339357 | G6: ='IP_BS Raw'!H7 -> 136236074178 | H6: ='IP_BS Raw'!I7 -> 288524181242 | I6: =H6 -> 288524181242 | J6: =I6 -> 288524181242 | K6: =J6 -> 288524181242 | L6: =K6 -> 288524181242 | M6: =L6 -> 288524181242 | N6: =M6 -> 288524181242
B7: Short-term investments | C7: (VND bn) | D7: ='IP_BS Raw'!E10 -> 4900000000 | E7: ='IP_BS Raw'!F10 -> 50000000 | F7: ='IP_BS Raw'!G10 -> 230000000 | G7: ='IP_BS Raw'!H10 -> 1230000000 | H7: ='IP_BS Raw'!I10 -> 164600000000 | I7: =H7 -> 164600000000 | J7: =I7 -> 164600000000 | K7: =J7 -> 164600000000 | L7: =K7 -> 164600000000 | M7: =L7 -> 164600000000 | N7: =M7 -> 164600000000
B8: Account Receivables | C8: (VND bn) | D8: ='IP_BS Raw'!E14 -> 1059557585612 | E8: ='IP_BS Raw'!F14 -> 541296932112 | F8: ='IP_BS Raw'!G14 -> 845395421575 | G8: ='IP_BS Raw'!H14 -> 1101930451740 | H8: ='IP_BS Raw'!I14 -> 1305199947643 | I8: =PD_Operation!I16/365*OD_IS!I4 -> 7.0053107e+11 | J8: =PD_Operation!J16/365*OD_IS!J4 -> 7.1220659e+11 | K8: =PD_Operation!K16/365*OD_IS!K4 -> 7.3713382e+11 | L8: =PD_Operation!L16/365*OD_IS!L4 -> 7.2730537e+11 | M8: =PD_Operation!M16/365*OD_IS!M4 -> 7.854898e+11 | N8: =PD_Operation!N16/365*OD_IS!N4 -> 8.2476429e+11
B9: Inventories | C9: (VND bn) | D9: ='IP_BS Raw'!E23 -> 30723500694 | E9: ='IP_BS Raw'!F23 -> 15511002401 | F9: ='IP_BS Raw'!G23 -> 29168608393 | G9: ='IP_BS Raw'!H23 -> 40804852414 | H9: ='IP_BS Raw'!I23 -> 97855839839 | I9: =PD_Operation!I17/365*(-OD_IS!I5) -> 1.0791689e+11 | J9: =PD_Operation!J17/365*(-OD_IS!J5) -> 1.3014529e+11 | K9: =PD_Operation!K17/365*(-OD_IS!K5) -> 1.4618645e+11 | L9: =PD_Operation!L17/365*(-OD_IS!L5) -> 1.5840346e+11 | M9: =PD_Operation!M17/365*(-OD_IS!M5) -> 1.6898945e+11 | N9: =PD_Operation!N17/365*(-OD_IS!N5) -> 1.7743892e+11
B10: Other Current Asset | C10: (VND bn) | D10: ='IP_BS Raw'!E26 -> 35077724004 | E10: ='IP_BS Raw'!F26 -> 39827692848 | F10: ='IP_BS Raw'!G26 -> 64384330038 | G10: ='IP_BS Raw'!H26 -> 25105511119 | H10: ='IP_BS Raw'!I26 -> 14755525359 | I10: =PD_Operation!I19*OD_IS!I4 -> 3.5658063e+10 | J10: =PD_Operation!J19*OD_IS!J4 -> 4.3502837e+10 | K10: =PD_Operation!K19*OD_IS!K4 -> 5.0028262e+10 | L10: =PD_Operation!L19*OD_IS!L4 -> 5.5531371e+10 | M10: =PD_Operation!M19*OD_IS!M4 -> 5.9973881e+10 | N10: =PD_Operation!N19*OD_IS!N4 -> 6.2972575e+10
B11: Non-Current Asset | C11: (VND bn) | D11: =D14+D15+D16+D17 -> 253887110014 | E11: =E14+E15+E16+E17 -> 688773656347 | F11: =F14+F15+F16+F17 -> 943585977043 | G11: =G14+G15+G16+G17 -> 1509425961006 | H11: =H14+H15+H16+H17 -> 1195298665980 | I11: =I14+I15+I16+I17 -> 1.0731456e+12 | J11: =J14+J15+J16+J17 -> 9.4062329e+11 | K11: =K14+K15+K16+K17 -> 7.8457777e+11 | ... N11: =N14+N15+N16+N17 -> 2.9882917e+11
B12: Gross PPE (incl. CIP & Goodwill) | C12: (VND bn) | D12: ='IP_BS Raw'!E43+'IP_BS Raw'!E46+'IP_BS Raw'!E49+'IP_BS Raw'!E57+'IP_BS Raw'!E70 -> 78197611614 | E12: ='IP_BS Raw'!F43+'IP_BS Raw'!F46+'IP_BS Raw'!F49+'IP_BS Raw'!F57+'IP_BS Raw'!F70 -> 144636525187 | F12: ='IP_BS Raw'!G43+'IP_BS Raw'!G46+'IP_BS Raw'!G49+'IP_BS Raw'!G57+'IP_BS Raw'!G70 -> 160812961982 | G12: ='IP_BS Raw'!H43+'IP_BS Raw'!H46+'IP_BS Raw'!H49+'IP_BS Raw'!H57+'IP_BS Raw'!H70 -> 624540055042 | H12: ='IP_BS Raw'!I43+'IP_BS Raw'!I46+'IP_BS Raw'!I49+'IP_BS Raw'!I57+'IP_BS Raw'!I70 -> 649825980677 | I12: =H12+(-OD_CF!I10) -> 7.776729e+11 | J12: =I12+(-OD_CF!J10) -> 9.076506e+11 | K12: =J12+(-OD_CF!K10) -> 1.0272301e+12 | L12: =K12+(-OD_CF!L10) -> 1.1599633e+12 | M12: =L12+(-OD_CF!M10) -> 1.3033152e+12 | N12: =M12+(-OD_CF!N10) -> 1.4538347e+12
B13: Accumulated D&A | C13: (VND bn) | D13: ='IP_BS Raw'!E44+'IP_BS Raw'!E50+'IP_BS Raw'!E47 -> -26027784727 | E13: ='IP_BS Raw'!F44+'IP_BS Raw'!F50+'IP_BS Raw'!F47 -> -38889210546 | F13: ='IP_BS Raw'!G44+'IP_BS Raw'!G50+'IP_BS Raw'!G47 -> -30312993339 | G13: ='IP_BS Raw'!H44+'IP_BS Raw'!H50+'IP_BS Raw'!H47 -> -50969214414 | H13: ='IP_BS Raw'!I44+'IP_BS Raw'!I50+'IP_BS Raw'!I47 -> -99467544716 | I13: =H13+(-OD_CF!I6) -> -349467544716 | J13: =I13+(-OD_CF!J6) -> -611967544716 | K13: =J13+(-OD_CF!K6) -> -887592544716 | L13: =K13+(-OD_CF!L6) -> -1176998794716 | M13: =L13+(-OD_CF!M6) -> -1480875357216 | N13: =M13+(-OD_CF!N6) -> -1799945747841
B14: Net Fixed Assets | C14: (VND bn) | D14: =D12+D13 -> 52169826887 | E14: =E12+E13 -> 105747314641 | F14: =F12+F13 -> 130499968643 | G14: =G12+G13 -> 573570840628 | H14: =H12+H13 -> 550358435961 | I14: =I12+I13 -> 4.2820536e+11 | J14: =J12+J13 -> 2.9568306e+11 | K14: =K12+K13 -> 1.3963754e+11 | ... N14: =N12+N13 -> -3.4611106e+11
B15: (CIP merged into Fixed Assets) | C15: (VND bn) | D15: 0 | E15: 0 | F15: 0 | G15: 0 | H15: 0 | I15: 0 | J15: 0 | K15: 0 | L15: 0 | M15: 0 | N15: 0
B16: Long-term investment | C16: (VND bn) | D16: ='IP_BS Raw'!E58 -> 133341086382 | E16: ='IP_BS Raw'!F58 -> 140347514642 | F16: ='IP_BS Raw'!G58 -> 383408540098 | G16: ='IP_BS Raw'!H58 -> 111178423767 | H16: ='IP_BS Raw'!I58 -> 124915632725 | I16: =H16 -> 124915632725 | J16: =I16 -> 124915632725 | K16: =J16 -> 124915632725 | L16: =K16 -> 124915632725 | M16: =L16 -> 124915632725 | N16: =M16 -> 124915632725
B17: Other Long-term asset | C17: (VND bn) | D17: ='IP_BS Raw'!E33+'IP_BS Raw'!E52+'IP_BS Raw'!E64+'IP_BS Raw'!E65 -> 68376196745 | E17: ='IP_BS Raw'!F33+'IP_BS Raw'!F52+'IP_BS Raw'!F64+'IP_BS Raw'!F65 -> 442678827064 | F17: ='IP_BS Raw'!G33+'IP_BS Raw'!G52+'IP_BS Raw'!G64+'IP_BS Raw'!G65 -> 429677468302 | G17: ='IP_BS Raw'!H33+'IP_BS Raw'!H52+'IP_BS Raw'!H64+'IP_BS Raw'!H65 -> 824676696611 | H17: ='IP_BS Raw'!I33+'IP_BS Raw'!I52+'IP_BS Raw'!I64+'IP_BS Raw'!I65 -> 520024597294 | I17: =H17 -> 520024597294 | J17: =I17 -> 520024597294 | K17: =J17 -> 520024597294 | L17: =K17 -> 520024597294 | M17: =L17 -> 520024597294 | N17: =M17 -> 520024597294
B18: Total Liabilities and Stockholder' equity | C18: (VNDbn) | D18: =D19+D23+D26 -> 1059227672799 | E18: =E19+E23+E26 -> 909883790040 | F18: =F19+F23+F26 -> 889451768689 | G18: =G19+G23+G26 -> 1195908489386 | H18: =H19+H23+H26 -> 806242806747 | I18: =I19+I23+I26 -> 2.3703758e+12 | J18: =J19+J23+J26 -> 2.2796022e+12 | K18: =K19+K23+K26 -> 2.1710505e+12 | ... N18: =N19+N23+N26 -> 2.5805081e+12
B19: Current Liabilities | C19: (VND bn) | D19: =SUM(D20:D22) -> 403533140176 | E19: =SUM(E20:E22) -> 315495843209 | F19: =SUM(F20:F22) -> 408623646511 | G19: =SUM(G20:G22) -> 962985040933 | H19: =SUM(H20:H22) -> 630726249783 | I19: =SUM(I20:I22) -> 2.1140787e+12 | J19: =SUM(J20:J22) -> 1.9139892e+12 | K19: =SUM(K20:K22) -> 1.6521958e+12 | ... N19: =SUM(N20:N22) -> 1.3734703e+12
B20: Account Payables | C20: (VND bn) | D20: ='IP_BS Raw'!E74 -> 87325315040 | E20: ='IP_BS Raw'!F74 -> 83181799835 | F20: ='IP_BS Raw'!G74 -> 98153102705 | G20: ='IP_BS Raw'!H74 -> 137590758890 | H20: ='IP_BS Raw'!I74 -> 149093578776 | I20: =PD_Operation!I18/365*(-OD_IS!I5) -> 1.9408795e+11 | J20: =PD_Operation!J18/365*(-OD_IS!J5) -> 2.340656e+11 | K20: =PD_Operation!K18/365*(-OD_IS!K5) -> 2.6291555e+11 | L20: =PD_Operation!L18/365*(-OD_IS!L5) -> 2.8488778e+11 | M20: =PD_Operation!M18/365*(-OD_IS!M5) -> 3.0392662e+11 | N20: =PD_Operation!N18/365*(-OD_IS!N5) -> 3.1912295e+11
B21: Short-term debt | C21: (VND bn) | D21: ='IP_BS Raw'!E83 -> 130796216812 | E21: ='IP_BS Raw'!F83 -> 94317807400 | F21: ='IP_BS Raw'!G83 -> 171352690912 | G21: ='IP_BS Raw'!H83 -> 527364096445 | H21: ='IP_BS Raw'!I83 -> 304271257481 | I21: =MAX(PD_Operation!$H$24, I4-I20-I22-I24-I25-I27-I28-I29-I30-I31-I32) -> 1.4952621e+12 | J21: =MAX(PD_Operation!$H$24, J4-J20-J22-J24-J25-J27-J28-J29-J30-J31-J32) -> 1.1617545e+12 | K21: =MAX(PD_Operation!$H$24, K4-K20-K22-K24-K25-K27-K28-K29-K30-K31-K32) -> 7.9338587e+11 | L21: =MAX(PD_Operation!$H$24, L4-L20-L22-L24-L25-L27-L28-L29-L30-L31-L32) -> 3.5234983e+11 | M21: =MAX(PD_Operation!$H$24, M4-M20-M22-M24-M25-M27-M28-M29-M30-M31-M32) -> 304271257481 | N21: =MAX(PD_Operation!$H$24, N4-N20-N22-N24-N25-N27-N28-N29-N30-N31-N32) -> 304271257481
B22: Other Current Liabilities | C22: (VND bn) | D22: ='IP_BS Raw'!E75+'IP_BS Raw'!E76+'IP_BS Raw'!E77+'IP_BS Raw'!E78+'IP_BS Raw'!E79+'IP_BS Raw'!E80+'IP_BS Raw'!E81+'IP_BS Raw'!E82+'IP_BS Raw'!E84+'IP_BS Raw'!E85+'IP_BS Raw'!E86+'IP_BS Raw'!E87 -> 185411608324 | E22: ='IP_BS Raw'!F75+'IP_BS Raw'!F76+'IP_BS Raw'!F77+'IP_BS Raw'!F78+'IP_BS Raw'!F79+'IP_BS Raw'!F80+'IP_BS Raw'!F81+'IP_BS Raw'!F82+'IP_BS Raw'!F84+'IP_BS Raw'!F85+'IP_BS Raw'!F86+'IP_BS Raw'!F87 -> 137996235974 | F22: ='IP_BS Raw'!G75+'IP_BS Raw'!G76+'IP_BS Raw'!G77+'IP_BS Raw'!G78+'IP_BS Raw'!G79+'IP_BS Raw'!G80+'IP_BS Raw'!G81+'IP_BS Raw'!G82+'IP_BS Raw'!G84+'IP_BS Raw'!G85+'IP_BS Raw'!G86+'IP_BS Raw'!G87 -> 139117852894 | G22: ='IP_BS Raw'!H75+'IP_BS Raw'!H76+'IP_BS Raw'!H77+'IP_BS Raw'!H78+'IP_BS Raw'!H79+'IP_BS Raw'!H80+'IP_BS Raw'!H81+'IP_BS Raw'!H82+'IP_BS Raw'!H84+'IP_BS Raw'!H85+'IP_BS Raw'!H86+'IP_BS Raw'!H87 -> 298030185598 | H22: ='IP_BS Raw'!I75+'IP_BS Raw'!I76+'IP_BS Raw'!I77+'IP_BS Raw'!I78+'IP_BS Raw'!I79+'IP_BS Raw'!I80+'IP_BS Raw'!I81+'IP_BS Raw'!I82+'IP_BS Raw'!I84+'IP_BS Raw'!I85+'IP_BS Raw'!I86+'IP_BS Raw'!I87 -> 177361413526 | I22: =PD_Operation!I20*OD_IS!I4 -> 4.247287e+11 | J22: =PD_Operation!J20*OD_IS!J4 -> 5.1816902e+11 | K22: =PD_Operation!K20*OD_IS!K4 -> 5.9589437e+11 | L22: =PD_Operation!L20*OD_IS!L4 -> 6.6144275e+11 | M22: =PD_Operation!M20*OD_IS!M4 -> 7.1435817e+11 | N22: =PD_Operation!N20*OD_IS!N4 -> 7.5007608e+11
B23: Non-Current Liabilities | C23: (VND bn) | D23: =SUM(D24:D25) -> 91046386521 | E23: =SUM(E24:E25) -> 18701860119 | F23: =SUM(F24:F25) -> 68475256799 | G23: =SUM(G24:G25) -> 50006060793 | H23: =SUM(H24:H25) -> 44904016385 | I23: =SUM(I24:I25) -> 44904016385 | J23: =SUM(J24:J25) -> 44904016385 | K23: =SUM(K24:K25) -> 44904016385 | ... N23: =SUM(N24:N25) -> 44904016385
B24: Long-term Debt | C24: (VND bn) | D24: ='IP_BS Raw'!E96 -> 71000000000 | E24: ='IP_BS Raw'!F96 -> 1000000000 | F24: ='IP_BS Raw'!G96 -> 39014432856 | G24: ='IP_BS Raw'!H96 -> 50006060793 | H24: ='IP_BS Raw'!I96 -> 36866802037 | I24: =PD_Operation!I25 -> 36866802037 | J24: =PD_Operation!J25 -> 36866802037 | K24: =PD_Operation!K25 -> 36866802037 | L24: =PD_Operation!L25 -> 36866802037 | M24: =PD_Operation!M25 -> 36866802037 | N24: =PD_Operation!N25 -> 36866802037
B25: Other Non-Current Liabilities | C25: (VND bn) | D25: ='IP_BS Raw'!E88-'IP_BS Raw'!E96 -> 20046386521 | E25: ='IP_BS Raw'!F88-'IP_BS Raw'!F96 -> 17701860119 | F25: ='IP_BS Raw'!G88-'IP_BS Raw'!G96 -> 29460823943 | G25: ='IP_BS Raw'!H88-'IP_BS Raw'!H96 -> 0 | H25: ='IP_BS Raw'!I88-'IP_BS Raw'!I96 -> 8037214348 | I25: =H25 -> 8037214348 | J25: =I25 -> 8037214348 | K25: =J25 -> 8037214348 | L25: =K25 -> 8037214348 | M25: =L25 -> 8037214348 | N25: =M25 -> 8037214348
B26: Total stockholders' equity | C26: (VND bn) | D26: =SUM(D27:D32) -> 564648146102 | E26: =SUM(E27:E32) -> 575686086712 | F26: =SUM(F27:F32) -> 412352865379 | G26: =SUM(G27:G32) -> 182917387660 | H26: =SUM(H27:H32) -> 130612540579 | I26: =SUM(I27:I32) -> 2.1139306e+11 | J26: =SUM(J27:J32) -> 3.20709e+11 | K26: =SUM(K27:K32) -> 4.7395068e+11 | ... N26: =SUM(N27:N32) -> 1.1621338e+12
B27: Common shares value | C27: (VND bn) | D27: ='IP_BS Raw'!E106 -> 0 | E27: ='IP_BS Raw'!F106 -> 0 | F27: ='IP_BS Raw'!G106 -> 0 | G27: ='IP_BS Raw'!H106 -> 0 | H27: ='IP_BS Raw'!I106 -> 0 | I27: =H27 -> 0 | J27: =I27 -> 0 | K27: =J27 -> 0 | L27: =K27 -> 0 | M27: =L27 -> 0 | N27: =M27 -> 0
B28: Preferred shares value | C28: (VND bn) | D28: ='IP_BS Raw'!E107 -> 0 | E28: ='IP_BS Raw'!F107 -> 0 | F28: ='IP_BS Raw'!G107 -> 0 | G28: ='IP_BS Raw'!H107 -> 0 | H28: ='IP_BS Raw'!I107 -> 0 | I28: =H28 -> 0 | J28: =I28 -> 0 | K28: =J28 -> 0 | L28: =K28 -> 0 | M28: =L28 -> 0 | N28: =M28 -> 0
B29: Share premium | C29: (VND bn) | D29: ='IP_BS Raw'!E108 -> 550873478254 | E29: ='IP_BS Raw'!F108 -> 550873478254 | F29: ='IP_BS Raw'!G108 -> 140518254 | G29: ='IP_BS Raw'!H108 -> 140518254 | H29: ='IP_BS Raw'!I108 -> 75418254 | I29: =H29 -> 75418254 | J29: =I29 -> 75418254 | K29: =J29 -> 75418254 | L29: =K29 -> 75418254 | M29: =L29 -> 75418254 | N29: =M29 -> 75418254
B30: Retained earnings | C30: (VND bn) | D30: ='IP_BS Raw'!E118 -> 20536615720 | E30: ='IP_BS Raw'!F118 -> 12261220660 | F30: ='IP_BS Raw'!G118 -> 708163 | G30: ='IP_BS Raw'!H118 -> 125708063567 | H30: ='IP_BS Raw'!I118 -> 76561931411 | I30: =H30+OD_IS!I21-(OD_IS!I21*PD_Operation!I26) -> 1.5734245e+11 | J30: =I30+OD_IS!J21-(OD_IS!J21*PD_Operation!J26) -> 2.6665839e+11 | K30: =J30+OD_IS!K21-(OD_IS!K21*PD_Operation!K26) -> 4.1990007e+11 | L30: =K30+OD_IS!L21-(OD_IS!L21*PD_Operation!L26) -> 6.2463415e+11 | M30: =L30+OD_IS!M21-(OD_IS!M21*PD_Operation!M26) -> 8.6718506e+11 | N30: =M30+OD_IS!N21-(OD_IS!N21*PD_Operation!N26) -> 1.1080832e+12
B31: Minority interests | C31: (VND bn) | D31: ='IP_BS Raw'!E121 -> -6506464721 | E31: ='IP_BS Raw'!F121 -> 12551387798 | F31: ='IP_BS Raw'!G121 -> 412211638962 | G31: ='IP_BS Raw'!H121 -> 57068805839 | H31: ='IP_BS Raw'!I121 -> 53940074673 | I31: =H31 -> 53940074673 | J31: =I31 -> 53940074673 | K31: =J31 -> 53940074673 | L31: =K31 -> 53940074673 | M31: =L31 -> 53940074673 | N31: =M31 -> 53940074673
B32: Other Equity | C32: (VND bn) | D32: ='IP_BS Raw'!E109+'IP_BS Raw'!E110+'IP_BS Raw'!E111+'IP_BS Raw'!E112+'IP_BS Raw'!E113+'IP_BS Raw'!E114+'IP_BS Raw'!E115+'IP_BS Raw'!E116+'IP_BS Raw'!E117+'IP_BS Raw'!E122+'IP_BS Raw'!E125 -> -255483151 | E32: ='IP_BS Raw'!F109+'IP_BS Raw'!F110+'IP_BS Raw'!F111+'IP_BS Raw'!F112+'IP_BS Raw'!F113+'IP_BS Raw'!F114+'IP_BS Raw'!F115+'IP_BS Raw'!F116+'IP_BS Raw'!F117+'IP_BS Raw'!F122+'IP_BS Raw'!F125 -> 0 | F32: ='IP_BS Raw'!G109+'IP_BS Raw'!G110+'IP_BS Raw'!G111+'IP_BS Raw'!G112+'IP_BS Raw'!G113+'IP_BS Raw'!G114+'IP_BS Raw'!G115+'IP_BS Raw'!G116+'IP_BS Raw'!G117+'IP_BS Raw'!G122+'IP_BS Raw'!G125 -> 0 | G32: ='IP_BS Raw'!H109+'IP_BS Raw'!H110+'IP_BS Raw'!H111+'IP_BS Raw'!H112+'IP_BS Raw'!H113+'IP_BS Raw'!H114+'IP_BS Raw'!H115+'IP_BS Raw'!H116+'IP_BS Raw'!H117+'IP_BS Raw'!H122+'IP_BS Raw'!H125 -> 0 | H32: ='IP_BS Raw'!I109+'IP_BS Raw'!I110+'IP_BS Raw'!I111+'IP_BS Raw'!I112+'IP_BS Raw'!I113+'IP_BS Raw'!I114+'IP_BS Raw'!I115+'IP_BS Raw'!I116+'IP_BS Raw'!I117+'IP_BS Raw'!I122+'IP_BS Raw'!I125 -> 35116241 | I32: =H32 -> 35116241 | J32: =I32 -> 35116241 | K32: =J32 -> 35116241 | L32: =K32 -> 35116241 | M32: =L32 -> 35116241 | N32: =M32 -> 35116241
B34: Backing Test | D34: =D4-D18 -> 329239473399 | E34: =E4-E18 -> 402048507532 | F34: =F4-F18 -> 1001773907717 | G34: =G4-G18 -> 1618824361071 | H34: =H4-H18 -> 2259991353316 | I34: =I4-I18 -> 0 | J34: =J4-J18 -> 0 | K34: =K4-K18 -> 0 | ... N34: =N4-N18 -> -7.6337901e+11
B36: Change in Working Capital | E36: =SUM(E37:E41) -> 477164295394 | F36: =SUM(F37:F41) -> -326219812855 | G36: =SUM(G37:G41) -> -30542466378 | H36: =SUM(H37:H41) -> -359136449754 | I36: =SUM(I37:I41) -> 8.6606695e+11 | J36: =SUM(J37:J41) -> 9.166928e+10 | K36: =SUM(K37:K41) -> 5.908148e+10 | L36: =SUM(L37:L41) -> 7.962894e+10 | ... N36: =SUM(N37:N41) -> 1.9158318e+08
B37: (Ins) Des in Account Receivables | E37: =D8-E8 -> 518260653500 | F37: =E8-F8 -> -304098489463 | G37: =F8-G8 -> -256535030165 | H37: =G8-H8 -> -203269495903 | I37: =H8-I8 -> 6.0466888e+11 | J37: =I8-J8 -> -1.1675518e+10 | K37: =J8-K8 -> -2.4927231e+10 | L37: =K8-L8 -> 9.8284509e+09 | ... N37: =M8-N8 -> -3.927449e+10
B38: (Ins) Des in Inventory | E38: =D9-E9 -> 15212498293 | F38: =E9-F9 -> -13657605992 | G38: =F9-G9 -> -11636244021 | H38: =G9-H9 -> -57050987425 | I38: =H9-I9 -> -1.006105e+10 | J38: =I9-J9 -> -2.2228398e+10 | K38: =J9-K9 -> -1.6041163e+10 | L38: =K9-L9 -> -1.2217011e+10 | ... N38: =M9-N9 -> -8.4494725e+09
B39: (Ins) Des in Other Current Asset | E39: =D10-E10 -> -4749968844 | F39: =E10-F10 -> -24556637190 | G39: =F10-G10 -> 39278818919 | H39: =G10-H10 -> 10349985760 | I39: =H10-I10 -> -2.0902538e+10 | J39: =I10-J10 -> -7.8447738e+09 | K39: =J10-K10 -> -6.5254255e+09 | L39: =K10-L10 -> -5.5031088e+09 | ... N39: =M10-N10 -> -2.998694e+09
B40: Ins (Des) in Account Payable | E40: =E20-D20 -> -4143515205 | F40: =F20-E20 -> 14971302870 | G40: =G20-F20 -> 39437656185 | H40: =H20-G20 -> 11502819886 | I40: =I20-H20 -> 4.499437e+10 | J40: =J20-I20 -> 3.9977656e+10 | K40: =K20-J20 -> 2.8849947e+10 | L40: =L20-K20 -> 2.1972228e+10 | ... N40: =N20-M20 -> 1.5196331e+10
B41: Ins (Des) in Current Liabilities | E41: =E22-D22 -> -47415372350 | F41: =F22-E22 -> 1121616920 | G41: =G22-F22 -> 158912332704 | H41: =H22-G22 -> -120668772072 | I41: =I22-H22 -> 2.4736729e+11 | J41: =J22-I22 -> 9.3440314e+10 | K41: =K22-J22 -> 7.7725352e+10 | L41: =L22-K22 -> 6.5548381e+10 | ... N41: =N22-M22 -> 3.5717908e+10
B43: Activities ratios
B44: Day in Account Receivables | E44: =365*(((E8+D8)/2)/OD_IS!E4) -> 930.06477 | F44: =365*(((F8+E8)/2)/OD_IS!F4) -> 614.74805 | G44: =365*(((G8+F8)/2)/OD_IS!G4) -> 346.34904 | H44: =365*(((H8+G8)/2)/OD_IS!H4) -> 268.01976 | I44: =365*(((I8+H8)/2)/OD_IS!I4) -> 171.78947 | J44: =365*(((J8+I8)/2)/OD_IS!J4) -> 99.180328 | K44: =365*(((K8+J8)/2)/OD_IS!K4) -> 88.478261 | L44: =365*(((L8+K8)/2)/OD_IS!L4) -> 80.540541 | ... N44: =365*(((N8+M8)/2)/OD_IS!N4) -> 78.095238
B45: Day in Account Inventories | E45: =365*(((E9+D9)/2)/-OD_IS!E5) -> 40.247904 | F45: =365*(((F9+E9)/2)/-OD_IS!F5) -> 27.502708 | G45: =365*(((G9+F9)/2)/-OD_IS!G5) -> 14.9316 | H45: =365*(((H9+G9)/2)/-OD_IS!H5) -> 17.770416 | I45: =365*(((I9+H9)/2)/-OD_IS!I5) -> 20.257806 | J45: =365*(((J9+I9)/2)/-OD_IS!J5) -> 19.433721 | K45: =365*(((K9+J9)/2)/-OD_IS!K5) -> 20.082495 | L45: =365*(((L9+K9)/2)/-OD_IS!L5) -> 20.428895 | ... N45: =365*(((N9+M9)/2)/-OD_IS!N5) -> 20.74238
B46: Day in Account Payables | E46: =365*(((E20+D20)/2)/-OD_IS!E5) -> 148.42928 | F46: =365*(((F20+E20)/2)/-OD_IS!F5) -> 111.6214 | G46: =365*(((G20+F20)/2)/-OD_IS!G5) -> 50.305257 | H46: =365*(((H20+G20)/2)/-OD_IS!H5) -> 36.740765 | I46: =365*(((I20+H20)/2)/-OD_IS!I5) -> 33.785356 | J46: =365*(((J20+I20)/2)/-OD_IS!J5) -> 34.951444 | K46: =365*(((K20+J20)/2)/-OD_IS!K5) -> 36.118259 | L46: =365*(((L20+K20)/2)/-OD_IS!L5) -> 36.741257 | ... N46: =365*(((N20+M20)/2)/-OD_IS!N5) -> 37.305059
B47: Other % short-term asset on sale | C47: (%) | D47: =D10/OD_IS!D4 -> 0.032494183 | E47: =E10/OD_IS!E4 -> 0.12678959 | F47: =F10/OD_IS!F4 -> 0.15639914 | G47: =G10/OD_IS!G4 -> 0.024467047 | H47: =H10/OD_IS!H4 -> 0.0090024146 | I47: =I10/OD_IS!I4 -> 0.016734731 | J47: =J10/OD_IS!J4 -> 0.016734731 | K47: =K10/OD_IS!K4 -> 0.016734731 | ... N47: =N10/OD_IS!N4 -> 0.016734731
B48: Other % short-term liabilities on sale | C48: (%) | D48: =D22/OD_IS!D4 -> 0.17175569 | E48: =E22/OD_IS!E4 -> 0.43930455 | F48: =F22/OD_IS!F4 -> 0.33793801 | G48: =G22/OD_IS!G4 -> 0.29045091 | H48: =H22/OD_IS!H4 -> 0.10820902 | I48: =I22/OD_IS!I4 -> 0.19932996 | J48: =J22/OD_IS!J4 -> 0.19932996 | K48: =K22/OD_IS!K4 -> 0.19932996 | ... N48: =N22/OD_IS!N4 -> 0.19932996

Sheet OD_IS
G2: 45291 | H2: =DATE(YEAR(G2),MONTH(G2)+13,0) -> 45657 | I2: =DATE(YEAR(H2),MONTH(H2)+13,0) -> 46022 | J2: =DATE(YEAR(I2),MONTH(I2)+13,0) -> 46387 | K2: =DATE(YEAR(J2),MONTH(J2)+13,0) -> 46752 | L2: =DATE(YEAR(K2),MONTH(K2)+13,0) -> 47118 | M2: =DATE(YEAR(L2),MONTH(L2)+13,0) -> 47483 | N2: =DATE(YEAR(M2),MONTH(M2)+13,0) -> 47848
B3: Items | C3: Unit | D3: ='IP_BS Raw'!E2 -> 2021 | E3: =D3+1 -> 2022 | F3: =E3+1 -> 2023 | G3: =F3+1 -> 2024 | H3: =G3+1 -> 2025 | I3: =H3+1 -> 2026 | J3: =I3+1 -> 2027 | K3: =J3+1 -> 2028 | L3: =K3+1 -> 2029 | ... N3: =M3+1 -> 2031
B4: Revenue | C4: (VND) | D4: ='IP_IS Raw'!E8 -> 1079507793378 | E4: ='IP_IS Raw'!F8 -> 314124306314 | F4: ='IP_IS Raw'!G8 -> 411666784900 | G4: ='IP_IS Raw'!H8 -> 1026094868172 | H4: ='IP_IS Raw'!I8 -> 1639063078002 | I4: =PD_Operation!I6 -> 2.130782e+12 | J4: =PD_Operation!J6 -> 2.599554e+12 | K4: =PD_Operation!K6 -> 2.9894871e+12 | L4: =PD_Operation!L6 -> 3.3183307e+12 | M4: =PD_Operation!M6 -> 3.5837972e+12 | N4: =PD_Operation!N6 -> 3.7629871e+12
B5: Cost of good sold | C5: (VND) | D5: ='IP_IS Raw'!E9 -> -1045382703416 | E5: ='IP_IS Raw'!F9 -> -209645620562 | F5: ='IP_IS Raw'!G9 -> -296480952992 | G5: ='IP_IS Raw'!H9 -> -855243703997 | H5: ='IP_IS Raw'!I9 -> -1424028369399 | I5: =-PD_Operation!I8*I4 -> -1.8537803e+12 | J5: =-PD_Operation!J8*J4 -> -2.2356165e+12 | K5: =-PD_Operation!K8*K4 -> -2.5111692e+12 | L5: =-PD_Operation!L8*L4 -> -2.7210312e+12 | M5: =-PD_Operation!M8*M4 -> -2.9028757e+12 | N5: =-PD_Operation!N8*N4 -> -3.0480195e+12
B6: Gross Profit | C6: (VND) | D6: =D4+D5 -> 34125089962 | E6: =E4+E5 -> 104478685752 | F6: =F4+F5 -> 115185831908 | G6: =G4+G5 -> 170851164175 | H6: =H4+H5 -> 215034708603 | I6: =I4+I5 -> 2.7700166e+11 | J6: =J4+J5 -> 3.6393757e+11 | K6: =K4+K5 -> 4.7831794e+11 | ... N6: =N4+N5 -> 7.1496754e+11
B7: Selling Expenses | C7: (VND) | D7: ='IP_IS Raw'!E15 -> -86766850424 | E7: ='IP_IS Raw'!F15 -> -20658752305 | F7: ='IP_IS Raw'!G15 -> -14260496293 | G7: ='IP_IS Raw'!H15 -> -26239808550 | H7: ='IP_IS Raw'!I15 -> -39335239608 | I7: =-PD_Operation!I9*I4 -> -5.326955e+10 | J7: =-PD_Operation!J9*J4 -> -6.4988851e+10 | K7: =-PD_Operation!K9*K4 -> -7.4737179e+10 | L7: =-PD_Operation!L9*L4 -> -8.2958268e+10 | M7: =-PD_Operation!M9*M4 -> -8.959493e+10 | N7: =-PD_Operation!N9*N4 -> -9.4074676e+10
B8: GS&A Expenses | C8: (VND) | D8: ='IP_IS Raw'!E16 -> -211115902487 | E8: ='IP_IS Raw'!F16 -> -93384172422 | F8: ='IP_IS Raw'!G16 -> -66900478155 | G8: ='IP_IS Raw'!H16 -> -151633232794 | H8: ='IP_IS Raw'!I16 -> -167762629718 | I8: =-PD_Operation!I10*I4 -> -2.130782e+11 | J8: =-PD_Operation!J10*J4 -> -2.547563e+11 | K8: =-PD_Operation!K10*K4 -> -2.8400128e+11 | L8: =-PD_Operation!L10*L4 -> -3.0860476e+11 | M8: =-PD_Operation!M10*M4 -> -3.2254175e+11 | N8: =-PD_Operation!N10*N4 -> -3.3866883e+11
B9: Operating Profit | C9: (VND) | D9: =D6+D7+D8 -> -263757662949 | E9: =E6+E7+E8 -> -9564238975 | F9: =F6+F7+F8 -> 34024857460 | G9: =G6+G7+G8 -> -7021877169 | H9: =H6+H7+H8 -> 7936839277 | I9: =I6+I7+I8 -> 1.065391e+10 | J9: =J6+J7+J8 -> 4.4192419e+10 | K9: =K6+K7+K8 -> 1.1957949e+11 | ... N9: =N6+N7+N8 -> 2.8222403e+11
B10: Financial income | C10: (VND) | D10: ='IP_IS Raw'!E11 -> 423849348595 | E10: ='IP_IS Raw'!F11 -> 47340388199 | F10: ='IP_IS Raw'!G11 -> 43586401680 | G10: ='IP_IS Raw'!H11 -> 191906506913 | H10: ='IP_IS Raw'!I11 -> 120349183176 | I10: =PD_Operation!I12*I4 -> 1.2784692e+11 | J10: =PD_Operation!J12*J4 -> 1.299777e+11 | K10: =PD_Operation!K12*K4 -> 1.1957949e+11 | L10: =PD_Operation!L12*L4 -> 1.1614158e+11 | M10: =PD_Operation!M12*M4 -> 1.254329e+11 | N10: =PD_Operation!N12*N4 -> 1.3170455e+11
B11: Financial expenses | C11: (VND) | D11: ='IP_IS Raw'!E12 -> -28037984463 | E11: ='IP_IS Raw'!F12 -> -9021747176 | F11: ='IP_IS Raw'!G12 -> -23482415579 | G11: ='IP_IS Raw'!H12 -> -51108323960 | H11: ='IP_IS Raw'!I12 -> -27197709414 | I11: =-OD_Valuation!$C$10*(PD_Operation!I24+PD_Operation!I25) -> -3.7525187e+10 | J11: =-OD_Valuation!$C$10*(PD_Operation!J24+PD_Operation!J25) -> -3.7525187e+10 | K11: =-OD_Valuation!$C$10*(PD_Operation!K24+PD_Operation!K25) -> -3.7525187e+10 | L11: =-OD_Valuation!$C$10*(PD_Operation!L24+PD_Operation!L25) -> -3.7525187e+10 | M11: =-OD_Valuation!$C$10*(PD_Operation!M24+PD_Operation!M25) -> -3.7525187e+10 | N11: =-OD_Valuation!$C$10*(PD_Operation!N24+PD_Operation!N25) -> -3.7525187e+10
B12: Interest expenses | C12: (VND) | D12: ='IP_IS Raw'!E13 -> -21801000846 | E12: ='IP_IS Raw'!F13 -> -6906877175 | F12: ='IP_IS Raw'!G13 -> -21505000199 | G12: ='IP_IS Raw'!H13 -> -28208427529 | H12: ='IP_IS Raw'!I13 -> -25900554619 | I12: =I11 -> -3.7525187e+10 | J12: =J11 -> -3.7525187e+10 | K12: =K11 -> -3.7525187e+10 | L12: =L11 -> -3.7525187e+10 | M12: =M11 -> -3.7525187e+10 | N12: =N11 -> -3.7525187e+10
B13: Gain/(loss) from joint ventures (from 2015) | C13: (VND) | D13: ='IP_IS Raw'!E14 -> 436847500 | E13: ='IP_IS Raw'!F14 -> 505897455 | F13: ='IP_IS Raw'!G14 -> -4853955053 | G13: ='IP_IS Raw'!H14 -> -15223546244 | H13: ='IP_IS Raw'!I14 -> -1456928964 | I13: 0 | J13: 0 | K13: 0 | L13: 0 | M13: 0 | N13: 0
B14: Net other income/(expenses) | C14: (VND) | D14: ='IP_IS Raw'!E18 -> -34173832376 | E14: ='IP_IS Raw'!F18 -> -345291142 | F14: ='IP_IS Raw'!G18 -> -20350770574 | G14: 0 | H14: 0 | I14: 0 | J14: 0 | K14: 0 | L14: 0 | M14: 0 | N14: 0
B16: Eearning before tax (EBT) | C16: (VND) | D16: =D9+D10+D13+D14+D11 -> 98316716307 | E16: =E9+E10+E13+E14+E11 -> 28915008361 | F16: =F9+F10+F13+F14+F11 -> 28924117934 | G16: =G9+G10+G13+G14+G11 -> 118552759540 | H16: =H9+H10+H11+H13+H14 -> 99631384075 | I16: =I9+I10+I11+I13+I14 -> 1.0097564e+11 | J16: =J9+J10+J11+J13+J14 -> 1.3664493e+11 | K16: =K9+K10+K11+K13+K14 -> 2.0163379e+11 | L16: =L9+L10+L11+L13+L14 -> 2.8435289e+11 | M16: =M9+M10+M11+M13+M14 -> 3.566925e+11 | N16: =N9+N10+N11+N13+N14 -> 3.7640339e+11
B17: EBITDA | C17: (VND) | D17: =D16-D12+OD_CF!D6 -> 320552074419 | E17: =E16-E12+OD_CF!E6 -> 237348407592 | F17: =F16-F12+OD_CF!F6 -> 243796643578 | G17: =G16-G12+OD_CF!G6 -> 400991615962 | H17: =H16-H12+OD_CF!H6 -> 125531938694 | I17: =I16-I12+OD_CF!I6 -> 3.8850083e+11 | J17: =J16-J12+OD_CF!J6 -> 4.3667012e+11 | K17: =K16-K12+OD_CF!K6 -> 5.1478397e+11 | ... N17: =N16-N12+OD_CF!N6 -> 7.3299897e+11
B19: Income tax expenses | C19: (VND) | D19: ='IP_IS Raw'!E23 -> -68326484945 | E19: ='IP_IS Raw'!F23 -> -4024148047 | F19: ='IP_IS Raw'!G23 -> -2405158607 | G19: ='IP_IS Raw'!H23 -> 11951746732 | H19: ='IP_IS Raw'!I23 -> -17278295298 | I19: =-MAX(0,I16)*PD_Operation!I13 -> -2.0195129e+10 | J19: =-MAX(0,J16)*PD_Operation!J13 -> -2.7328987e+10 | K19: =-MAX(0,K16)*PD_Operation!K13 -> -4.0326757e+10 | L19: =-MAX(0,L16)*PD_Operation!L13 -> -5.6870579e+10 | M19: =-MAX(0,M16)*PD_Operation!M13 -> -7.1338501e+10 | N19: =-MAX(0,N16)*PD_Operation!N13 -> -7.5280678e+10
B20: Tax rates | C20: (%) | D20: 0.2 | E20: 0.2 | F20: 0.2 | G20: 0.2 | H20: =PD_Operation!H13 -> 0.17342221 | I20: =PD_Operation!I13 -> 0.2 | J20: =PD_Operation!J13 -> 0.2 | K20: =PD_Operation!K13 -> 0.2 | L20: =PD_Operation!L13 -> 0.2 | M20: =PD_Operation!M13 -> 0.2 | N20: =PD_Operation!N13 -> 0.2
B21: Eearning after tax (EAT) | C21: (VND) | D21: =D16+D19 -> 29990231362 | E21: =E16+E19 -> 24890860314 | F21: =F16+F19 -> 26518959327 | G21: =G16+G19 -> 130504506272 | H21: =H16+H19 -> 82353088777 | I21: =I16+I19 -> 8.0780515e+10 | J21: =J16+J19 -> 1.0931595e+11 | K21: =K16+K19 -> 1.6130703e+11 | ... N21: =N16+N19 -> 3.0112271e+11
B24: Financial Income | C24: (VND) | D24: =D25+D27 -> 11231811523 | E24: =E25+E27 -> 27353187905 | F24: =F25+F27 -> 28617412106 | G24: =G25+G27 -> 30826499682 | H24: =H25+H27 -> 0
B25: Interest income of cash | C25: (VND) | D25: ='IP_Notes Raw'!E139 -> 11231811523 | E25: ='IP_Notes Raw'!F139 -> 27353187905 | F25: ='IP_Notes Raw'!G139 -> 28617412106 | G25: ='IP_Notes Raw'!H139 -> 30826499682 | H25: ='IP_Notes Raw'!I139 -> 0
B26: Interest rate | C26: (%) | D26: =D25/(OD_BS!D6+OD_BS!D7) -> 1.2180389 | E26: =E25/(OD_BS!E6+OD_BS!E7) -> 1.0313001 | F26: =F25/(OD_BS!F6+OD_BS!F7) -> 3.2926355 | G26: =G25/(OD_BS!G6+OD_BS!G7) -> 0.22424805 | H26: =H25/(OD_BS!H6+OD_BS!H7) -> 0
B27: Realized FX gains | C27: (VND) | D27: ='IP_Notes Raw'!E144 -> 0 | E27: ='IP_Notes Raw'!F144 -> 0 | F27: ='IP_Notes Raw'!G144 -> 0 | G27: ='IP_Notes Raw'!H144 -> 0 | H27: ='IP_Notes Raw'!I144 -> 0
B28: Realized FX gains % of sales (USD) | C28: (VND) | D28: =D27/D4 -> 0 | E28: =E27/E4 -> 0 | F28: =F27/F4 -> 0 | G28: =G27/G4 -> 0 | H28: =H27/H4 -> 0
B30: Financial expenses | C30: (VND) | D30: =-(D31+SUM(D59:D62)) -> -1977959712 | E30: =-(E31+SUM(E59:E62)) -> -5019819879 | F30: =-(F31+SUM(F59:F62)) -> -172619631145 | G30: =-(G31+SUM(G59:G62)) -> -219383871885 | H30: =-(H31+SUM(H59:H62)) -> 0
B31: Interest expenses | C31: (VND) | D31: ='IP_Notes Raw'!E149 -> 0 | E31: ='IP_Notes Raw'!F149 -> 1104887671 | F31: ='IP_Notes Raw'!G149 -> 170446855907 | G31: ='IP_Notes Raw'!H149 -> 167149402470 | H31: ='IP_Notes Raw'!I149 -> 0
B32: Cash available/required before debt | E32: =OD_CF!E4+OD_CF!E9+OD_CF!E15+OD_CF!E16+OD_CF!E17+OD_CF!E20 -> 128630197402 | F32: =OD_CF!F4+OD_CF!F9+OD_CF!F15+OD_CF!F16+OD_CF!F17+OD_CF!F20 -> -133060990875 | G32: =OD_CF!G4+OD_CF!G9+OD_CF!G15+OD_CF!G16+OD_CF!G17+OD_CF!G20 -> -239228298649 | H32: =OD_CF!H4+OD_CF!H9+OD_CF!H15+OD_CF!H16+OD_CF!H17+OD_CF!H20 -> 388508013333
B33: (Add) Beginning cash in BS | E33: =OD_BS!D6 -> 4321225874 | F33: =OD_BS!E6 -> 26473013864 | G33: =OD_BS!F6 -> 8461339357 | H33: =OD_BS!G6 -> 136236074178
B34: (Less): Mnimum cash balance | C34: (VND) | D34: =D4*D35 -> 4321225874 | E34: =E4*E35 -> 26473013864 | F34: =F4*F35 -> 8.4613394e+09 | G34: =G4*G35 -> 1.3623607e+11 | H34: =H4*H35 -> 288524181242
B35: Minimum cash % on Net Sales | C35: (%) | D35: =OD_BS!D6/OD_IS!D4 -> 0.0040029594 | E35: =OD_BS!E6/OD_IS!E4 -> 0.084275598 | F35: =OD_BS!F6/OD_IS!F4 -> 0.020553855 | G35: =OD_BS!G6/OD_IS!G4 -> 0.13277142 | H35: =OD_BS!H6/OD_IS!H4 -> 0.17602994
B36: (Add) Net mandatory debt | C36: (VND) | D36: 0 | E36: 0 | F36: 0 | G36: 0
B37: Cash before discretionary debt | E37: =E32+E33-E34+E36 -> 106478409412 | F37: =F32+F33-F34+F36 -> -115049316368 | G37: =G32+G33-G34+G36 -> -367003033470 | H37: =H32+H33-H34+H36 -> 236219906269
B39: Debt breakdown (Long term)
B40: Beginning balance
B41: Mandatory Debt Repayment (Transfer to short-term)
B42: Borrowing - Refinance
B43: Ending balance
B44: Average balance
B46: Debt breakdown (Short term)
B47: Beginning balance
B48: Discretionary Sweep/borrowing
B49: Minimum short term debt balance to fullfill liquidity need | C49: (VND)
B50: Working capital | C50: (VND)
B51: Short term debt % on working cap | C51: (%)
B52: Minimum Shorterm Debt | C52: (VND)
B53: Transfer from long term debt
B54: Ending balance
B55: Average balance
B57: Interest rate | D57: 0 | E57: =-E12/(OD_BS!E21+OD_BS!E24) -> 0.072461562 | F57: =-F12/(OD_BS!F21+OD_BS!F24) -> 0.10222605 | G57: =-G12/(OD_BS!G21+OD_BS!G24) -> 0.048856747 | H57: =-H12/(OD_BS!H21+OD_BS!H24) -> 0.075923967
B59: Payment discount | C59: (VND) | D59: ='IP_Notes Raw'!E150 -> 0 | E59: ='IP_Notes Raw'!F150 -> 0 | F59: ='IP_Notes Raw'!G150 -> 0 | G59: ='IP_Notes Raw'!H150 -> 0 | H59: ='IP_Notes Raw'!I150 -> 0
B60: Realized FX losses | C60: (VND) | D60: ='IP_Notes Raw'!E153 -> 0 | E60: ='IP_Notes Raw'!F153 -> 3914932208 | F60: ='IP_Notes Raw'!G153 -> 2172775238 | G60: ='IP_Notes Raw'!H153 -> 0 | H60: ='IP_Notes Raw'!I153 -> 0
B61: Unrealized FX losses | C61: (VND) | D61: ='IP_Notes Raw'!E154 -> 0 | E61: ='IP_Notes Raw'!F154 -> 0 | F61: ='IP_Notes Raw'!G154 -> 0 | G61: ='IP_Notes Raw'!H154 -> 0 | H61: ='IP_Notes Raw'!I154 -> 0
B62: Others | C62: (VND) | D62: ='IP_Notes Raw'!E151+'IP_Notes Raw'!E152+'IP_Notes Raw'!E155+'IP_Notes Raw'!E156 -> 1977959712 | E62: ='IP_Notes Raw'!F151+'IP_Notes Raw'!F152+'IP_Notes Raw'!F155+'IP_Notes Raw'!F156 -> 0 | F62: ='IP_Notes Raw'!G151+'IP_Notes Raw'!G152+'IP_Notes Raw'!G155+'IP_Notes Raw'!G156 -> 0 | G62: ='IP_Notes Raw'!H151+'IP_Notes Raw'!H152+'IP_Notes Raw'!H155+'IP_Notes Raw'!H156 -> 52234469415 | H62: ='IP_Notes Raw'!I151+'IP_Notes Raw'!I152+'IP_Notes Raw'!I155+'IP_Notes Raw'!I156 -> 0

Sheet OD_CF
G2: 45291 | H2: =DATE(YEAR(G2),MONTH(G2)+13,0) -> 45657 | I2: =DATE(YEAR(H2),MONTH(H2)+13,0) -> 46022 | J2: =DATE(YEAR(I2),MONTH(I2)+13,0) -> 46387 | K2: =DATE(YEAR(J2),MONTH(J2)+13,0) -> 46752 | L2: =DATE(YEAR(K2),MONTH(K2)+13,0) -> 47118 | M2: =DATE(YEAR(L2),MONTH(L2)+13,0) -> 47483 | N2: =DATE(YEAR(M2),MONTH(M2)+13,0) -> 47848
B3: Items | C3: Unit | D3: ='IP_BS Raw'!E2 -> 2021 | E3: =D3+1 -> 2022 | F3: =E3+1 -> 2023 | G3: =F3+1 -> 2024 | H3: =G3+1 -> 2025 | I3: =H3+1 -> 2026 | J3: =I3+1 -> 2027 | K3: =J3+1 -> 2028 | L3: =K3+1 -> 2029 | ... N3: =M3+1 -> 2031
B4: Cash from Operating activities | C4: (VND) | D4: ='IP_CF Raw'!E25 -> -88400373518 | E4: ='IP_CF Raw'!F25 -> -165318879753 | F4: ='IP_CF Raw'!G25 -> -192469587749 | G4: ='IP_CF Raw'!H25 -> 357427851606 | H4: ='IP_CF Raw'!I25 -> 7365426858 | I4: =I5+I6+I7+I8 -> 1.1968475e+12 | J4: =J5+J6+J7+J8 -> 4.6348523e+11 | K4: =K5+K6+K7+K8 -> 4.9601351e+11 | L4: =L5+L6+L7+L8 -> 5.9651751e+11 | M4: =M5+M6+M7+M8 -> 5.879719e+11 | N4: =N5+N6+N7+N8 -> 6.2038469e+11
B5: Net income | C5: (VND) | D5: =OD_IS!D21 -> 29990231362 | E5: =OD_IS!E21 -> 24890860314 | F5: =OD_IS!F21 -> 26518959327 | G5: =OD_IS!G21 -> 130504506272 | H5: =OD_IS!H21 -> 82353088777 | I5: =OD_IS!I21 -> 8.0780515e+10 | J5: =OD_IS!J21 -> 1.0931595e+11 | K5: =OD_IS!K21 -> 1.6130703e+11 | ... N5: =OD_IS!N21 -> 3.0112271e+11
B6: Depreciation & Amortization | C6: (VND) | D6: ='IP_Notes Raw'!E160 -> 200434357266 | E6: ='IP_Notes Raw'!F160 -> 201526522056 | F6: ='IP_Notes Raw'!G160 -> 193367525445 | G6: ='IP_Notes Raw'!H160 -> 254230428893 | H6: ='IP_Notes Raw'!I160 -> 0 | I6: =PD_Operation!I11*1000000000 -> 250000000000 | J6: =PD_Operation!J11*1000000000 -> 262500000000 | K6: =PD_Operation!K11*1000000000 -> 275625000000 | L6: =PD_Operation!L11*1000000000 -> 289406250000 | M6: =PD_Operation!M11*1000000000 -> 3.0387656e+11 | N6: =PD_Operation!N11*1000000000 -> 3.1907039e+11
B7: Change in working capital | E7: =OD_BS!E36 -> 477164295394 | F7: =OD_BS!F36 -> -326219812855 | G7: =OD_BS!G36 -> -30542466378 | H7: =OD_BS!H36 -> -359136449754 | I7: =OD_BS!I36 -> 8.6606695e+11 | J7: =OD_BS!J36 -> 9.166928e+10 | K7: =OD_BS!K36 -> 5.908148e+10 | L7: =OD_BS!L36 -> 7.962894e+10 | ... N7: =OD_BS!N36 -> 1.9158318e+08
B8: Other adjustment | E8: =E4-SUM(E5:E7) -> -868900557517 | F8: =F4-SUM(F5:F7) -> -86136259666 | G8: =G4-SUM(G5:G7) -> 3235382819 | H8: =H4-SUM(H5:H7) -> 284148787835 | I8: 0 | J8: 0 | K8: 0 | L8: 0 | M8: 0 | N8: 0
B9: Cash From Investing Activities | C9: (VND) | D9: =SUM(D10:D13) -> 11187918086 | E9: =SUM(E10:E13) -> 293110077155 | F9: =SUM(F10:F13) -> -397144764339 | G9: =SUM(G10:G13) -> -613628111128 | H9: =SUM(H10:H13) -> -192800335481 | I9: =SUM(I10:I13) -> -1.2784692e+11 | J9: =SUM(J10:J13) -> -1.299777e+11 | K9: =SUM(K10:K13) -> -1.1957949e+11 | ... N9: =SUM(N10:N13) -> -1.5051948e+11
B10: Capital Expenditure (CAPEX) | C10: (VND) | D10: ='IP_CF Raw'!E27 -> -2911894836 | E10: ='IP_CF Raw'!F27 -> -262090909 | F10: ='IP_CF Raw'!G27 -> -85145283539 | G10: ='IP_CF Raw'!H27 -> -552939817718 | H10: ='IP_CF Raw'!I27 -> -98219383903 | I10: =-PD_Operation!I21*OD_IS!I4 -> -1.2784692e+11 | J10: =-PD_Operation!J21*OD_IS!J4 -> -1.299777e+11 | K10: =-PD_Operation!K21*OD_IS!K4 -> -1.1957949e+11 | L10: =-PD_Operation!L21*OD_IS!L4 -> -1.3273323e+11 | M10: =-PD_Operation!M21*OD_IS!M4 -> -1.4335189e+11 | N10: =-PD_Operation!N21*OD_IS!N4 -> -1.5051948e+11
B11: Disposal of FA | C11: (VND) | D11: ='IP_CF Raw'!E28 -> 386363636 | E11: ='IP_CF Raw'!F28 -> 9922527548 | F11: ='IP_CF Raw'!G28 -> 1818413608 | G11: ='IP_CF Raw'!H28 -> 0 | H11: ='IP_CF Raw'!I28 -> 5000000000 | I11: 0 | J11: 0 | K11: 0 | L11: 0 | M11: 0 | N11: 0
B12: Loans granted, purchases of debt instruments | C12: (VND) | D12: ='IP_CF Raw'!E29 -> -1360000000 | E12: ='IP_CF Raw'!F29 -> -201466970449 | F12: ='IP_CF Raw'!G29 -> -146568497700 | G12: ='IP_CF Raw'!H29 -> -235919838301 | H12: ='IP_CF Raw'!I29 -> -824373768000 | I12: 0 | J12: 0 | K12: 0 | L12: 0 | M12: 0 | N12: 0
B13: Net other investing cash flow | C13: (VND) | D13: =SUM('IP_CF Raw'!E30:E33) -> 15073449286 | E13: =SUM('IP_CF Raw'!F30:F33) -> 484916610965 | F13: =SUM('IP_CF Raw'!G30:G33) -> -167249396708 | G13: =SUM('IP_CF Raw'!H30:H33) -> 175231544891 | H13: =SUM('IP_CF Raw'!I30:I33) -> 724792816422 | I13: 0 | J13: 0 | K13: 0 | L13: 0 | M13: 0 | N13: 0
B14: Cash from Financing Activities | C14: (VND) | D14: ='IP_CF Raw'!E34 -> 45121186034 | E14: ='IP_CF Raw'!F34 -> -105639409412 | F14: ='IP_CF Raw'!G34 -> 571602677581 | G14: ='IP_CF Raw'!H34 -> 383974994343 | H14: ='IP_CF Raw'!I34 -> 337710824236 | I14: =SUM(I15:I20) -> 1.1909908e+12 | J14: =SUM(J15:J20) -> -3.3350753e+11 | K14: =SUM(K15:K20) -> -3.7643402e+11 | L14: =SUM(L15:L20) -> -4.6378428e+11 | M14: =SUM(M15:M20) -> -9.0881669e+10 | N14: =SUM(N15:N20) -> -6.0224542e+10
B15: Dividend paid | C15: (VND) | D15: ='IP_CF Raw'!E40 -> 0 | E15: ='IP_CF Raw'!F40 -> 0 | F15: ='IP_CF Raw'!G40 -> 0 | G15: ='IP_CF Raw'!H40 -> 0 | H15: ='IP_CF Raw'!I40 -> -1283438400 | I15: =-OD_IS!I21*PD_Operation!I26 -> 0 | J15: =-OD_IS!J21*PD_Operation!J26 -> 0 | K15: =-OD_IS!K21*PD_Operation!K26 -> -8.0653514e+09 | L15: =-OD_IS!L21*PD_Operation!L26 -> -2.2748232e+10 | M15: =-OD_IS!M21*PD_Operation!M26 -> -4.2803101e+10 | N15: =-OD_IS!N21*PD_Operation!N26 -> -6.0224542e+10
B16: New shares issue | C16: (VND) | D16: ='IP_CF Raw'!E35 -> 0 | E16: ='IP_CF Raw'!F35 -> 0 | F16: ='IP_CF Raw'!G35 -> 450000000000 | G16: ='IP_CF Raw'!H35 -> 1767608500 | H16: ='IP_CF Raw'!I35 -> 548175451265 | I16: 0 | J16: 0 | K16: 0 | L16: 0 | M16: 0 | N16: 0
B17: Rebuy shares | C17: (VND) | D17: ='IP_CF Raw'!E36 -> 0 | E17: ='IP_CF Raw'!F36 -> 0 | F17: ='IP_CF Raw'!G36 -> 0 | G17: ='IP_CF Raw'!H36 -> 0 | H17: ='IP_CF Raw'!I36 -> 0 | I17: 0 | J17: 0 | K17: 0 | L17: 0 | M17: 0 | N17: 0
B18: Change in short-term debt | E18: ='IP_BS Raw'!F83-'IP_BS Raw'!E83 -> -36478409412 | F18: ='IP_BS Raw'!G83-'IP_BS Raw'!F83 -> 77034883512 | G18: ='IP_BS Raw'!H83-'IP_BS Raw'!G83 -> 356011405533 | H18: ='IP_BS Raw'!I83-'IP_BS Raw'!H83 -> -223092838964 | I18: =OD_BS!I21-OD_BS!H21 -> 1.1909908e+12 | J18: =OD_BS!J21-OD_BS!I21 -> -3.3350753e+11 | K18: =OD_BS!K21-OD_BS!J21 -> -3.6836867e+11 | L18: =OD_BS!L21-OD_BS!K21 -> -4.4103604e+11 | M18: =OD_BS!M21-OD_BS!L21 -> -4.8078569e+10 | N18: =OD_BS!N21-OD_BS!M21 -> 0
B19: Change in Long-term debt | E19: ='IP_BS Raw'!F96-'IP_BS Raw'!E96 -> -70000000000 | F19: ='IP_BS Raw'!G96-'IP_BS Raw'!F96 -> 38014432856 | G19: ='IP_BS Raw'!H96-'IP_BS Raw'!G96 -> 10991627937 | H19: ='IP_BS Raw'!I96-'IP_BS Raw'!H96 -> -13139258756 | I19: =OD_BS!I24-OD_BS!H24 -> 0 | J19: =OD_BS!J24-OD_BS!I24 -> 0 | K19: =OD_BS!K24-OD_BS!J24 -> 0 | L19: =OD_BS!L24-OD_BS!K24 -> 0 | M19: =OD_BS!M24-OD_BS!L24 -> 0 | N19: =OD_BS!N24-OD_BS!M24 -> 0
B20: Other financing cash flows | E20: =E14-E15-E16-E17-E18-E19 -> 839000000 | F20: =F14-F15-F16-F17-F18-F19 -> 6553361213 | G20: =G14-G15-G16-G17-G18-G19 -> 15204352373 | H20: =H14-H15-H16-H17-H18-H19 -> 27050909091 | I20: 0 | J20: 0 | K20: 0 | L20: 0 | M20: 0 | N20: 0
B22: Beginning cash | H22: =G24 -> 0 | I22: =H24 -> 288524181242 | J22: =I24 -> 288524181242 | K22: =J24 -> 288524181242 | L22: =K24 -> 288524181242 | M22: =L24 -> 288524181242 | N22: =M24 -> 288524181242
B23: Net Change in period | C23: (VND) | H23: =H4+H9+H14 -> 152275915613 | I23: =I4+I9+I14 -> 2259991353316 | J23: =J4+J9+J14 -> 0 | K23: =K4+K9+K14 -> 0 | L23: =L4+L9+L14 -> 0 | M23: =M4+M9+M14 -> 3.5373834e+11 | N23: =N4+N9+N14 -> 4.0964066e+11
B24: Ending cash | H24: =OD_BS!H6 -> 288524181242 | I24: =OD_BS!I6 -> 288524181242 | J24: =OD_BS!J6 -> 288524181242 | K24: =OD_BS!K6 -> 288524181242 | L24: =OD_BS!L6 -> 288524181242 | M24: =OD_BS!M6 -> 288524181242 | N24: =OD_BS!N6 -> 288524181242

Sheet OD_Ratio
B1: OD_Ratio — Financial Ratios
F2: 45291 | G2: =DATE(YEAR(F2),MONTH(F2)+13,0) -> 45657 | H2: =DATE(YEAR(G2),MONTH(G2)+13,0) -> 46022 | I2: =DATE(YEAR(H2),MONTH(H2)+13,0) -> 46387 | J2: =DATE(YEAR(I2),MONTH(I2)+13,0) -> 46752 | K2: =DATE(YEAR(J2),MONTH(J2)+13,0) -> 47118 | L2: =DATE(YEAR(K2),MONTH(K2)+13,0) -> 47483 | M2: =DATE(YEAR(L2),MONTH(L2)+13,0) -> 47848
B3: Items | C3: Unit | D3: ='IP_BS Raw'!E2 -> 2021 | E3: =D3+1 -> 2022 | F3: =E3+1 -> 2023 | G3: =F3+1 -> 2024 | H3: =G3+1 -> 2025 | I3: =H3+1 -> 2026 | J3: =I3+1 -> 2027 | K3: =J3+1 -> 2028 | L3: =K3+1 -> 2029 | ... N3: =M3+1 -> 2031
B4: 1. Activity ratios
B5: Inventory turnover | D5: =-OD_IS!E5/((OD_BS!D9+OD_BS!E9)/2) -> 9.0687952 | E5: =-OD_IS!F5/((OD_BS!E9+OD_BS!F9)/2) -> 13.271421 | F5: =-OD_IS!G5/((OD_BS!F9+OD_BS!G9)/2) -> 24.444802 | G5: =-OD_IS!H5/((OD_BS!G9+OD_BS!H9)/2) -> 20.539756 | H5: =-OD_IS!I5/((OD_BS!H9+OD_BS!I9)/2) -> 18.017746 | I5: =-OD_IS!J5/((OD_BS!I9+OD_BS!J9)/2) -> 18.781786 | J5: =-OD_IS!K5/((OD_BS!J9+OD_BS!K9)/2) -> 18.175033 | K5: =-OD_IS!L5/((OD_BS!K9+OD_BS!L9)/2) -> 17.86685 | ... M5: =-OD_IS!N5/((OD_BS!M9+OD_BS!N9)/2) -> 17.596824
B6: Days of inventory on hand (DOH) | D6: =365/D5 -> 40.247904 | E6: =365/E5 -> 27.502708 | F6: =365/F5 -> 14.9316 | G6: =365/G5 -> 17.770416 | H6: =365/H5 -> 20.257806 | I6: =365/I5 -> 19.433721 | J6: =365/J5 -> 20.082495 | K6: =365/K5 -> 20.428895 | ... M6: =365/M5 -> 20.74238
B7: Receivables turnover | D7: =OD_IS!E4/((OD_BS!D8+OD_BS!E8)/2) -> 0.39244579 | E7: =OD_IS!F4/((OD_BS!E8+OD_BS!F8)/2) -> 0.59373917 | F7: =OD_IS!G4/((OD_BS!F8+OD_BS!G8)/2) -> 1.0538502 | G7: =OD_IS!H4/((OD_BS!G8+OD_BS!H8)/2) -> 1.3618399 | H7: =OD_IS!I4/((OD_BS!H8+OD_BS!I8)/2) -> 2.1246937 | I7: =OD_IS!J4/((OD_BS!I8+OD_BS!J8)/2) -> 3.6801653 | J7: =OD_IS!K4/((OD_BS!J8+OD_BS!K8)/2) -> 4.1253071 | K7: =OD_IS!L4/((OD_BS!K8+OD_BS!L8)/2) -> 4.5318792 | ... M7: =OD_IS!N4/((OD_BS!M8+OD_BS!N8)/2) -> 4.6737805
B8: Days of sales outstanding (DSO) | D8: =365/D7 -> 930.06477 | E8: =365/E7 -> 614.74805 | F8: =365/F7 -> 346.34904 | G8: =365/G7 -> 268.01976 | H8: =365/H7 -> 171.78947 | I8: =365/I7 -> 99.180328 | J8: =365/J7 -> 88.478261 | K8: =365/K7 -> 80.540541 | ... M8: =365/M7 -> 78.095238
B9: Payable Turnover | D9: =-OD_IS!E5/((OD_BS!D20+OD_BS!E20)/2) -> 2.4590835 | E9: =-OD_IS!F5/((OD_BS!E20+OD_BS!F20)/2) -> 3.2699822 | F9: =-OD_IS!G5/((OD_BS!F20+OD_BS!G20)/2) -> 7.2557028 | G9: =-OD_IS!H5/((OD_BS!G20+OD_BS!H20)/2) -> 9.9344693 | H9: =-OD_IS!I5/((OD_BS!H20+OD_BS!I20)/2) -> 10.803497 | I9: =-OD_IS!J5/((OD_BS!I20+OD_BS!J20)/2) -> 10.443059 | J9: =-OD_IS!K5/((OD_BS!J20+OD_BS!K20)/2) -> 10.105692 | K9: =-OD_IS!L5/((OD_BS!K20+OD_BS!L20)/2) -> 9.9343361 | ... M9: =-OD_IS!N5/((OD_BS!M20+OD_BS!N20)/2) -> 9.7841958
B10: Number of days of payables | D10: =365/D9 -> 148.42928 | E10: =365/E9 -> 111.6214 | F10: =365/F9 -> 50.305257 | G10: =365/G9 -> 36.740765 | H10: =365/H9 -> 33.785356 | I10: =365/I9 -> 34.951444 | J10: =365/J9 -> 36.118259 | K10: =365/K9 -> 36.741257 | ... M10: =365/M9 -> 37.305059
B11: Working capital turnover | D11: =OD_IS!E4/(OD_BS!E5-OD_BS!E19) -> 1.0210019 | E11: =OD_IS!F4/(OD_BS!F5-OD_BS!F19) -> 0.76373752 | F11: =OD_IS!G4/(OD_BS!G5-OD_BS!G19) -> 2.9974566 | G11: =OD_IS!H4/(OD_BS!H5-OD_BS!H19) -> 1.321602 | H11: =OD_IS!I4/(OD_BS!I5-OD_BS!I19) -> -2.60854 | I11: =OD_IS!J4/(OD_BS!J5-OD_BS!J19) -> -4.5208828 | J11: =OD_IS!K4/(OD_BS!K5-OD_BS!K19) -> -11.250386 | K11: =OD_IS!L4/(OD_BS!L5-OD_BS!L19) -> 34.680091 | ... M11: =OD_IS!N4/(OD_BS!N5-OD_BS!N19) -> 25.982155
B12: Fixed assets turnover | D12: =OD_IS!E4/((OD_BS!D12+OD_BS!E12)/2) -> 2.8193553 | E12: =OD_IS!F4/((OD_BS!E12+OD_BS!F12)/2) -> 2.6954819 | F12: =OD_IS!G4/((OD_BS!F12+OD_BS!G12)/2) -> 2.6130793 | G12: =OD_IS!H4/((OD_BS!G12+OD_BS!H12)/2) -> 2.5723584 | H12: =OD_IS!I4/((OD_BS!H12+OD_BS!I12)/2) -> 2.9853361 | I12: =OD_IS!J4/((OD_BS!I12+OD_BS!J12)/2) -> 3.0849318 | J12: =OD_IS!K4/((OD_BS!J12+OD_BS!K12)/2) -> 3.0900997 | K12: =OD_IS!L4/((OD_BS!K12+OD_BS!L12)/2) -> 3.0343277 | ... M12: =OD_IS!N4/((OD_BS!M12+OD_BS!N12)/2) -> 2.7296209
B13: Total Asset turnover | D13: =OD_IS!E4/((OD_BS!D4+OD_BS!E4)/2) -> 0.23265025 | E13: =OD_IS!F4/((OD_BS!E4+OD_BS!F4)/2) -> 0.25703808 | F13: =OD_IS!G4/((OD_BS!F4+OD_BS!G4)/2) -> 0.43608326 | G13: =OD_IS!H4/((OD_BS!G4+OD_BS!H4)/2) -> 0.55741278 | H13: =OD_IS!I4/((OD_BS!H4+OD_BS!I4)/2) -> 0.78386422 | I13: =OD_IS!J4/((OD_BS!I4+OD_BS!J4)/2) -> 1.1180931 | J13: =OD_IS!K4/((OD_BS!J4+OD_BS!K4)/2) -> 1.3433927 | K13: =OD_IS!L4/((OD_BS!K4+OD_BS!L4)/2) -> 1.5826748 | ... M13: =OD_IS!N4/((OD_BS!M4+OD_BS!N4)/2) -> 2.0058104
B14: 2. Liquidity ratios
B15: Current | D15: =OD_BS!E5/OD_BS!E19 -> 1.9751723 | E15: =OD_BS!F5/OD_BS!F19 -> 2.3191015 | F15: =OD_BS!G5/OD_BS!G19 -> 1.3554799 | G15: =OD_BS!H5/OD_BS!H19 -> 2.9663194 | H15: =OD_BS!I5/OD_BS!I19 -> 0.6136149 | I15: =OD_BS!J5/OD_BS!J19 -> 0.69957496 | J15: =OD_BS!K5/OD_BS!K19 -> 0.83916974 | K15: =OD_BS!L5/OD_BS!L19 -> 1.0736779 | ... M15: =OD_BS!N5/OD_BS!N19 -> 1.105448
B16: Quick | D16: =(OD_BS!E5-OD_BS!E9-OD_BS!E10)/OD_BS!E19 -> 1.79977 | E16: =(OD_BS!F5-OD_BS!F9-OD_BS!F10)/OD_BS!F19 -> 2.090155 | F16: =(OD_BS!G5-OD_BS!G9-OD_BS!G10)/OD_BS!G19 -> 1.2870361 | G16: =(OD_BS!H5-OD_BS!H9-OD_BS!H10)/OD_BS!H19 -> 2.787777 | H16: =(OD_BS!I5-OD_BS!I9-OD_BS!I10)/OD_BS!I19 -> 0.54570118 | I16: =(OD_BS!J5-OD_BS!J9-OD_BS!J10)/OD_BS!J19 -> 0.6088492 | J16: =(OD_BS!K5-OD_BS!K9-OD_BS!K10)/OD_BS!K19 -> 0.72040978 | K16: =(OD_BS!L5-OD_BS!L9-OD_BS!L10)/OD_BS!L19 -> 0.90894541 | ... M16: =(OD_BS!N5-OD_BS!N9-OD_BS!N10)/OD_BS!N19 -> 0.93040853
B17: Cash | D17: =(OD_BS!E5-OD_BS!E9-OD_BS!E10-OD_BS!E8)/OD_BS!E19 -> 0.084067713 | E17: =(OD_BS!F5-OD_BS!F9-OD_BS!F10-OD_BS!F8)/OD_BS!F19 -> 0.021269791 | F17: =(OD_BS!G5-OD_BS!G9-OD_BS!G10-OD_BS!G8)/OD_BS!G19 -> 0.14274996 | G17: =(OD_BS!H5-OD_BS!H9-OD_BS!H10-OD_BS!H8)/OD_BS!H19 -> 0.71841656 | H17: =(OD_BS!I5-OD_BS!I9-OD_BS!I10-OD_BS!I8)/OD_BS!I19 -> 0.21433648 | I17: =(OD_BS!J5-OD_BS!J9-OD_BS!J10-OD_BS!J8)/OD_BS!J19 -> 0.23674334 | J17: =(OD_BS!K5-OD_BS!K9-OD_BS!K10-OD_BS!K8)/OD_BS!K19 -> 0.27425574 | K17: =(OD_BS!L5-OD_BS!L9-OD_BS!L10-OD_BS!L8)/OD_BS!L19 -> 0.34891125 | ... M17: =(OD_BS!N5-OD_BS!N9-OD_BS!N10-OD_BS!N8)/OD_BS!N19 -> 0.32991189
B18: Cash conversion cycle | D18: =D6+D8-D10 -> 821.88339 | E18: =E6+E8-E10 -> 530.62936 | F18: =F6+F8-F10 -> 310.97538 | G18: =G6+G8-G10 -> 249.04941 | H18: =H6+H8-H10 -> 158.26192 | I18: =I6+I8-I10 -> 83.662605 | J18: =J6+J8-J10 -> 72.442496 | K18: =K6+K8-K10 -> 64.228178 | ... M18: =M6+M8-M10 -> 61.532559
B19: 3. Solvency Ratios
B20: Debt-to-assets | D20: =(OD_BS!E21+OD_BS!E24)/OD_BS!E4 -> 0.072654517 | E20: =(OD_BS!F21+OD_BS!F24)/OD_BS!F4 -> 0.11123322 | F20: =(OD_BS!G21+OD_BS!G24)/OD_BS!G4 -> 0.20512432 | G20: =(OD_BS!H21+OD_BS!H24)/OD_BS!H4 -> 0.11125636 | H20: =(OD_BS!I21+OD_BS!I24)/OD_BS!I4 -> 0.64636539 | I20: =(OD_BS!J21+OD_BS!J24)/OD_BS!J4 -> 0.52580286 | J20: =(OD_BS!K21+OD_BS!K24)/OD_BS!K4 -> 0.38241979 | K20: =(OD_BS!L21+OD_BS!L24)/OD_BS!L4 -> 0.1924653 | ... M20: =(OD_BS!N21+OD_BS!N24)/OD_BS!N4 -> 0.18773463
B21: Dept-to-capital | D21: =(OD_BS!E21+OD_BS!E24)/(OD_BS!E21+OD_BS!E24+OD_BS!E26) -> 0.14205254 | E21: =(OD_BS!F21+OD_BS!F24)/(OD_BS!F21+OD_BS!F24+OD_BS!F26) -> 0.33781977 | F21: =(OD_BS!G21+OD_BS!G24)/(OD_BS!G21+OD_BS!G24+OD_BS!G26) -> 0.75941025 | G21: =(OD_BS!H21+OD_BS!H24)/(OD_BS!H21+OD_BS!H24+OD_BS!H26) -> 0.72313222 | H21: =(OD_BS!I21+OD_BS!I24)/(OD_BS!I21+OD_BS!I24+OD_BS!I26) -> 0.87875515 | I21: =(OD_BS!J21+OD_BS!J24)/(OD_BS!J21+OD_BS!J24+OD_BS!J26) -> 0.78891424 | J21: =(OD_BS!K21+OD_BS!K24)/(OD_BS!K21+OD_BS!K24+OD_BS!K26) -> 0.63659756 | K21: =(OD_BS!L21+OD_BS!L24)/(OD_BS!L21+OD_BS!L24+OD_BS!L26) -> 0.3644687 | ... M21: =(OD_BS!N21+OD_BS!N24)/(OD_BS!N21+OD_BS!N24+OD_BS!N26) -> 0.22693038
B22: Dept-to-equity | D22: =(OD_BS!E21+OD_BS!E24)/(OD_BS!E26) -> 0.16557254 | E22: =(OD_BS!F21+OD_BS!F24)/(OD_BS!F26) -> 0.51016288 | F22: =(OD_BS!G21+OD_BS!G24)/(OD_BS!G26) -> 3.1564531 | G22: =(OD_BS!H21+OD_BS!H24)/(OD_BS!H26) -> 2.6118324 | H22: =(OD_BS!I21+OD_BS!I24)/(OD_BS!I26) -> 7.2477729 | I22: =(OD_BS!J21+OD_BS!J24)/(OD_BS!J26) -> 3.737411 | J22: =(OD_BS!K21+OD_BS!K24)/(OD_BS!K26) -> 1.7517702 | K22: =(OD_BS!L21+OD_BS!L24)/(OD_BS!L26) -> 0.57348662 | ... M22: =(OD_BS!N21+OD_BS!N24)/(OD_BS!N26) -> 0.29354455
B23: Financial leverage | D23: =((OD_BS!E4+OD_BS!D4)/2)/OD_BS!E26 -> 2.3453749 | E23: =((OD_BS!F4+OD_BS!E4)/2)/OD_BS!F26 -> 3.8840011 | F23: =((OD_BS!G4+OD_BS!F4)/2)/OD_BS!G26 -> 12.863617 | G23: =((OD_BS!H4+OD_BS!G4)/2)/OD_BS!H26 -> 22.513026 | H23: =((OD_BS!I4+OD_BS!H4)/2)/OD_BS!I26 -> 12.859008 | I23: =((OD_BS!J4+OD_BS!I4)/2)/OD_BS!J26 -> 7.2495283 | J23: =((OD_BS!K4+OD_BS!J4)/2)/OD_BS!K26 -> 4.6952698 | K23: =((OD_BS!L4+OD_BS!K4)/2)/OD_BS!L26 -> 3.0892985 | ... M23: =((OD_BS!N4+OD_BS!M4)/2)/OD_BS!N26 -> 1.6143091
B24: 4. Profitability ratios
B25: Gross profit margin | D25: =OD_IS!E6/OD_IS!E4 -> 0.332603 | E25: =OD_IS!F6/OD_IS!F4 -> 0.27980356 | F25: =OD_IS!G6/OD_IS!G4 -> 0.16650621 | G25: =OD_IS!H6/OD_IS!H4 -> 0.13119367 | H25: =OD_IS!I6/OD_IS!I4 -> 0.13 | I25: =OD_IS!J6/OD_IS!J4 -> 0.14 | J25: =OD_IS!K6/OD_IS!K4 -> 0.16 | K25: =OD_IS!L6/OD_IS!L4 -> 0.18 | ... M25: =OD_IS!N6/OD_IS!N4 -> 0.19
B26: Operating margin | D26: =OD_IS!E9/OD_IS!E4 -> -0.030447306 | E26: =OD_IS!F9/OD_IS!F4 -> 0.082651452 | F26: =OD_IS!G9/OD_IS!G4 -> -0.0068433021 | G26: =OD_IS!H9/OD_IS!H4 -> 0.0048423025 | H26: =OD_IS!I9/OD_IS!I4 -> 0.005 | I26: =OD_IS!J9/OD_IS!J4 -> 0.017 | J26: =OD_IS!K9/OD_IS!K4 -> 0.04 | K26: =OD_IS!L9/OD_IS!L4 -> 0.062 | ... M26: =OD_IS!N9/OD_IS!N4 -> 0.075
B27: Pretax margin | D27: =OD_IS!E16/OD_IS!E4 -> 0.092049573 | E27: =OD_IS!F16/OD_IS!F4 -> 0.070260995 | F27: =OD_IS!G16/OD_IS!G4 -> 0.11553782 | G27: =OD_IS!H16/OD_IS!H4 -> 0.06078557 | H27: =OD_IS!I16/OD_IS!I4 -> 0.047389007 | I27: =OD_IS!J16/OD_IS!J4 -> 0.05256476 | J27: =OD_IS!K16/OD_IS!K4 -> 0.067447617 | K27: =OD_IS!L16/OD_IS!L4 -> 0.085691547 | ... M27: =OD_IS!N16/OD_IS!N4 -> 0.10002782
B28: Net profit margin | D28: =OD_IS!E21/OD_IS!E4 -> 0.079238887 | E28: =OD_IS!F21/OD_IS!F4 -> 0.064418506 | F28: =OD_IS!G21/OD_IS!G4 -> 0.12718561 | G28: =OD_IS!H21/OD_IS!H4 -> 0.050244002 | H28: =OD_IS!I21/OD_IS!I4 -> 0.037911206 | I28: =OD_IS!J21/OD_IS!J4 -> 0.042051808 | J28: =OD_IS!K21/OD_IS!K4 -> 0.053958094 | K28: =OD_IS!L21/OD_IS!L4 -> 0.068553238 | ... M28: =OD_IS!N21/OD_IS!N4 -> 0.080022256
B29: Opearting ROA | D29: =OD_IS!E9/((OD_BS!D4+OD_BS!E4)/2) -> -0.0070835735 | E29: =OD_IS!F9/((OD_BS!E4+OD_BS!F4)/2) -> 0.02124457 | F29: =OD_IS!G9/((OD_BS!F4+OD_BS!G4)/2) -> -0.0029842495 | G29: =OD_IS!H9/((OD_BS!G4+OD_BS!H4)/2) -> 0.0026991613 | H29: =OD_IS!I9/((OD_BS!H4+OD_BS!I4)/2) -> 0.0039193211 | I29: =OD_IS!J9/((OD_BS!I4+OD_BS!J4)/2) -> 0.019007582 | J29: =OD_IS!K9/((OD_BS!J4+OD_BS!K4)/2) -> 0.053735708 | K29: =OD_IS!L9/((OD_BS!K4+OD_BS!L4)/2) -> 0.09812584 | ... M29: =OD_IS!N9/((OD_BS!M4+OD_BS!N4)/2) -> 0.15043578
B30: ROA | D30: =OD_IS!E21/((OD_BS!D4+OD_BS!E4)/2) -> 0.018434947 | E30: =OD_IS!F21/((OD_BS!E4+OD_BS!F4)/2) -> 0.016558009 | F30: =OD_IS!G21/((OD_BS!F4+OD_BS!G4)/2) -> 0.055463517 | G30: =OD_IS!H21/((OD_BS!G4+OD_BS!H4)/2) -> 0.028006649 | H30: =OD_IS!I21/((OD_BS!H4+OD_BS!I4)/2) -> 0.029717238 | I30: =OD_IS!J21/((OD_BS!I4+OD_BS!J4)/2) -> 0.047017835 | J30: =OD_IS!K21/((OD_BS!J4+OD_BS!K4)/2) -> 0.072486909 | K30: =OD_IS!L21/((OD_BS!K4+OD_BS!L4)/2) -> 0.10849748 | ... M30: =OD_IS!N21/((OD_BS!M4+OD_BS!N4)/2) -> 0.16050947
B31: Return on total capital | D31: =(OD_IS!E16+(OD_IS!E12*(1-OD_IS!E20)))/(OD_BS!E21+OD_BS!E24+OD_BS!E26) -> 0.034857483 | E31: =(OD_IS!F16+(OD_IS!F12*(1-OD_IS!F20)))/(OD_BS!F21+OD_BS!F24+OD_BS!F26) -> 0.018820847 | F31: =(OD_IS!G16+(OD_IS!G12*(1-OD_IS!G20)))/(OD_BS!G21+OD_BS!G24+OD_BS!G26) -> 0.12624963 | G31: =(OD_IS!H16+(OD_IS!H12*(1-OD_IS!H20)))/(OD_BS!H21+OD_BS!H24+OD_BS!H26) -> 0.16581338 | H31: =(OD_IS!I16+(OD_IS!I12*(1-OD_IS!I20)))/(OD_BS!I21+OD_BS!I24+OD_BS!I26) -> 0.040696646 | I31: =(OD_IS!J16+(OD_IS!J12*(1-OD_IS!J20)))/(OD_BS!J21+OD_BS!J24+OD_BS!J26) -> 0.070178803 | J31: =(OD_IS!K16+(OD_IS!K12*(1-OD_IS!K20)))/(OD_BS!K21+OD_BS!K24+OD_BS!K26) -> 0.13158503 | K31: =(OD_IS!L16+(OD_IS!L12*(1-OD_IS!L20)))/(OD_BS!L21+OD_BS!L24+OD_BS!L26) -> 0.23816126 | ... M31: =(OD_IS!N16+(OD_IS!N12*(1-OD_IS!N20)))/(OD_BS!N21+OD_BS!N24+OD_BS!N26) -> 0.23041955
B32: ROE | D32: =OD_IS!E21/((OD_BS!D26+OD_BS!E26)/2) -> 0.043655377 | E32: =OD_IS!F21/((OD_BS!E26+OD_BS!F26)/2) -> 0.053679988 | F32: =OD_IS!G21/((OD_BS!F26+OD_BS!G26)/2) -> 0.43847145 | G32: =OD_IS!H21/((OD_BS!G26+OD_BS!H26)/2) -> 0.52532841 | H32: =OD_IS!I21/((OD_BS!H26+OD_BS!I26)/2) -> 0.47239294 | I32: =OD_IS!J21/((OD_BS!I26+OD_BS!J26)/2) -> 0.41088338 | J32: =OD_IS!K21/((OD_BS!J26+OD_BS!K26)/2) -> 0.40597763 | K32: =OD_IS!L21/((OD_BS!K26+OD_BS!L26)/2) -> 0.39471685 | ... M32: =OD_IS!N21/((OD_BS!M26+OD_BS!N26)/2) -> 0.28907278
P50: Profitability | Q50: 2021 | R50: 2022 | S50: 2023 | T50: 2024 | U50: 2025 | V50: 2026 | W50: 2027 | X50: 2028 | Y50: 2029 | Z50: 2030
P51: Gross Margin | Q51: =D25 -> 0.332603 | R51: =E25 -> 0.27980356 | S51: =F25 -> 0.16650621 | T51: =G25 -> 0.13119367 | U51: =H25 -> 0.13 | V51: =I25 -> 0.14 | W51: =J25 -> 0.16 | X51: =K25 -> 0.18 | ... Z51: =M25 -> 0.19
P52: Operating Margin | Q52: =D26 -> -0.030447306 | R52: =E26 -> 0.082651452 | S52: =F26 -> -0.0068433021 | T52: =G26 -> 0.0048423025 | U52: =H26 -> 0.005 | V52: =I26 -> 0.017 | W52: =J26 -> 0.04 | X52: =K26 -> 0.062 | ... Z52: =M26 -> 0.075
P53: Net Margin | Q53: =D28 -> 0.079238887 | R53: =E28 -> 0.064418506 | S53: =F28 -> 0.12718561 | T53: =G28 -> 0.050244002 | U53: =H28 -> 0.037911206 | V53: =I28 -> 0.042051808 | W53: =J28 -> 0.053958094 | X53: =K28 -> 0.068553238 | ... Z53: =M28 -> 0.080022256
P56: ROA / ROE | Q56: 2021 | R56: 2022 | S56: 2023 | T56: 2024 | U56: 2025 | V56: 2026 | W56: 2027 | X56: 2028 | Y56: 2029 | Z56: 2030
P57: ROA | Q57: =D30 -> 0.018434947 | R57: =E30 -> 0.016558009 | S57: =F30 -> 0.055463517 | T57: =G30 -> 0.028006649 | U57: =H30 -> 0.029717238 | V57: =I30 -> 0.047017835 | W57: =J30 -> 0.072486909 | X57: =K30 -> 0.10849748 | ... Z57: =M30 -> 0.16050947
P58: ROE | Q58: =D32 -> 0.043655377 | R58: =E32 -> 0.053679988 | S58: =F32 -> 0.43847145 | T58: =G32 -> 0.52532841 | U58: =H32 -> 0.47239294 | V58: =I32 -> 0.41088338 | W58: =J32 -> 0.40597763 | X58: =K32 -> 0.39471685 | ... Z58: =M32 -> 0.28907278
P62: Liquidity | Q62: 2021 | R62: 2022 | S62: 2023 | T62: 2024 | U62: 2025 | V62: 2026 | W62: 2027 | X62: 2028 | Y62: 2029 | Z62: 2030
P63: Current Ratio | Q63: =D15 -> 1.9751723 | R63: =E15 -> 2.3191015 | S63: =F15 -> 1.3554799 | T63: =G15 -> 2.9663194 | U63: =H15 -> 0.6136149 | V63: =I15 -> 0.69957496 | W63: =J15 -> 0.83916974 | X63: =K15 -> 1.0736779 | ... Z63: =M15 -> 1.105448
P64: Quick Ratio | Q64: =D16 -> 1.79977 | R64: =E16 -> 2.090155 | S64: =F16 -> 1.2870361 | T64: =G16 -> 2.787777 | U64: =H16 -> 0.54570118 | V64: =I16 -> 0.6088492 | W64: =J16 -> 0.72040978 | X64: =K16 -> 0.90894541 | ... Z64: =M16 -> 0.93040853
P65: Cash Ratio | Q65: =D17 -> 0.084067713 | R65: =E17 -> 0.021269791 | S65: =F17 -> 0.14274996 | T65: =G17 -> 0.71841656 | U65: =H17 -> 0.21433648 | V65: =I17 -> 0.23674334 | W65: =J17 -> 0.27425574 | X65: =K17 -> 0.34891125 | ... Z65: =M17 -> 0.32991189
P68: Solvency | Q68: 2021 | R68: 2022 | S68: 2023 | T68: 2024 | U68: 2025 | V68: 2026 | W68: 2027 | X68: 2028 | Y68: 2029 | Z68: 2030
P69: Debt-to-Assets | Q69: =D20 -> 0.072654517 | R69: =E20 -> 0.11123322 | S69: =F20 -> 0.20512432 | T69: =G20 -> 0.11125636 | U69: =H20 -> 0.64636539 | V69: =I20 -> 0.52580286 | W69: =J20 -> 0.38241979 | X69: =K20 -> 0.1924653 | ... Z69: =M20 -> 0.18773463
P70: Debt-to-Equity | Q70: =D22 -> 0.16557254 | R70: =E22 -> 0.51016288 | S70: =F22 -> 3.1564531 | T70: =G22 -> 2.6118324 | U70: =H22 -> 7.2477729 | V70: =I22 -> 3.737411 | W70: =J22 -> 1.7517702 | X70: =K22 -> 0.57348662 | ... Z70: =M22 -> 0.29354455
P74: Activity (days) | Q74: 2021 | R74: 2022 | S74: 2023 | T74: 2024 | U74: 2025 | V74: 2026 | W74: 2027 | X74: 2028 | Y74: 2029 | Z74: 2030
P75: DSO (AR days) | Q75: =D8 -> 930.06477 | R75: =E8 -> 614.74805 | S75: =F8 -> 346.34904 | T75: =G8 -> 268.01976 | U75: =H8 -> 171.78947 | V75: =I8 -> 99.180328 | W75: =J8 -> 88.478261 | X75: =K8 -> 80.540541 | ... Z75: =M8 -> 78.095238
P76: DOH (Inv days) | Q76: =D6 -> 40.247904 | R76: =E6 -> 27.502708 | S76: =F6 -> 14.9316 | T76: =G6 -> 17.770416 | U76: =H6 -> 20.257806 | V76: =I6 -> 19.433721 | W76: =J6 -> 20.082495 | X76: =K6 -> 20.428895 | ... Z76: =M6 -> 20.74238
P77: DOP (AP days) | Q77: =D10 -> 148.42928 | R77: =E10 -> 111.6214 | S77: =F10 -> 50.305257 | T77: =G10 -> 36.740765 | U77: =H10 -> 33.785356 | V77: =I10 -> 34.951444 | W77: =J10 -> 36.118259 | X77: =K10 -> 36.741257 | ... Z77: =M10 -> 37.305059
P80: Asset Turnover | Q80: 2021 | R80: 2022 | S80: 2023 | T80: 2024 | U80: 2025 | V80: 2026 | W80: 2027 | X80: 2028 | Y80: 2029 | Z80: 2030
P81: FA Turnover | Q81: =D12 -> 2.8193553 | R81: =E12 -> 2.6954819 | S81: =F12 -> 2.6130793 | T81: =G12 -> 2.5723584 | U81: =H12 -> 2.9853361 | V81: =I12 -> 3.0849318 | W81: =J12 -> 3.0900997 | X81: =K12 -> 3.0343277 | ... Z81: =M12 -> 2.7296209
P82: Total Asset Turnover | Q82: =D13 -> 0.23265025 | R82: =E13 -> 0.25703808 | S82: =F13 -> 0.43608326 | T82: =G13 -> 0.55741278 | U82: =H13 -> 0.78386422 | V82: =I13 -> 1.1180931 | W82: =J13 -> 1.3433927 | X82: =K13 -> 1.5826748 | ... Z82: =M13 -> 2.0058104

Sheet OD_Valuation
B1: OD_Valuation — DCF / FCFF
B2: Active scenario → | C2: Bear
B3: INPUTS (edit these — blue cells)
B4: Valuation date | C4: =TODAY() -> 46138
B5: Last historical year-end | C5: =DATE(OD_IS!G3,12,31) -> 45657
B6: Forecast years (N) | C6: 5
B7: Risk-free rate (Rf) | C7: =INDEX($C$81:$E$81,MATCH($C$2,$C$76:$E$76,0)) -> 0.045
B8: Beta | C8: =INDEX($C$77:$E$77,MATCH($C$2,$C$76:$E$76,0)) -> 1.05
B9: Equity Risk Premium (ERP) | C9: =INDEX($C$78:$E$78,MATCH($C$2,$C$76:$E$76,0)) -> 0.0911
B10: Pre-tax Cost of Debt (Kd) | C10: =INDEX($C$82:$E$82,MATCH($C$2,$C$76:$E$76,0)) -> 0.11
B11: Tax rate | C11: =INDEX($C$83:$E$83,MATCH($C$2,$C$76:$E$76,0)) -> 0.2
B12: Target D/(D+E) | C12: =INDEX($C$84:$E$84,MATCH($C$2,$C$76:$E$76,0)) -> 0.35
B13: Constant growth (g) | C13: =INDEX($C$79:$E$79,MATCH($C$2,$C$76:$E$76,0)) -> 0.025
B14: Current market price (VND/share) | C14: =IPc_Others!H4 -> 9990
B15: Shares outstanding (mn) | C15: =IPc_Others!G50 -> 191.80203
B17: DERIVED (auto-calculated)
B18: Cost of Equity (Ke = Rf + Beta*ERP) | C18: =C7+C8*C9 -> 0.140655
B19: After-tax Cost of Debt (Kd*(1-T)) | C19: =C10*(1-C11) -> 0.088
B20: WACC | C20: =C18*(1-C12)+C19*C12 -> 0.12222575
B21: Partial year (valuation date → year-end) | C21: =(DATE(YEAR(C4),12,31)-C4)/365 -> 0.68219178
B23: 3. FCFF Build (VND bn) | G23: 3.1 FCFF Streams
B24: Item | C24: Unit | G24: =OD_IS!H3 -> 2025 | H24: =OD_IS!I3 -> 2026 | I24: =OD_IS!J3 -> 2027 | J24: =OD_IS!K3 -> 2028 | K24: =OD_IS!L3 -> 2029 | L24: =OD_IS!M3 -> 2030 | M24: =OD_IS!N3 -> 2031
B25: Net Income (NI) | C25: (VND bn) | G25: =OD_IS!H21/1000000000 -> 82.353089 | H25: =OD_IS!I21/1000000000 -> 80.780515 | I25: =OD_IS!J21/1000000000 -> 109.31595 | J25: =OD_IS!K21/1000000000 -> 161.30703 | K25: =OD_IS!L21/1000000000 -> 227.48232 | L25: =OD_IS!M21/1000000000 -> 285.354 | M25: =OD_IS!N21/1000000000 -> 301.12271 | Z25: =OD_IS!T21/1000000000 -> 0
B26: (+) Depreciation & Amortization | C26: (VND bn) | G26: =OD_CF!H6/1000000000 -> 0 | H26: =OD_CF!I6/1000000000 -> 250 | I26: =OD_CF!J6/1000000000 -> 262.5 | J26: =OD_CF!K6/1000000000 -> 275.625 | K26: =OD_CF!L6/1000000000 -> 289.40625 | L26: =OD_CF!M6/1000000000 -> 303.87656 | M26: =OD_CF!N6/1000000000 -> 319.07039 | Z26: =OD_CF!T6/1000000000 -> 0
B27: (-) Net CapEx | C27: (VND bn) | G27: =OD_CF!H10/1000000000 -> -98.219384 | H27: =OD_CF!I10/1000000000 -> -127.84692 | I27: =OD_CF!J10/1000000000 -> -129.9777 | J27: =OD_CF!K10/1000000000 -> -119.57949 | K27: =OD_CF!L10/1000000000 -> -132.73323 | L27: =OD_CF!M10/1000000000 -> -143.35189 | M27: =OD_CF!N10/1000000000 -> -150.51948 | Z27: =OD_CF!T10/1000000000 -> 0
B28: (±) Change in Working Capital | C28: (VND bn) | G28: =OD_BS!H36/1000000000 -> -359.13645 | H28: =OD_BS!I36/1000000000 -> 866.06695 | I28: =OD_BS!J36/1000000000 -> 91.66928 | J28: =OD_BS!K36/1000000000 -> 59.08148 | K28: =OD_BS!L36/1000000000 -> 79.62894 | L28: =OD_BS!M36/1000000000 -> -1.2586647 | M28: =OD_BS!N36/1000000000 -> 0.19158318 | Z28: =OD_BS!T36/1000000000 -> 0
B29: (+) Interest expense * (1 - T) | C29: (VND bn) | G29: =-OD_IS!H12*(1-OD_IS!H20)/1000000000 -> 21.408823 | H29: =-OD_IS!I12*(1-OD_IS!I20)/1000000000 -> 30.020149 | I29: =-OD_IS!J12*(1-OD_IS!J20)/1000000000 -> 30.020149 | J29: =-OD_IS!K12*(1-OD_IS!K20)/1000000000 -> 30.020149 | K29: =-OD_IS!L12*(1-OD_IS!L20)/1000000000 -> 30.020149 | L29: =-OD_IS!M12*(1-OD_IS!M20)/1000000000 -> 30.020149 | M29: =-OD_IS!N12*(1-OD_IS!N20)/1000000000 -> 30.020149 | Z29: =-OD_IS!T12*(1-OD_IS!T20)/1000000000 -> 0
B30: FCFF | C30: (VND bn) | G30: =SUM(G25:G29) -> -353.59392 | H30: =SUM(H25:H29) -> 1099.0207 | I30: =SUM(I25:I29) -> 363.52767 | J30: =SUM(J25:J29) -> 406.45417 | K30: =SUM(K25:K29) -> 493.80443 | L30: =SUM(L25:L29) -> 474.64016 | M30: =SUM(M25:M29) -> 499.88535 | Z30: =SUM(Z25:Z29) -> 0
B32: Year fraction (from val date to year-end N) | C32: (yr) | G32: =$C$21+(COLUMN(G32)-COLUMN($G$32)) -> 0.68219178 | H32: =$C$21+(COLUMN(H32)-COLUMN($G$32)) -> 1.6821918 | I32: =$C$21+(COLUMN(I32)-COLUMN($G$32)) -> 2.6821918 | J32: =$C$21+(COLUMN(J32)-COLUMN($G$32)) -> 3.6821918 | K32: =$C$21+(COLUMN(K32)-COLUMN($G$32)) -> 4.6821918 | L32: =$C$21+(COLUMN(L32)-COLUMN($G$32)) -> 5.6821918 | M32: =$C$21+(COLUMN(M32)-COLUMN($G$32)) -> 6.6821918 | Z32: =$C$21+(COLUMN(Z32)-COLUMN($G$32)) -> 19.682192
B33: Discount factor = (1+WACC)^t | C33: (x) | G33: =(1+$C$20)^G32 -> 1.0818432 | H33: =(1+$C$20)^H32 -> 1.2140723 | I33: =(1+$C$20)^I32 -> 1.3624632 | J33: =(1+$C$20)^J32 -> 1.5289913 | K33: =(1+$C$20)^K32 -> 1.7158734 | L33: =(1+$C$20)^L32 -> 1.9255973 | M33: =(1+$C$20)^M32 -> 2.1609549 | Z33: =(1+$C$20)^Z32 -> 9.6758401
B34: PV of FCFF | C34: (VND bn) | G34: =G30/G33 -> -326.84396 | H34: =H30/H33 -> 905.23496 | I34: =I30/I33 -> 266.81651 | J34: =J30/J33 -> 265.83158 | K34: =K30/K33 -> 287.78605 | L34: =L30/L33 -> 246.48984 | M34: =M30/M33 -> 231.32614 | Z34: =Z30/Z33 -> 0
B36: 4. Enterprise / Equity Value (VND bn)
B37: Sum of PV of FCFF (explicit) | C37: =SUM(G34:M34)*(1+INDEX($C$80:$E$80,MATCH($C$2,$C$76:$E$76,0))) -> 1829.7251
B38: Terminal value (at year T) | C38: =M30*(1+INDEX($C$80:$E$80,MATCH($C$2,$C$76:$E$76,0)))*(1+C13)/(C20-C13) -> 5138.2779
B39: PV of terminal value | C39: =C38/M33 -> 2377.7812
B40: Enterprise Value (EV) | C40: =C37+C39 -> 4207.5063
B41: (+) Excess cash | C41: =OD_BS!G6/1000000000 -> 136.23607
B42: (+) Short-term investments | C42: =OD_BS!G7/1000000000 -> 1.23
B43: (+) Long-term investments | C43: =OD_BS!G16/1000000000 -> 111.17842
B44: (-) Total debt | C44: =-(OD_BS!G21+OD_BS!G24)/1000000000 -> -577.37016
B45: (-) Minority interest | C45: =-OD_BS!G31/1000000000 -> -57.068806
B46: Equity Value | C46: =C40+C41+C42+C43+C44+C45 -> 3821.7118
B47: Shares outstanding (mn) | C47: =C15 -> 191.80203
B48: Equity Value per share (VND) | C48: =C46/C47*1000 -> 19925.293
B49: Current market price (VND) | C49: =C14 -> 9990
B50: Upside / (Downside) | C50: =C48/C49-1 -> 0.99452387
B52: 5. Sensitivity Analysis — Equity Value per Share & Upside / (Downside)
B54: 5a. WACC × Terminal growth (g) — Upside / (Downside)
B55: WACC \ g | C55: =$C$13-0.015 -> 0.01 | D55: =$C$13-0.01 -> 0.015 | E55: =$C$13-0.005 -> 0.02 | F55: =$C$13 -> 0.025 | G55: =$C$13+0.005 -> 0.03 | H55: =$C$13+0.01 -> 0.035 | I55: =$C$13+0.015 -> 0.04
B56: =$C$20-0.015 -> 0.10722575 | C56: {=((SUMPRODUCT($G$30:$M$30,1/(1+$B56)^$G$32:$M$32) + $M$30*(1+C$55)/($B56-C$55)/(1+$B56)^$M$32) + ($C$46-$C$40))/$C$47*1000/$C$49-1} -> 1.2029544 | D56: {=((SUMPRODUCT($G$30:$M$30,1/(1+$B56)^$G$32:$M$32) + $M$30*(1+D$55)/($B56-D$55)/(1+$B56)^$M$32) + ($C$46-$C$40))/$C$47*1000/$C$49-1} -> 1.2845055 | E56: {=((SUMPRODUCT($G$30:$M$30,1/(1+$B56)^$G$32:$M$32) + $M$30*(1+E$55)/($B56-E$55)/(1+$B56)^$M$32) + ($C$46-$C$40))/$C$47*1000/$C$49-1} -> 1.375406 | F56: {=((SUMPRODUCT($G$30:$M$30,1/(1+$B56)^$G$32:$M$32) + $M$30*(1+F$55)/($B56-F$55)/(1+$B56)^$M$32) + ($C$46-$C$40))/$C$47*1000/$C$49-1} -> 1.4773615 | G56: {=((SUMPRODUCT($G$30:$M$30,1/(1+$B56)^$G$32:$M$32) + $M$30*(1+G$55)/($B56-G$55)/(1+$B56)^$M$32) + ($C$46-$C$40))/$C$47*1000/$C$49-1} -> 1.5925193 | H56: {=((SUMPRODUCT($G$30:$M$30,1/(1+$B56)^$G$32:$M$32) + $M$30*(1+H$55)/($B56-H$55)/(1+$B56)^$M$32) + ($C$46-$C$40))/$C$47*1000/$C$49-1} -> 1.7236212 | I56: {=((SUMPRODUCT($G$30:$M$30,1/(1+$B56)^$G$32:$M$32) + $M$30*(1+I$55)/($B56-I$55)/(1+$B56)^$M$32) + ($C$46-$C$40))/$C$47*1000/$C$49-1} -> 1.8742249
B57: =$C$20-0.01 -> 0.11222575 | C57: {=((SUMPRODUCT($G$30:$M$30,1/(1+$B57)^$G$32:$M$32) + $M$30*(1+C$55)/($B57-C$55)/(1+$B57)^$M$32) + ($C$46-$C$40))/$C$47*1000/$C$49-1} -> 1.0791159 | D57: {=((SUMPRODUCT($G$30:$M$30,1/(1+$B57)^$G$32:$M$32) + $M$30*(1+D$55)/($B57-D$55)/(1+$B57)^$M$32) + ($C$46-$C$40))/$C$47*1000/$C$49-1} -> 1.1508297 | E57: {=((SUMPRODUCT($G$30:$M$30,1/(1+$B57)^$G$32:$M$32) + $M$30*(1+E$55)/($B57-E$55)/(1+$B57)^$M$32) + ($C$46-$C$40))/$C$47*1000/$C$49-1} -> 1.2303195 | F57: {=((SUMPRODUCT($G$30:$M$30,1/(1+$B57)^$G$32:$M$32) + $M$30*(1+F$55)/($B57-F$55)/(1+$B57)^$M$32) + ($C$46-$C$40))/$C$47*1000/$C$49-1} -> 1.3189223 | G57: {=((SUMPRODUCT($G$30:$M$30,1/(1+$B57)^$G$32:$M$32) + $M$30*(1+G$55)/($B57-G$55)/(1+$B57)^$M$32) + ($C$46-$C$40))/$C$47*1000/$C$49-1} -> 1.4183007 | H57: {=((SUMPRODUCT($G$30:$M$30,1/(1+$B57)^$G$32:$M$32) + $M$30*(1+H$55)/($B57-H$55)/(1+$B57)^$M$32) + ($C$46-$C$40))/$C$47*1000/$C$49-1} -> 1.5305476 | I57: {=((SUMPRODUCT($G$30:$M$30,1/(1+$B57)^$G$32:$M$32) + $M$30*(1+I$55)/($B57-I$55)/(1+$B57)^$M$32) + ($C$46-$C$40))/$C$47*1000/$C$49-1} -> 1.6583357
B58: =$C$20-0.005 -> 0.11722575 | C58: {=((SUMPRODUCT($G$30:$M$30,1/(1+$B58)^$G$32:$M$32) + $M$30*(1+C$55)/($B58-C$55)/(1+$B58)^$M$32) + ($C$46-$C$40))/$C$47*1000/$C$49-1} -> 0.96683801 | D58: {=((SUMPRODUCT($G$30:$M$30,1/(1+$B58)^$G$32:$M$32) + $M$30*(1+D$55)/($B58-D$55)/(1+$B58)^$M$32) + ($C$46-$C$40))/$C$47*1000/$C$49-1} -> 1.0302274 | E58: {=((SUMPRODUCT($G$30:$M$30,1/(1+$B58)^$G$32:$M$32) + $M$30*(1+E$55)/($B58-E$55)/(1+$B58)^$M$32) + ($C$46-$C$40))/$C$47*1000/$C$49-1} -> 1.1001365 | F58: {=((SUMPRODUCT($G$30:$M$30,1/(1+$B58)^$G$32:$M$32) + $M$30*(1+F$55)/($B58-F$55)/(1+$B58)^$M$32) + ($C$46-$C$40))/$C$47*1000/$C$49-1} -> 1.1776259 | G58: {=((SUMPRODUCT($G$30:$M$30,1/(1+$B58)^$G$32:$M$32) + $M$30*(1+G$55)/($B58-G$55)/(1+$B58)^$M$32) + ($C$46-$C$40))/$C$47*1000/$C$49-1} -> 1.2639991 | H58: {=((SUMPRODUCT($G$30:$M$30,1/(1+$B58)^$G$32:$M$32) + $M$30*(1+H$55)/($B58-H$55)/(1+$B58)^$M$32) + ($C$46-$C$40))/$C$47*1000/$C$49-1} -> 1.3608766 | I58: {=((SUMPRODUCT($G$30:$M$30,1/(1+$B58)^$G$32:$M$32) + $M$30*(1+I$55)/($B58-I$55)/(1+$B58)^$M$32) + ($C$46-$C$40))/$C$47*1000/$C$49-1} -> 1.4702989
B59: =$C$20 -> 0.12222575 | C59: {=((SUMPRODUCT($G$30:$M$30,1/(1+$B59)^$G$32:$M$32) + $M$30*(1+C$55)/($B59-C$55)/(1+$B59)^$M$32) + ($C$46-$C$40))/$C$47*1000/$C$49-1} -> 0.86457499 | D59: {=((SUMPRODUCT($G$30:$M$30,1/(1+$B59)^$G$32:$M$32) + $M$30*(1+D$55)/($B59-D$55)/(1+$B59)^$M$32) + ($C$46-$C$40))/$C$47*1000/$C$49-1} -> 0.92086931 | E59: {=((SUMPRODUCT($G$30:$M$30,1/(1+$B59)^$G$32:$M$32) + $M$30*(1+E$55)/($B59-E$55)/(1+$B59)^$M$32) + ($C$46-$C$40))/$C$47*1000/$C$49-1} -> 0.98267051 | F59: {=((SUMPRODUCT($G$30:$M$30,1/(1+$B59)^$G$32:$M$32) + $M$30*(1+F$55)/($B59-F$55)/(1+$B59)^$M$32) + ($C$46-$C$40))/$C$47*1000/$C$49-1} -> 1.0508282 | G59: {=((SUMPRODUCT($G$30:$M$30,1/(1+$B59)^$G$32:$M$32) + $M$30*(1+G$55)/($B59-G$55)/(1+$B59)^$M$32) + ($C$46-$C$40))/$C$47*1000/$C$49-1} -> 1.1263761 | H59: {=((SUMPRODUCT($G$30:$M$30,1/(1+$B59)^$G$32:$M$32) + $M$30*(1+H$55)/($B59-H$55)/(1+$B59)^$M$32) + ($C$46-$C$40))/$C$47*1000/$C$49-1} -> 1.2105853 | I59: {=((SUMPRODUCT($G$30:$M$30,1/(1+$B59)^$G$32:$M$32) + $M$30*(1+I$55)/($B59-I$55)/(1+$B59)^$M$32) + ($C$46-$C$40))/$C$47*1000/$C$49-1} -> 1.3050357
B60: =$C$20+0.005 -> 0.12722575 | C60: {=((SUMPRODUCT($G$30:$M$30,1/(1+$B60)^$G$32:$M$32) + $M$30*(1+C$55)/($B60-C$55)/(1+$B60)^$M$32) + ($C$46-$C$40))/$C$47*1000/$C$49-1} -> 0.77104478 | D60: {=((SUMPRODUCT($G$30:$M$30,1/(1+$B60)^$G$32:$M$32) + $M$30*(1+D$55)/($B60-D$55)/(1+$B60)^$M$32) + ($C$46-$C$40))/$C$47*1000/$C$49-1} -> 0.82125247 | E60: {=((SUMPRODUCT($G$30:$M$30,1/(1+$B60)^$G$32:$M$32) + $M$30*(1+E$55)/($B60-E$55)/(1+$B60)^$M$32) + ($C$46-$C$40))/$C$47*1000/$C$49-1} -> 0.87614259 | F60: {=((SUMPRODUCT($G$30:$M$30,1/(1+$B60)^$G$32:$M$32) + $M$30*(1+F$55)/($B60-F$55)/(1+$B60)^$M$32) + ($C$46-$C$40))/$C$47*1000/$C$49-1} -> 0.93640222 | G60: {=((SUMPRODUCT($G$30:$M$30,1/(1+$B60)^$G$32:$M$32) + $M$30*(1+G$55)/($B60-G$55)/(1+$B60)^$M$32) + ($C$46-$C$40))/$C$47*1000/$C$49-1} -> 1.0028597 | H60: {=((SUMPRODUCT($G$30:$M$30,1/(1+$B60)^$G$32:$M$32) + $M$30*(1+H$55)/($B60-H$55)/(1+$B60)^$M$32) + ($C$46-$C$40))/$C$47*1000/$C$49-1} -> 1.0765232 | I60: {=((SUMPRODUCT($G$30:$M$30,1/(1+$B60)^$G$32:$M$32) + $M$30*(1+I$55)/($B60-I$55)/(1+$B60)^$M$32) + ($C$46-$C$40))/$C$47*1000/$C$49-1} -> 1.1586319
B61: =$C$20+0.01 -> 0.13222575 | C61: {=((SUMPRODUCT($G$30:$M$30,1/(1+$B61)^$G$32:$M$32) + $M$30*(1+C$55)/($B61-C$55)/(1+$B61)^$M$32) + ($C$46-$C$40))/$C$47*1000/$C$49-1} -> 0.68517518 | D61: {=((SUMPRODUCT($G$30:$M$30,1/(1+$B61)^$G$32:$M$32) + $M$30*(1+D$55)/($B61-D$55)/(1+$B61)^$M$32) + ($C$46-$C$40))/$C$47*1000/$C$49-1} -> 0.7301302 | E61: {=((SUMPRODUCT($G$30:$M$30,1/(1+$B61)^$G$32:$M$32) + $M$30*(1+E$55)/($B61-E$55)/(1+$B61)^$M$32) + ($C$46-$C$40))/$C$47*1000/$C$49-1} -> 0.77909099 | F61: {=((SUMPRODUCT($G$30:$M$30,1/(1+$B61)^$G$32:$M$32) + $M$30*(1+F$55)/($B61-F$55)/(1+$B61)^$M$32) + ($C$46-$C$40))/$C$47*1000/$C$49-1} -> 0.83261791 | G61: {=((SUMPRODUCT($G$30:$M$30,1/(1+$B61)^$G$32:$M$32) + $M$30*(1+G$55)/($B61-G$55)/(1+$B61)^$M$32) + ($C$46-$C$40))/$C$47*1000/$C$49-1} -> 0.89138099 | H61: {=((SUMPRODUCT($G$30:$M$30,1/(1+$B61)^$G$32:$M$32) + $M$30*(1+H$55)/($B61-H$55)/(1+$B61)^$M$32) + ($C$46-$C$40))/$C$47*1000/$C$49-1} -> 0.95618804 | I61: {=((SUMPRODUCT($G$30:$M$30,1/(1+$B61)^$G$32:$M$32) + $M$30*(1+I$55)/($B61-I$55)/(1+$B61)^$M$32) + ($C$46-$C$40))/$C$47*1000/$C$49-1} -> 1.0280221
B62: =$C$20+0.015 -> 0.13722575 | C62: {=((SUMPRODUCT($G$30:$M$30,1/(1+$B62)^$G$32:$M$32) + $M$30*(1+C$55)/($B62-C$55)/(1+$B62)^$M$32) + ($C$46-$C$40))/$C$47*1000/$C$49-1} -> 0.60606256 | D62: {=((SUMPRODUCT($G$30:$M$30,1/(1+$B62)^$G$32:$M$32) + $M$30*(1+D$55)/($B62-D$55)/(1+$B62)^$M$32) + ($C$46-$C$40))/$C$47*1000/$C$49-1} -> 0.64645987 | E62: {=((SUMPRODUCT($G$30:$M$30,1/(1+$B62)^$G$32:$M$32) + $M$30*(1+E$55)/($B62-E$55)/(1+$B62)^$M$32) + ($C$46-$C$40))/$C$47*1000/$C$49-1} -> 0.69030329 | F62: {=((SUMPRODUCT($G$30:$M$30,1/(1+$B62)^$G$32:$M$32) + $M$30*(1+F$55)/($B62-F$55)/(1+$B62)^$M$32) + ($C$46-$C$40))/$C$47*1000/$C$49-1} -> 0.73805342 | G62: {=((SUMPRODUCT($G$30:$M$30,1/(1+$B62)^$G$32:$M$32) + $M$30*(1+G$55)/($B62-G$55)/(1+$B62)^$M$32) + ($C$46-$C$40))/$C$47*1000/$C$49-1} -> 0.79025679 | H62: {=((SUMPRODUCT($G$30:$M$30,1/(1+$B62)^$G$32:$M$32) + $M$30*(1+H$55)/($B62-H$55)/(1+$B62)^$M$32) + ($C$46-$C$40))/$C$47*1000/$C$49-1} -> 0.84756684 | I62: {=((SUMPRODUCT($G$30:$M$30,1/(1+$B62)^$G$32:$M$32) + $M$30*(1+I$55)/($B62-I$55)/(1+$B62)^$M$32) + ($C$46-$C$40))/$C$47*1000/$C$49-1} -> 0.91077141
B64: 5b. Beta × Equity Risk Premium (ERP) — Upside / (Downside)
B65: Beta \ ERP | C65: =$C$9-0.015 -> 0.0761 | D65: =$C$9-0.01 -> 0.0811 | E65: =$C$9-0.005 -> 0.0861 | F65: =$C$9 -> 0.0911 | G65: =$C$9+0.005 -> 0.0961 | H65: =$C$9+0.01 -> 0.1011 | I65: =$C$9+0.015 -> 0.1061
B66: =$C$8-0.3 -> 0.75 | C66: {=_xlfn.LET(_xlpm.w,($C$7+$B66*C$65)*(1-$C$12)+$C$19*$C$12,((SUMPRODUCT($G$30:$M$30,1/(1+_xlpm.w)^$G$32:$M$32) + $M$30*(1+$C$13)/(_xlpm.w-$C$13)/(1+_xlpm.w)^$M$32) + ($C$46-$C$40))/$C$47*1000/$C$49-1)} -> 1.8632625 | D66: {=_xlfn.LET(_xlpm.w,($C$7+$B66*D$65)*(1-$C$12)+$C$19*$C$12,((SUMPRODUCT($G$30:$M$30,1/(1+_xlpm.w)^$G$32:$M$32) + $M$30*(1+$C$13)/(_xlpm.w-$C$13)/(1+_xlpm.w)^$M$32) + ($C$46-$C$40))/$C$47*1000/$C$49-1)} -> 1.7603746 | E66: {=_xlfn.LET(_xlpm.w,($C$7+$B66*E$65)*(1-$C$12)+$C$19*$C$12,((SUMPRODUCT($G$30:$M$30,1/(1+_xlpm.w)^$G$32:$M$32) + $M$30*(1+$C$13)/(_xlpm.w-$C$13)/(1+_xlpm.w)^$M$32) + ($C$46-$C$40))/$C$47*1000/$C$49-1)} -> 1.6639878 | F66: {=_xlfn.LET(_xlpm.w,($C$7+$B66*F$65)*(1-$C$12)+$C$19*$C$12,((SUMPRODUCT($G$30:$M$30,1/(1+_xlpm.w)^$G$32:$M$32) + $M$30*(1+$C$13)/(_xlpm.w-$C$13)/(1+_xlpm.w)^$M$32) + ($C$46-$C$40))/$C$47*1000/$C$49-1)} -> 1.5735039 | G66: {=_xlfn.LET(_xlpm.w,($C$7+$B66*G$65)*(1-$C$12)+$C$19*$C$12,((SUMPRODUCT($G$30:$M$30,1/(1+_xlpm.w)^$G$32:$M$32) + $M$30*(1+$C$13)/(_xlpm.w-$C$13)/(1+_xlpm.w)^$M$32) + ($C$46-$C$40))/$C$47*1000/$C$49-1)} -> 1.488396 | H66: {=_xlfn.LET(_xlpm.w,($C$7+$B66*H$65)*(1-$C$12)+$C$19*$C$12,((SUMPRODUCT($G$30:$M$30,1/(1+_xlpm.w)^$G$32:$M$32) + $M$30*(1+$C$13)/(_xlpm.w-$C$13)/(1+_xlpm.w)^$M$32) + ($C$46-$C$40))/$C$47*1000/$C$49-1)} -> 1.4081979 | I66: {=_xlfn.LET(_xlpm.w,($C$7+$B66*I$65)*(1-$C$12)+$C$19*$C$12,((SUMPRODUCT($G$30:$M$30,1/(1+_xlpm.w)^$G$32:$M$32) + $M$30*(1+$C$13)/(_xlpm.w-$C$13)/(1+_xlpm.w)^$M$32) + ($C$46-$C$40))/$C$47*1000/$C$49-1)} -> 1.3324961
B67: =$C$8-0.2 -> 0.85 | C67: {=_xlfn.LET(_xlpm.w,($C$7+$B67*C$65)*(1-$C$12)+$C$19*$C$12,((SUMPRODUCT($G$30:$M$30,1/(1+_xlpm.w)^$G$32:$M$32) + $M$30*(1+$C$13)/(_xlpm.w-$C$13)/(1+_xlpm.w)^$M$32) + ($C$46-$C$40))/$C$47*1000/$C$49-1)} -> 1.6612523 | D67: {=_xlfn.LET(_xlpm.w,($C$7+$B67*D$65)*(1-$C$12)+$C$19*$C$12,((SUMPRODUCT($G$30:$M$30,1/(1+_xlpm.w)^$G$32:$M$32) + $M$30*(1+$C$13)/(_xlpm.w-$C$13)/(1+_xlpm.w)^$M$32) + ($C$46-$C$40))/$C$47*1000/$C$49-1)} -> 1.5593066 | E67: {=_xlfn.LET(_xlpm.w,($C$7+$B67*E$65)*(1-$C$12)+$C$19*$C$12,((SUMPRODUCT($G$30:$M$30,1/(1+_xlpm.w)^$G$32:$M$32) + $M$30*(1+$C$13)/(_xlpm.w-$C$13)/(1+_xlpm.w)^$M$32) + ($C$46-$C$40))/$C$47*1000/$C$49-1)} -> 1.4641653 | F67: {=_xlfn.LET(_xlpm.w,($C$7+$B67*F$65)*(1-$C$12)+$C$19*$C$12,((SUMPRODUCT($G$30:$M$30,1/(1+_xlpm.w)^$G$32:$M$32) + $M$30*(1+$C$13)/(_xlpm.w-$C$13)/(1+_xlpm.w)^$M$32) + ($C$46-$C$40))/$C$47*1000/$C$49-1)} -> 1.3751683 | G67: {=_xlfn.LET(_xlpm.w,($C$7+$B67*G$65)*(1-$C$12)+$C$19*$C$12,((SUMPRODUCT($G$30:$M$30,1/(1+_xlpm.w)^$G$32:$M$32) + $M$30*(1+$C$13)/(_xlpm.w-$C$13)/(1+_xlpm.w)^$M$32) + ($C$46-$C$40))/$C$47*1000/$C$49-1)} -> 1.2917379 | H67: {=_xlfn.LET(_xlpm.w,($C$7+$B67*H$65)*(1-$C$12)+$C$19*$C$12,((SUMPRODUCT($G$30:$M$30,1/(1+_xlpm.w)^$G$32:$M$32) + $M$30*(1+$C$13)/(_xlpm.w-$C$13)/(1+_xlpm.w)^$M$32) + ($C$46-$C$40))/$C$47*1000/$C$49-1)} -> 1.2133667 | I67: {=_xlfn.LET(_xlpm.w,($C$7+$B67*I$65)*(1-$C$12)+$C$19*$C$12,((SUMPRODUCT($G$30:$M$30,1/(1+_xlpm.w)^$G$32:$M$32) + $M$30*(1+$C$13)/(_xlpm.w-$C$13)/(1+_xlpm.w)^$M$32) + ($C$46-$C$40))/$C$47*1000/$C$49-1)} -> 1.1396072
B68: =$C$8-0.1 -> 0.95 | C68: {=_xlfn.LET(_xlpm.w,($C$7+$B68*C$65)*(1-$C$12)+$C$19*$C$12,((SUMPRODUCT($G$30:$M$30,1/(1+_xlpm.w)^$G$32:$M$32) + $M$30*(1+$C$13)/(_xlpm.w-$C$13)/(1+_xlpm.w)^$M$32) + ($C$46-$C$40))/$C$47*1000/$C$49-1)} -> 1.4835597 | D68: {=_xlfn.LET(_xlpm.w,($C$7+$B68*D$65)*(1-$C$12)+$C$19*$C$12,((SUMPRODUCT($G$30:$M$30,1/(1+_xlpm.w)^$G$32:$M$32) + $M$30*(1+$C$13)/(_xlpm.w-$C$13)/(1+_xlpm.w)^$M$32) + ($C$46-$C$40))/$C$47*1000/$C$49-1)} -> 1.3830949 | E68: {=_xlfn.LET(_xlpm.w,($C$7+$B68*E$65)*(1-$C$12)+$C$19*$C$12,((SUMPRODUCT($G$30:$M$30,1/(1+_xlpm.w)^$G$32:$M$32) + $M$30*(1+$C$13)/(_xlpm.w-$C$13)/(1+_xlpm.w)^$M$32) + ($C$46-$C$40))/$C$47*1000/$C$49-1)} -> 1.2896477 | F68: {=_xlfn.LET(_xlpm.w,($C$7+$B68*F$65)*(1-$C$12)+$C$19*$C$12,((SUMPRODUCT($G$30:$M$30,1/(1+_xlpm.w)^$G$32:$M$32) + $M$30*(1+$C$13)/(_xlpm.w-$C$13)/(1+_xlpm.w)^$M$32) + ($C$46-$C$40))/$C$47*1000/$C$49-1)} -> 1.2025063 | G68: {=_xlfn.LET(_xlpm.w,($C$7+$B68*G$65)*(1-$C$12)+$C$19*$C$12,((SUMPRODUCT($G$30:$M$30,1/(1+_xlpm.w)^$G$32:$M$32) + $M$30*(1+$C$13)/(_xlpm.w-$C$13)/(1+_xlpm.w)^$M$32) + ($C$46-$C$40))/$C$47*1000/$C$49-1)} -> 1.1210522 | H68: {=_xlfn.LET(_xlpm.w,($C$7+$B68*H$65)*(1-$C$12)+$C$19*$C$12,((SUMPRODUCT($G$30:$M$30,1/(1+_xlpm.w)^$G$32:$M$32) + $M$30*(1+$C$13)/(_xlpm.w-$C$13)/(1+_xlpm.w)^$M$32) + ($C$46-$C$40))/$C$47*1000/$C$49-1)} -> 1.0447451 | I68: {=_xlfn.LET(_xlpm.w,($C$7+$B68*I$65)*(1-$C$12)+$C$19*$C$12,((SUMPRODUCT($G$30:$M$30,1/(1+_xlpm.w)^$G$32:$M$32) + $M$30*(1+$C$13)/(_xlpm.w-$C$13)/(1+_xlpm.w)^$M$32) + ($C$46-$C$40))/$C$47*1000/$C$49-1)} -> 0.97311099
B69: =$C$8 -> 1.05 | C69: {=_xlfn.LET(_xlpm.w,($C$7+$B69*C$65)*(1-$C$12)+$C$19*$C$12,((SUMPRODUCT($G$30:$M$30,1/(1+_xlpm.w)^$G$32:$M$32) + $M$30*(1+$C$13)/(_xlpm.w-$C$13)/(1+_xlpm.w)^$M$32) + ($C$46-$C$40))/$C$47*1000/$C$49-1)} -> 1.326037 | D69: {=_xlfn.LET(_xlpm.w,($C$7+$B69*D$65)*(1-$C$12)+$C$19*$C$12,((SUMPRODUCT($G$30:$M$30,1/(1+_xlpm.w)^$G$32:$M$32) + $M$30*(1+$C$13)/(_xlpm.w-$C$13)/(1+_xlpm.w)^$M$32) + ($C$46-$C$40))/$C$47*1000/$C$49-1)} -> 1.2273921 | E69: {=_xlfn.LET(_xlpm.w,($C$7+$B69*E$65)*(1-$C$12)+$C$19*$C$12,((SUMPRODUCT($G$30:$M$30,1/(1+_xlpm.w)^$G$32:$M$32) + $M$30*(1+$C$13)/(_xlpm.w-$C$13)/(1+_xlpm.w)^$M$32) + ($C$46-$C$40))/$C$47*1000/$C$49-1)} -> 1.135907 | F69: {=_xlfn.LET(_xlpm.w,($C$7+$B69*F$65)*(1-$C$12)+$C$19*$C$12,((SUMPRODUCT($G$30:$M$30,1/(1+_xlpm.w)^$G$32:$M$32) + $M$30*(1+$C$13)/(_xlpm.w-$C$13)/(1+_xlpm.w)^$M$32) + ($C$46-$C$40))/$C$47*1000/$C$49-1)} -> 1.0508282 | G69: {=_xlfn.LET(_xlpm.w,($C$7+$B69*G$65)*(1-$C$12)+$C$19*$C$12,((SUMPRODUCT($G$30:$M$30,1/(1+_xlpm.w)^$G$32:$M$32) + $M$30*(1+$C$13)/(_xlpm.w-$C$13)/(1+_xlpm.w)^$M$32) + ($C$46-$C$40))/$C$47*1000/$C$49-1)} -> 0.97150402 | H69: {=_xlfn.LET(_xlpm.w,($C$7+$B69*H$65)*(1-$C$12)+$C$19*$C$12,((SUMPRODUCT($G$30:$M$30,1/(1+_xlpm.w)^$G$32:$M$32) + $M$30*(1+$C$13)/(_xlpm.w-$C$13)/(1+_xlpm.w)^$M$32) + ($C$46-$C$40))/$C$47*1000/$C$49-1)} -> 0.89736857 | I69: {=_xlfn.LET(_xlpm.w,($C$7+$B69*I$65)*(1-$C$12)+$C$19*$C$12,((SUMPRODUCT($G$30:$M$30,1/(1+_xlpm.w)^$G$32:$M$32) + $M$30*(1+$C$13)/(_xlpm.w-$C$13)/(1+_xlpm.w)^$M$32) + ($C$46-$C$40))/$C$47*1000/$C$49-1)} -> 0.82792769
B70: =$C$8+0.1 -> 1.15 | C70: {=_xlfn.LET(_xlpm.w,($C$7+$B70*C$65)*(1-$C$12)+$C$19*$C$12,((SUMPRODUCT($G$30:$M$30,1/(1+_xlpm.w)^$G$32:$M$32) + $M$30*(1+$C$13)/(_xlpm.w-$C$13)/(1+_xlpm.w)^$M$32) + ($C$46-$C$40))/$C$47*1000/$C$49-1)} -> 1.1854291 | D70: {=_xlfn.LET(_xlpm.w,($C$7+$B70*D$65)*(1-$C$12)+$C$19*$C$12,((SUMPRODUCT($G$30:$M$30,1/(1+_xlpm.w)^$G$32:$M$32) + $M$30*(1+$C$13)/(_xlpm.w-$C$13)/(1+_xlpm.w)^$M$32) + ($C$46-$C$40))/$C$47*1000/$C$49-1)} -> 1.0888087 | E70: {=_xlfn.LET(_xlpm.w,($C$7+$B70*E$65)*(1-$C$12)+$C$19*$C$12,((SUMPRODUCT($G$30:$M$30,1/(1+_xlpm.w)^$G$32:$M$32) + $M$30*(1+$C$13)/(_xlpm.w-$C$13)/(1+_xlpm.w)^$M$32) + ($C$46-$C$40))/$C$47*1000/$C$49-1)} -> 0.99943508 | F70: {=_xlfn.LET(_xlpm.w,($C$7+$B70*F$65)*(1-$C$12)+$C$19*$C$12,((SUMPRODUCT($G$30:$M$30,1/(1+_xlpm.w)^$G$32:$M$32) + $M$30*(1+$C$13)/(_xlpm.w-$C$13)/(1+_xlpm.w)^$M$32) + ($C$46-$C$40))/$C$47*1000/$C$49-1)} -> 0.91652078 | G70: {=_xlfn.LET(_xlpm.w,($C$7+$B70*G$65)*(1-$C$12)+$C$19*$C$12,((SUMPRODUCT($G$30:$M$30,1/(1+_xlpm.w)^$G$32:$M$32) + $M$30*(1+$C$13)/(_xlpm.w-$C$13)/(1+_xlpm.w)^$M$32) + ($C$46-$C$40))/$C$47*1000/$C$49-1)} -> 0.83938842 | H70: {=_xlfn.LET(_xlpm.w,($C$7+$B70*H$65)*(1-$C$12)+$C$19*$C$12,((SUMPRODUCT($G$30:$M$30,1/(1+_xlpm.w)^$G$32:$M$32) + $M$30*(1+$C$13)/(_xlpm.w-$C$13)/(1+_xlpm.w)^$M$32) + ($C$46-$C$40))/$C$47*1000/$C$49-1)} -> 0.76745217 | I70: {=_xlfn.LET(_xlpm.w,($C$7+$B70*I$65)*(1-$C$12)+$C$19*$C$12,((SUMPRODUCT($G$30:$M$30,1/(1+_xlpm.w)^$G$32:$M$32) + $M$30*(1+$C$13)/(_xlpm.w-$C$13)/(1+_xlpm.w)^$M$32) + ($C$46-$C$40))/$C$47*1000/$C$49-1)} -> 0.70020281
B71: =$C$8+0.2 -> 1.25 | C71: {=_xlfn.LET(_xlpm.w,($C$7+$B71*C$65)*(1-$C$12)+$C$19*$C$12,((SUMPRODUCT($G$30:$M$30,1/(1+_xlpm.w)^$G$32:$M$32) + $M$30*(1+$C$13)/(_xlpm.w-$C$13)/(1+_xlpm.w)^$M$32) + ($C$46-$C$40))/$C$47*1000/$C$49-1)} -> 1.0591458 | D71: {=_xlfn.LET(_xlpm.w,($C$7+$B71*D$65)*(1-$C$12)+$C$19*$C$12,((SUMPRODUCT($G$30:$M$30,1/(1+_xlpm.w)^$G$32:$M$32) + $M$30*(1+$C$13)/(_xlpm.w-$C$13)/(1+_xlpm.w)^$M$32) + ($C$46-$C$40))/$C$47*1000/$C$49-1)} -> 0.96466346 | E71: {=_xlfn.LET(_xlpm.w,($C$7+$B71*E$65)*(1-$C$12)+$C$19*$C$12,((SUMPRODUCT($G$30:$M$30,1/(1+_xlpm.w)^$G$32:$M$32) + $M$30*(1+$C$13)/(_xlpm.w-$C$13)/(1+_xlpm.w)^$M$32) + ($C$46-$C$40))/$C$47*1000/$C$49-1)} -> 0.87747159 | F71: {=_xlfn.LET(_xlpm.w,($C$7+$B71*F$65)*(1-$C$12)+$C$19*$C$12,((SUMPRODUCT($G$30:$M$30,1/(1+_xlpm.w)^$G$32:$M$32) + $M$30*(1+$C$13)/(_xlpm.w-$C$13)/(1+_xlpm.w)^$M$32) + ($C$46-$C$40))/$C$47*1000/$C$49-1)} -> 0.79675584 | G71: {=_xlfn.LET(_xlpm.w,($C$7+$B71*G$65)*(1-$C$12)+$C$19*$C$12,((SUMPRODUCT($G$30:$M$30,1/(1+_xlpm.w)^$G$32:$M$32) + $M$30*(1+$C$13)/(_xlpm.w-$C$13)/(1+_xlpm.w)^$M$32) + ($C$46-$C$40))/$C$47*1000/$C$49-1)} -> 0.72181883 | H71: {=_xlfn.LET(_xlpm.w,($C$7+$B71*H$65)*(1-$C$12)+$C$19*$C$12,((SUMPRODUCT($G$30:$M$30,1/(1+_xlpm.w)^$G$32:$M$32) + $M$30*(1+$C$13)/(_xlpm.w-$C$13)/(1+_xlpm.w)^$M$32) + ($C$46-$C$40))/$C$47*1000/$C$49-1)} -> 0.65205986 | I71: {=_xlfn.LET(_xlpm.w,($C$7+$B71*I$65)*(1-$C$12)+$C$19*$C$12,((SUMPRODUCT($G$30:$M$30,1/(1+_xlpm.w)^$G$32:$M$32) + $M$30*(1+$C$13)/(_xlpm.w-$C$13)/(1+_xlpm.w)^$M$32) + ($C$46-$C$40))/$C$47*1000/$C$49-1)} -> 0.58695875
B72: =$C$8+0.3 -> 1.35 | C72: {=_xlfn.LET(_xlpm.w,($C$7+$B72*C$65)*(1-$C$12)+$C$19*$C$12,((SUMPRODUCT($G$30:$M$30,1/(1+_xlpm.w)^$G$32:$M$32) + $M$30*(1+$C$13)/(_xlpm.w-$C$13)/(1+_xlpm.w)^$M$32) + ($C$46-$C$40))/$C$47*1000/$C$49-1)} -> 0.94510004 | D72: {=_xlfn.LET(_xlpm.w,($C$7+$B72*D$65)*(1-$C$12)+$C$19*$C$12,((SUMPRODUCT($G$30:$M$30,1/(1+_xlpm.w)^$G$32:$M$32) + $M$30*(1+$C$13)/(_xlpm.w-$C$13)/(1+_xlpm.w)^$M$32) + ($C$46-$C$40))/$C$47*1000/$C$49-1)} -> 0.8528073 | E72: {=_xlfn.LET(_xlpm.w,($C$7+$B72*E$65)*(1-$C$12)+$C$19*$C$12,((SUMPRODUCT($G$30:$M$30,1/(1+_xlpm.w)^$G$32:$M$32) + $M$30*(1+$C$13)/(_xlpm.w-$C$13)/(1+_xlpm.w)^$M$32) + ($C$46-$C$40))/$C$47*1000/$C$49-1)} -> 0.76781492 | F72: {=_xlfn.LET(_xlpm.w,($C$7+$B72*F$65)*(1-$C$12)+$C$19*$C$12,((SUMPRODUCT($G$30:$M$30,1/(1+_xlpm.w)^$G$32:$M$32) + $M$30*(1+$C$13)/(_xlpm.w-$C$13)/(1+_xlpm.w)^$M$32) + ($C$46-$C$40))/$C$47*1000/$C$49-1)} -> 0.6892876 | G72: {=_xlfn.LET(_xlpm.w,($C$7+$B72*G$65)*(1-$C$12)+$C$19*$C$12,((SUMPRODUCT($G$30:$M$30,1/(1+_xlpm.w)^$G$32:$M$32) + $M$30*(1+$C$13)/(_xlpm.w-$C$13)/(1+_xlpm.w)^$M$32) + ($C$46-$C$40))/$C$47*1000/$C$49-1)} -> 0.61651284 | H72: {=_xlfn.LET(_xlpm.w,($C$7+$B72*H$65)*(1-$C$12)+$C$19*$C$12,((SUMPRODUCT($G$30:$M$30,1/(1+_xlpm.w)^$G$32:$M$32) + $M$30*(1+$C$13)/(_xlpm.w-$C$13)/(1+_xlpm.w)^$M$32) + ($C$46-$C$40))/$C$47*1000/$C$49-1)} -> 0.54887918 | I72: {=_xlfn.LET(_xlpm.w,($C$7+$B72*I$65)*(1-$C$12)+$C$19*$C$12,((SUMPRODUCT($G$30:$M$30,1/(1+_xlpm.w)^$G$32:$M$32) + $M$30*(1+$C$13)/(_xlpm.w-$C$13)/(1+_xlpm.w)^$M$32) + ($C$46-$C$40))/$C$47*1000/$C$49-1)} -> 0.48585887
B74: 6. Scenario Analysis
B76: Assumption | C76: Bear | D76: Base | E76: Bull
B77: Beta | C77: 1.05 | D77: 0.82336143 | E77: 0.65
B78: ERP | C78: 0.0911 | D78: 0.08112 | E78: 0.0711
B79: Terminal growth (g) | C79: 0.025 | D79: 0.025 | E79: 0.045
B80: FCFF adjustment (±%) | C80: -0.025 | D80: 0.025 | E80: 0.075
B81: Risk-free rate (Rf) | C81: 0.045 | D81: 0.042 | E81: 0.04
B82: Pre-tax Kd | C82: 0.11 | D82: 0.1 | E82: 0.09
B83: Tax rate | C83: 0.2 | D83: 0.18 | E83: 0.16
B84: D/(D+E) | C84: 0.35 | D84: 0.27794947 | E84: 0.22
B86: Output
B87: Cost of Equity (Ke) | C87: =C81+C77*C78 -> 0.140655 | D87: =D81+D77*D78 -> 0.10879108 | E87: =E81+E77*E78 -> 0.086215
B88: WACC | C88: =C87*(1-C84)+C82*(1-C83)*C84 -> 0.12222575 | D88: =D87*(1-D84)+D82*(1-D83)*D84 -> 0.10134451 | E88: =E87*(1-E84)+E82*(1-E83)*E84 -> 0.0838797
B89: PV of explicit FCFF (VND bn) | C89: {=SUMPRODUCT($G$30:$M$30,1/(1+C88)^$G$32:$M$32)*(1+C80)} -> 1829.7251 | D89: {=SUMPRODUCT($G$30:$M$30,1/(1+D88)^$G$32:$M$32)*(1+D80)} -> 2069.9419 | E89: {=SUMPRODUCT($G$30:$M$30,1/(1+E88)^$G$32:$M$32)*(1+E80)} -> 2312.2316
B90: PV of Terminal Value (VND bn) | C90: =$M$30*(1+C80)*(1+C79)/(C88-C79)/(1+C88)^$M$32 -> 2377.7812 | D90: =$M$30*(1+D80)*(1+D79)/(D88-D79)/(1+D88)^$M$32 -> 3609.1215 | E90: =$M$30*(1+E80)*(1+E79)/(E88-E79)/(1+E88)^$M$32 -> 8431.8323
B91: Enterprise Value (VND bn) | C91: =C89+C90 -> 4207.5063 | D91: =D89+D90 -> 5679.0634 | E91: =E89+E90 -> 10744.064
B92: (+/-) Net non-operating items | C92: =$C$46-$C$40 -> -385.79447 | D92: =$C$46-$C$40 -> -385.79447 | E92: =$C$46-$C$40 -> -385.79447
B93: Equity Value per share (VND) | C93: =(C91+C92)/$C$47*1000 -> 19925.293 | D93: =(D91+D92)/$C$47*1000 -> 27597.564 | E93: =(E91+E92)/$C$47*1000 -> 54005.003
B94: Upside / (Downside) | C94: =C93/$C$49-1 -> 0.99452387 | D94: =D93/$C$49-1 -> 1.7625189 | E94: =E93/$C$49-1 -> 4.4059062
B96: 7. Input Sensitivity — Elasticity to Equity Value per Share
B97: Each input shocked ±10% holding others constant. Elasticity = % Δ price / 10%.
B99: Input | C99: Base value | D99: -10% case | E99: +10% case | F99: Price -10% | G99: Price +10% | H99: % Δ (-10%) | I99: % Δ (+10%) | J99: Elasticity | K99: Range (abs)
B100: Risk-free rate (Rf) | C100: =$C$7 -> 0.045 | D100: =C100*0.9 -> 0.0405 | E100: =C100*1.1 -> 0.0495 | F100: {=_xlfn.LET(_xlpm.rf,D100,_xlpm.b,$C$8,_xlpm.erp,$C$9,_xlpm.kd,$C$10,_xlpm.tx,$C$11,_xlpm.de,$C$12,_xlpm.g,$C$13,_xlpm.w,(_xlpm.rf+_xlpm.b*_xlpm.erp)*(1-_xlpm.de)+_xlpm.kd*(1-_xlpm.tx)*_xlpm.de,((SUMPRODUCT($G$30:$M$30,1/(1+_xlpm.w)^$G$32:$M$32)+$M$30*(1+_xlpm.g)/(_xlpm.w-_xlpm.g)/(1+_xlpm.w)^$M$32)+($C$46-$C$40))/$C$47*1000)} -> 21212.535 | G100: {=_xlfn.LET(_xlpm.rf,E100,_xlpm.b,$C$8,_xlpm.erp,$C$9,_xlpm.kd,$C$10,_xlpm.tx,$C$11,_xlpm.de,$C$12,_xlpm.g,$C$13,_xlpm.w,(_xlpm.rf+_xlpm.b*_xlpm.erp)*(1-_xlpm.de)+_xlpm.kd*(1-_xlpm.tx)*_xlpm.de,((SUMPRODUCT($G$30:$M$30,1/(1+_xlpm.w)^$G$32:$M$32)+$M$30*(1+_xlpm.g)/(_xlpm.w-_xlpm.g)/(1+_xlpm.w)^$M$32)+($C$46-$C$40))/$C$47*1000)} -> 19805.235 | H100: =F100/$C$48-1 -> 0.064603396 | I100: =G100/$C$48-1 -> -0.0060254338 | J100: =(I100-H100)/0.2 -> -0.35314415 | K100: =ABS(I100-H100) -> 0.07062883
B101: Beta | C101: =$C$8 -> 1.05 | D101: =C101*0.9 -> 0.945 | E101: =C101*1.1 -> 1.155 | F101: {=_xlfn.LET(_xlpm.rf,$C$7,_xlpm.b,D101,_xlpm.erp,$C$9,_xlpm.kd,$C$10,_xlpm.tx,$C$11,_xlpm.de,$C$12,_xlpm.g,$C$13,_xlpm.w,(_xlpm.rf+_xlpm.b*_xlpm.erp)*(1-_xlpm.de)+_xlpm.kd*(1-_xlpm.tx)*_xlpm.de,((SUMPRODUCT($G$30:$M$30,1/(1+_xlpm.w)^$G$32:$M$32)+$M$30*(1+_xlpm.g)/(_xlpm.w-_xlpm.g)/(1+_xlpm.w)^$M$32)+($C$46-$C$40))/$C$47*1000)} -> 22083.964 | G101: {=_xlfn.LET(_xlpm.rf,$C$7,_xlpm.b,E101,_xlpm.erp,$C$9,_xlpm.kd,$C$10,_xlpm.tx,$C$11,_xlpm.de,$C$12,_xlpm.g,$C$13,_xlpm.w,(_xlpm.rf+_xlpm.b*_xlpm.erp)*(1-_xlpm.de)+_xlpm.kd*(1-_xlpm.tx)*_xlpm.de,((SUMPRODUCT($G$30:$M$30,1/(1+_xlpm.w)^$G$32:$M$32)+$M$30*(1+_xlpm.g)/(_xlpm.w-_xlpm.g)/(1+_xlpm.w)^$M$32)+($C$46-$C$40))/$C$47*1000)} -> 19082.977 | H101: =F101/$C$48-1 -> 0.10833822 | I101: =G101/$C$48-1 -> -0.042273736 | J101: =(I101-H101)/0.2 -> -0.75305979 | K101: =ABS(I101-H101) -> 0.15061196
B102: Equity Risk Premium (ERP) | C102: =$C$9 -> 0.0911 | D102: =C102*0.9 -> 0.08199 | E102: =C102*1.1 -> 0.10021 | F102: {=_xlfn.LET(_xlpm.rf,$C$7,_xlpm.b,$C$8,_xlpm.erp,D102,_xlpm.kd,$C$10,_xlpm.tx,$C$11,_xlpm.de,$C$12,_xlpm.g,$C$13,_xlpm.w,(_xlpm.rf+_xlpm.b*_xlpm.erp)*(1-_xlpm.de)+_xlpm.kd*(1-_xlpm.tx)*_xlpm.de,((SUMPRODUCT($G$30:$M$30,1/(1+_xlpm.w)^$G$32:$M$32)+$M$30*(1+_xlpm.g)/(_xlpm.w-_xlpm.g)/(1+_xlpm.w)^$M$32)+($C$46-$C$40))/$C$47*1000)} -> 22083.964 | G102: {=_xlfn.LET(_xlpm.rf,$C$7,_xlpm.b,$C$8,_xlpm.erp,E102,_xlpm.kd,$C$10,_xlpm.tx,$C$11,_xlpm.de,$C$12,_xlpm.g,$C$13,_xlpm.w,(_xlpm.rf+_xlpm.b*_xlpm.erp)*(1-_xlpm.de)+_xlpm.kd*(1-_xlpm.tx)*_xlpm.de,((SUMPRODUCT($G$30:$M$30,1/(1+_xlpm.w)^$G$32:$M$32)+$M$30*(1+_xlpm.g)/(_xlpm.w-_xlpm.g)/(1+_xlpm.w)^$M$32)+($C$46-$C$40))/$C$47*1000)} -> 19082.977 | H102: =F102/$C$48-1 -> 0.10833822 | I102: =G102/$C$48-1 -> -0.042273736 | J102: =(I102-H102)/0.2 -> -0.75305979 | K102: =ABS(I102-H102) -> 0.15061196
B103: Pre-tax Cost of Debt (Kd) | C103: =$C$10 -> 0.11 | D103: =C103*0.9 -> 0.099 | E103: =C103*1.1 -> 0.121 | F103: {=_xlfn.LET(_xlpm.rf,$C$7,_xlpm.b,$C$8,_xlpm.erp,$C$9,_xlpm.kd,D103,_xlpm.tx,$C$11,_xlpm.de,$C$12,_xlpm.g,$C$13,_xlpm.w,(_xlpm.rf+_xlpm.b*_xlpm.erp)*(1-_xlpm.de)+_xlpm.kd*(1-_xlpm.tx)*_xlpm.de,((SUMPRODUCT($G$30:$M$30,1/(1+_xlpm.w)^$G$32:$M$32)+$M$30*(1+_xlpm.g)/(_xlpm.w-_xlpm.g)/(1+_xlpm.w)^$M$32)+($C$46-$C$40))/$C$47*1000)} -> 21252.194 | G103: {=_xlfn.LET(_xlpm.rf,$C$7,_xlpm.b,$C$8,_xlpm.erp,$C$9,_xlpm.kd,E103,_xlpm.tx,$C$11,_xlpm.de,$C$12,_xlpm.g,$C$13,_xlpm.w,(_xlpm.rf+_xlpm.b*_xlpm.erp)*(1-_xlpm.de)+_xlpm.kd*(1-_xlpm.tx)*_xlpm.de,((SUMPRODUCT($G$30:$M$30,1/(1+_xlpm.w)^$G$32:$M$32)+$M$30*(1+_xlpm.g)/(_xlpm.w-_xlpm.g)/(1+_xlpm.w)^$M$32)+($C$46-$C$40))/$C$47*1000)} -> 19770.174 | H103: =F103/$C$48-1 -> 0.066593797 | I103: =G103/$C$48-1 -> -0.0077850656 | J103: =(I103-H103)/0.2 -> -0.37189431 | K103: =ABS(I103-H103) -> 0.074378862
B104: Tax rate | C104: =$C$11 -> 0.2 | D104: =C104*0.9 -> 0.18 | E104: =C104*1.1 -> 0.22 | F104: {=_xlfn.LET(_xlpm.rf,$C$7,_xlpm.b,$C$8,_xlpm.erp,$C$9,_xlpm.kd,$C$10,_xlpm.tx,D104,_xlpm.de,$C$12,_xlpm.g,$C$13,_xlpm.w,(_xlpm.rf+_xlpm.b*_xlpm.erp)*(1-_xlpm.de)+_xlpm.kd*(1-_xlpm.tx)*_xlpm.de,((SUMPRODUCT($G$30:$M$30,1/(1+_xlpm.w)^$G$32:$M$32)+$M$30*(1+_xlpm.g)/(_xlpm.w-_xlpm.g)/(1+_xlpm.w)^$M$32)+($C$46-$C$40))/$C$47*1000)} -> 20304.156 | G104: {=_xlfn.LET(_xlpm.rf,$C$7,_xlpm.b,$C$8,_xlpm.erp,$C$9,_xlpm.kd,$C$10,_xlpm.tx,E104,_xlpm.de,$C$12,_xlpm.g,$C$13,_xlpm.w,(_xlpm.rf+_xlpm.b*_xlpm.erp)*(1-_xlpm.de)+_xlpm.kd*(1-_xlpm.tx)*_xlpm.de,((SUMPRODUCT($G$30:$M$30,1/(1+_xlpm.w)^$G$32:$M$32)+$M$30*(1+_xlpm.g)/(_xlpm.w-_xlpm.g)/(1+_xlpm.w)^$M$32)+($C$46-$C$40))/$C$47*1000)} -> 20674.314 | H104: =F104/$C$48-1 -> 0.019014165 | I104: =G104/$C$48-1 -> 0.037591438 | J104: =(I104-H104)/0.2 -> 0.092886365 | K104: =ABS(I104-H104) -> 0.018577273
B105: Target D/(D+E) | C105: =$C$12 -> 0.35 | D105: =C105*0.9 -> 0.315 | E105: =C105*1.1 -> 0.385 | F105: {=_xlfn.LET(_xlpm.rf,$C$7,_xlpm.b,$C$8,_xlpm.erp,$C$9,_xlpm.kd,$C$10,_xlpm.tx,$C$11,_xlpm.de,D105,_xlpm.g,$C$13,_xlpm.w,(_xlpm.rf+_xlpm.b*_xlpm.erp)*(1-_xlpm.de)+_xlpm.kd*(1-_xlpm.tx)*_xlpm.de,((SUMPRODUCT($G$30:$M$30,1/(1+_xlpm.w)^$G$32:$M$32)+$M$30*(1+_xlpm.g)/(_xlpm.w-_xlpm.g)/(1+_xlpm.w)^$M$32)+($C$46-$C$40))/$C$47*1000)} -> 20053.049 | G105: {=_xlfn.LET(_xlpm.rf,$C$7,_xlpm.b,$C$8,_xlpm.erp,$C$9,_xlpm.kd,$C$10,_xlpm.tx,$C$11,_xlpm.de,E105,_xlpm.g,$C$13,_xlpm.w,(_xlpm.rf+_xlpm.b*_xlpm.erp)*(1-_xlpm.de)+_xlpm.kd*(1-_xlpm.tx)*_xlpm.de,((SUMPRODUCT($G$30:$M$30,1/(1+_xlpm.w)^$G$32:$M$32)+$M$30*(1+_xlpm.g)/(_xlpm.w-_xlpm.g)/(1+_xlpm.w)^$M$32)+($C$46-$C$40))/$C$47*1000)} -> 20939.25 | H105: =F105/$C$48-1 -> 0.0064117381 | I105: =G105/$C$48-1 -> 0.050887904 | J105: =(I105-H105)/0.2 -> 0.22238083 | K105: =ABS(I105-H105) -> 0.044476166
B106: Constant growth (g) | C106: =$C$13 -> 0.025 | D106: =C106*0.9 -> 0.0225 | E106: =C106*1.1 -> 0.0275 | F106: {=_xlfn.LET(_xlpm.rf,$C$7,_xlpm.b,$C$8,_xlpm.erp,$C$9,_xlpm.kd,$C$10,_xlpm.tx,$C$11,_xlpm.de,$C$12,_xlpm.g,D106,_xlpm.w,(_xlpm.rf+_xlpm.b*_xlpm.erp)*(1-_xlpm.de)+_xlpm.kd*(1-_xlpm.tx)*_xlpm.de,((SUMPRODUCT($G$30:$M$30,1/(1+_xlpm.w)^$G$32:$M$32)+$M$30*(1+_xlpm.g)/(_xlpm.w-_xlpm.g)/(1+_xlpm.w)^$M$32)+($C$46-$C$40))/$C$47*1000)} -> 20138.791 | G106: {=_xlfn.LET(_xlpm.rf,$C$7,_xlpm.b,$C$8,_xlpm.erp,$C$9,_xlpm.kd,$C$10,_xlpm.tx,$C$11,_xlpm.de,$C$12,_xlpm.g,E106,_xlpm.w,(_xlpm.rf+_xlpm.b*_xlpm.erp)*(1-_xlpm.de)+_xlpm.kd*(1-_xlpm.tx)*_xlpm.de,((SUMPRODUCT($G$30:$M$30,1/(1+_xlpm.w)^$G$32:$M$32)+$M$30*(1+_xlpm.g)/(_xlpm.w-_xlpm.g)/(1+_xlpm.w)^$M$32)+($C$46-$C$40))/$C$47*1000)} -> 20855.176 | H106: =F106/$C$48-1 -> 0.010714911 | I106: =G106/$C$48-1 -> 0.04666845 | J106: =(I106-H106)/0.2 -> 0.17976769 | K106: =ABS(I106-H106) -> 0.035953539
B107: FCFF stream (±10%) | C107: 1 | D107: 0.9 | E107: 1.1 | F107: {=_xlfn.LET(_xlpm.rf,$C$7,_xlpm.b,$C$8,_xlpm.erp,$C$9,_xlpm.kd,$C$10,_xlpm.tx,$C$11,_xlpm.de,$C$12,_xlpm.g,$C$13,_xlpm.m,D107,_xlpm.w,(_xlpm.rf+_xlpm.b*_xlpm.erp)*(1-_xlpm.de)+_xlpm.kd*(1-_xlpm.tx)*_xlpm.de,((SUMPRODUCT($G$30:$M$30,1/(1+_xlpm.w)^$G$32:$M$32)*_xlpm.m+$M$30*_xlpm.m*(1+_xlpm.g)/(_xlpm.w-_xlpm.g)/(1+_xlpm.w)^$M$32)+($C$46-$C$40))/$C$47*1000)} -> 18237.854 | G107: {=_xlfn.LET(_xlpm.rf,$C$7,_xlpm.b,$C$8,_xlpm.erp,$C$9,_xlpm.kd,$C$10,_xlpm.tx,$C$11,_xlpm.de,$C$12,_xlpm.g,$C$13,_xlpm.m,E107,_xlpm.w,(_xlpm.rf+_xlpm.b*_xlpm.erp)*(1-_xlpm.de)+_xlpm.kd*(1-_xlpm.tx)*_xlpm.de,((SUMPRODUCT($G$30:$M$30,1/(1+_xlpm.w)^$G$32:$M$32)*_xlpm.m+$M$30*_xlpm.m*(1+_xlpm.g)/(_xlpm.w-_xlpm.g)/(1+_xlpm.w)^$M$32)+($C$46-$C$40))/$C$47*1000)} -> 22737.693 | H107: =F107/$C$48-1 -> -0.084688314 | I107: =G107/$C$48-1 -> 0.14114719 | J107: =(I107-H107)/0.2 -> 1.1291775 | K107: =ABS(I107-H107) -> 0.2258355

Sheet Analysis
B1: PHÂN TÍCH TÀI CHÍNH YEG 2021A-2031F
B3: A. Income Statement Analysis (tỷ VND)
B4: Chỉ tiêu | C4: 2021 | D4: 2022 | E4: 2023 | F4: 2024 | G4: 2025 | H4: 2026F | I4: 2027F | J4: 2028F | K4: 2029F | L4: 2030F | M4: 2031F | N4: Nhận xét
B5: Doanh thu thuần | C5: =OD_IS!D4/1000000000 -> 1079.5078 | D5: =OD_IS!E4/1000000000 -> 314.12431 | E5: =OD_IS!F4/1000000000 -> 411.66678 | F5: =OD_IS!G4/1000000000 -> 1026.0949 | G5: =OD_IS!H4/1000000000 -> 1639.0631 | H5: =OD_IS!I4/1000000000 -> 2130.782 | I5: =OD_IS!J4/1000000000 -> 2599.554 | J5: =OD_IS!K4/1000000000 -> 2989.4871 | ... M5: =OD_IS!N4/1000000000 -> 3762.9871 | N5: Bùng nổ 2024-2025 nhờ Premium Content; forecast tăng trưởng 35% → 6%
B6: Tăng trưởng YoY | C6: - | D6: =D5/C5-1 -> -0.70901154 | E6: =E5/D5-1 -> 0.31052191 | F6: =F5/E5-1 -> 1.4925374 | G6: =G5/F5-1 -> 0.59737967 | H6: =H5/G5-1 -> 0.3 | I6: =I5/H5-1 -> 0.22 | J6: =J5/I5-1 -> 0.15 | K6: =K5/J5-1 -> 0.11 | ... M6: =M5/L5-1 -> 0.05 | N6: Catalysts: Show It All, HAHA Farmer, ATVNCG concerts, JV SYE Holdings
B7: Lợi nhuận gộp | C7: =OD_IS!D6/1000000000 -> 34.12509 | D7: =OD_IS!E6/1000000000 -> 104.47869 | E7: =OD_IS!F6/1000000000 -> 115.18583 | F7: =OD_IS!G6/1000000000 -> 170.85116 | G7: =OD_IS!H6/1000000000 -> 215.03471 | H7: =OD_IS!I6/1000000000 -> 277.00166 | I7: =OD_IS!J6/1000000000 -> 363.93757 | J7: =OD_IS!K6/1000000000 -> 478.31794 | ... M7: =OD_IS!N6/1000000000 -> 714.96754 | N7: Cải thiện dần nhờ operating leverage và tái sử dụng IP
B8: Biên lợi nhuận gộp (%) | C8: =C7/C5 -> 0.031611712 | D8: =D7/D5 -> 0.332603 | E8: =E7/E5 -> 0.27980356 | F8: =F7/F5 -> 0.16650621 | G8: =G7/G5 -> 0.13119367 | H8: =H7/H5 -> 0.13 | I8: =I7/I5 -> 0.14 | J8: =J7/J5 -> 0.16 | ... M8: =M7/M5 -> 0.19 | N8: GPM 13% (2025) → 22% (2031F): production scale + IP reuse
B9: Lợi nhuận HDKD | C9: =OD_IS!D9/1000000000 -> -263.75766 | D9: =OD_IS!E9/1000000000 -> -9.564239 | E9: =OD_IS!F9/1000000000 -> 34.024857 | F9: =OD_IS!G9/1000000000 -> -7.0218772 | G9: =OD_IS!H9/1000000000 -> 7.9368393 | H9: =OD_IS!I9/1000000000 -> 10.65391 | I9: =OD_IS!J9/1000000000 -> 44.192419 | J9: =OD_IS!K9/1000000000 -> 119.57949 | ... M9: =OD_IS!N9/1000000000 -> 282.22403 | N9: Core biz chuyển từ lỗ sang lãi bền vững từ 2027F
B10: Doanh thu tài chính | C10: =OD_IS!D10/1000000000 -> 423.84935 | D10: =OD_IS!E10/1000000000 -> 47.340388 | E10: =OD_IS!F10/1000000000 -> 43.586402 | F10: =OD_IS!G10/1000000000 -> 191.90651 | G10: =OD_IS!H10/1000000000 -> 120.34918 | H10: =OD_IS!I10/1000000000 -> 127.84692 | I10: =OD_IS!J10/1000000000 -> 129.9777 | J10: =OD_IS!K10/1000000000 -> 119.57949 | ... M10: =OD_IS!N10/1000000000 -> 131.70455 | N10: Giảm dần khi rút đầu tư tài chính để fund Premium Content
B11: PBT (LN trước thuế) | C11: =OD_IS!D16/1000000000 -> 98.316716 | D11: =OD_IS!E16/1000000000 -> 28.915008 | E11: =OD_IS!F16/1000000000 -> 28.924118 | F11: =OD_IS!G16/1000000000 -> 118.55276 | G11: =OD_IS!H16/1000000000 -> 99.631384 | H11: =OD_IS!I16/1000000000 -> 100.97564 | I11: =OD_IS!J16/1000000000 -> 136.64493 | J11: =OD_IS!K16/1000000000 -> 201.63379 | ... M11: =OD_IS!N16/1000000000 -> 376.40339
B12: Lợi nhuận sau thuế (EAT) | C12: =OD_IS!D21/1000000000 -> 29.990231 | D12: =OD_IS!E21/1000000000 -> 24.89086 | E12: =OD_IS!F21/1000000000 -> 26.518959 | F12: =OD_IS!G21/1000000000 -> 130.50451 | G12: =OD_IS!H21/1000000000 -> 82.353089 | H12: =OD_IS!I21/1000000000 -> 80.780515 | I12: =OD_IS!J21/1000000000 -> 109.31595 | J12: =OD_IS!K21/1000000000 -> 161.30703 | ... M12: =OD_IS!N21/1000000000 -> 301.12271 | N12: EAT tăng 5.6x từ 2025→2031F
B13: Biên LN ròng (NPM) | C13: =C12/C5 -> 0.027781394 | D13: =D12/D5 -> 0.079238887 | E13: =E12/E5 -> 0.064418506 | F13: =F12/F5 -> 0.12718561 | G13: =G12/G5 -> 0.050244002 | H13: =H12/H5 -> 0.037911206 | I13: =I12/I5 -> 0.042051808 | J13: =J12/J5 -> 0.053958094 | ... M13: =M12/M5 -> 0.080022256 | N13: NPM hồi phục về 11% (2031F)
B15: B. Balance Sheet Analysis (tỷ VND)
B16: Chỉ tiêu | C16: 2021 | D16: 2022 | E16: 2023 | F16: 2024 | G16: 2025 | H16: 2026F | I16: 2027F | J16: 2028F | K16: 2029F | L16: 2030F | M16: 2031F | N16: Nhận xét
B17: Tổng tài sản | C17: =OD_BS!D4/1000000000 -> 1388.4671 | D17: =OD_BS!E4/1000000000 -> 1311.9323 | E17: =OD_BS!F4/1000000000 -> 1891.2257 | F17: =OD_BS!G4/1000000000 -> 2814.7329 | G17: =OD_BS!H4/1000000000 -> 3066.2342 | H17: =OD_BS!I4/1000000000 -> 2370.3758 | I17: =OD_BS!J4/1000000000 -> 2279.6022 | J17: =OD_BS!K4/1000000000 -> 2171.0505 | ... M17: =OD_BS!N4/1000000000 -> 1817.1291 | N17: Tăng 2.2x trong 4 năm đầu; mở rộng theo doanh thu
B18: Tiền & tương đương | C18: =OD_BS!D6/1000000000 -> 4.3212259 | D18: =OD_BS!E6/1000000000 -> 26.473014 | E18: =OD_BS!F6/1000000000 -> 8.4613394 | F18: =OD_BS!G6/1000000000 -> 136.23607 | G18: =OD_BS!H6/1000000000 -> 288.52418 | H18: =OD_BS!I6/1000000000 -> 288.52418 | I18: =OD_BS!J6/1000000000 -> 288.52418 | J18: =OD_BS!K6/1000000000 -> 288.52418 | ... M18: =OD_BS!N6/1000000000 -> 288.52418 | N18: Giữ flat 288B trong forecast (cash floor)
B19: Khoản phải thu | C19: =OD_BS!D8/1000000000 -> 1059.5576 | D19: =OD_BS!E8/1000000000 -> 541.29693 | E19: =OD_BS!F8/1000000000 -> 845.39542 | F19: =OD_BS!G8/1000000000 -> 1101.9305 | G19: =OD_BS!H8/1000000000 -> 1305.1999 | H19: =OD_BS!I8/1000000000 -> 700.53107 | I19: =OD_BS!J8/1000000000 -> 712.20659 | J19: =OD_BS!K8/1000000000 -> 737.13382 | ... M19: =OD_BS!N8/1000000000 -> 824.76429
B20: DSO (Days) | C20: =365*C19/C5 -> 358.25449 | D20: =365*D19/D5 -> 628.96559 | E20: =365*E19/E5 -> 749.56091 | F20: =365*F19/F5 -> 391.97605 | G20: =365*G19/G5 -> 290.65262 | H20: =365*H19/H5 -> 120 | I20: =365*I19/I5 -> 100 | J20: =365*J19/J5 -> 90 | ... M20: =365*M19/M5 -> 80 | N20: DSO 291 (2025) → 80 (2031F): cải thiện thu hồi công nợ
B21: TSCĐ ròng | C21: =OD_BS!D14/1000000000 -> 52.169827 | D21: =OD_BS!E14/1000000000 -> 105.74731 | E21: =OD_BS!F14/1000000000 -> 130.49997 | F21: =OD_BS!G14/1000000000 -> 573.57084 | G21: =OD_BS!H14/1000000000 -> 550.35844 | H21: =OD_BS!I14/1000000000 -> 428.20536 | I21: =OD_BS!J14/1000000000 -> 295.68306 | J21: =OD_BS!K14/1000000000 -> 139.63754 | ... M21: =OD_BS!N14/1000000000 -> -346.11106
B22: Nợ vay ngắn hạn | C22: =OD_BS!D21/1000000000 -> 130.79622 | D22: =OD_BS!E21/1000000000 -> 94.317807 | E22: =OD_BS!F21/1000000000 -> 171.35269 | F22: =OD_BS!G21/1000000000 -> 527.3641 | G22: =OD_BS!H21/1000000000 -> 304.27126 | H22: =OD_BS!I21/1000000000 -> 1495.2621 | I22: =OD_BS!J21/1000000000 -> 1161.7545 | J22: =OD_BS!K21/1000000000 -> 793.38587 | ... M22: =OD_BS!N21/1000000000 -> 304.27126 | N22: ST debt làm revolver/balancing plug trong forecast
B23: Nợ vay dài hạn | C23: =OD_BS!D24/1000000000 -> 71 | D23: =OD_BS!E24/1000000000 -> 1 | E23: =OD_BS!F24/1000000000 -> 39.014433 | F23: =OD_BS!G24/1000000000 -> 50.006061 | G23: =OD_BS!H24/1000000000 -> 36.866802 | H23: =OD_BS!I24/1000000000 -> 36.866802 | I23: =OD_BS!J24/1000000000 -> 36.866802 | J23: =OD_BS!K24/1000000000 -> 36.866802 | ... M23: =OD_BS!N24/1000000000 -> 36.866802
B24: Vốn chủ sở hữu | C24: =OD_BS!D26/1000000000 -> 564.64815 | D24: =OD_BS!E26/1000000000 -> 575.68609 | E24: =OD_BS!F26/1000000000 -> 412.35287 | F24: =OD_BS!G26/1000000000 -> 182.91739 | G24: =OD_BS!H26/1000000000 -> 130.61254 | H24: =OD_BS!I26/1000000000 -> 211.39306 | I24: =OD_BS!J26/1000000000 -> 320.709 | J24: =OD_BS!K26/1000000000 -> 473.95068 | ... M24: =OD_BS!N26/1000000000 -> 1162.1338 | N24: VCSH phục hồi mạnh nhờ retained earnings từ 2026F
B25: D/E (Debt/Equity) | C25: =(C22+C23)/C24 -> 0.35738401 | D25: =(D22+D23)/D24 -> 0.16557254 | E25: =(E22+E23)/E24 -> 0.51016288 | F25: =(F22+F23)/F24 -> 3.1564531 | G25: =(G22+G23)/G24 -> 2.6118324 | H25: =(H22+H23)/H24 -> 7.2477729 | I25: =(I22+I23)/I24 -> 3.737411 | J25: =(J22+J23)/J24 -> 1.7517702 | ... M25: =(M22+M23)/M24 -> 0.29354455 | N25: D/E giảm dần khi VCSH tích lũy lợi nhuận
B26: ROE | C26: =C12/C24 -> 0.053113132 | D26: =D12/D24 -> 0.043236863 | E26: =E12/E24 -> 0.064311325 | F26: =F12/F24 -> 0.71346146 | G26: =G12/G24 -> 0.63051441 | H26: =H12/H24 -> 0.38213419 | I26: =I12/I24 -> 0.34085712 | J26: =J12/J24 -> 0.3403456 | ... M26: =M12/M24 -> 0.2591119 | N26: ROE đỉnh ~63% (2025) sau giảm dần khi VCSH dày lên
B27: ROA | C27: =C12/C17 -> 0.021599525 | D27: =D12/D17 -> 0.018972671 | E27: =E12/E17 -> 0.014022102 | F27: =F12/F17 -> 0.046364793 | G27: =G12/G17 -> 0.026858056 | H27: =H12/H17 -> 0.034079202 | I27: =I12/I17 -> 0.047953958 | J27: =J12/J17 -> 0.074299068 | ... M27: =M12/M17 -> 0.16571344 | N27: ROA cải thiện từ 2.7% (2025) → 16% (2031F)
B29: C. Cash Flow Statement Analysis (tỷ VND)
B30: Chỉ tiêu | C30: 2021 | D30: 2022 | E30: 2023 | F30: 2024 | G30: 2025 | H30: 2026F | I30: 2027F | J30: 2028F | K30: 2029F | L30: 2030F | M30: 2031F | N30: Nhận xét
B31: CFO | C31: =OD_CF!D4/1000000000 -> -88.400374 | D31: =OD_CF!E4/1000000000 -> -165.31888 | E31: =OD_CF!F4/1000000000 -> -192.46959 | F31: =OD_CF!G4/1000000000 -> 357.42785 | G31: =OD_CF!H4/1000000000 -> 7.3654269 | H31: =OD_CF!I4/1000000000 -> 1196.8475 | I31: =OD_CF!J4/1000000000 -> 463.48523 | J31: =OD_CF!K4/1000000000 -> 496.01351 | ... M31: =OD_CF!N4/1000000000 -> 620.38469 | N31: CFO dương bền vững từ 2026F
B32: CFO / EAT | C32: =IFERROR(C31/C12,"-") -> -2.9476389 | D32: =IFERROR(D31/D12,"-") -> -6.6417503 | E32: =IFERROR(E31/E12,"-") -> -7.2578107 | F32: =IFERROR(F31/F12,"-") -> 2.7388162 | G32: =IFERROR(G31/G12,"-") -> 0.089437166 | H32: =IFERROR(H31/H12,"-") -> 14.816042 | I32: =IFERROR(I31/I12,"-") -> 4.2398684 | J32: =IFERROR(J31/J12,"-") -> 3.0749653 | ... M32: =IFERROR(M31/M12,"-") -> 2.0602388 | N32: Earnings quality cải thiện
B33: CFI | C33: =OD_CF!D9/1000000000 -> 11.187918 | D33: =OD_CF!E9/1000000000 -> 293.11008 | E33: =OD_CF!F9/1000000000 -> -397.14476 | F33: =OD_CF!G9/1000000000 -> -613.62811 | G33: =OD_CF!H9/1000000000 -> -192.80034 | H33: =OD_CF!I9/1000000000 -> -127.84692 | I33: =OD_CF!J9/1000000000 -> -129.9777 | J33: =OD_CF!K9/1000000000 -> -119.57949 | ... M33: =OD_CF!N9/1000000000 -> -150.51948 | N33: CFI âm ổn định = CapEx đầu tư thiết bị production
B34: CFF | C34: =OD_CF!D14/1000000000 -> 45.121186 | D34: =OD_CF!E14/1000000000 -> -105.63941 | E34: =OD_CF!F14/1000000000 -> 571.60268 | F34: =OD_CF!G14/1000000000 -> 383.97499 | G34: =OD_CF!H14/1000000000 -> 337.71082 | H34: =OD_CF!I14/1000000000 -> 1190.9908 | I34: =OD_CF!J14/1000000000 -> -333.50753 | J34: =OD_CF!K14/1000000000 -> -376.43402 | ... M34: =OD_CF!N14/1000000000 -> -60.224542
B35: D&A | C35: =OD_CF!D6/1000000000 -> 200.43436 | D35: =OD_CF!E6/1000000000 -> 201.52652 | E35: =OD_CF!F6/1000000000 -> 193.36753 | F35: =OD_CF!G6/1000000000 -> 254.23043 | G35: =OD_CF!H6/1000000000 -> 0 | H35: =OD_CF!I6/1000000000 -> 250 | I35: =OD_CF!J6/1000000000 -> 262.5 | J35: =OD_CF!K6/1000000000 -> 275.625 | ... M35: =OD_CF!N6/1000000000 -> 319.07039
B36: CapEx | C36: =-OD_CF!D10/1000000000 -> 2.9118948 | D36: =-OD_CF!E10/1000000000 -> 0.26209091 | E36: =-OD_CF!F10/1000000000 -> 85.145284 | F36: =-OD_CF!G10/1000000000 -> 552.93982 | G36: =-OD_CF!H10/1000000000 -> 98.219384 | H36: =-OD_CF!I10/1000000000 -> 127.84692 | I36: =-OD_CF!J10/1000000000 -> 129.9777 | J36: =-OD_CF!K10/1000000000 -> 119.57949 | ... M36: =-OD_CF!N10/1000000000 -> 150.51948 | N36: CapEx asset-light ~4-6% revenue (media biz)
B37: FCF (CFO - CapEx) | C37: =C31-C36 -> -91.312268 | D37: =D31-D36 -> -165.58097 | E37: =E31-E36 -> -277.61487 | F37: =F31-F36 -> -195.51197 | G37: =G31-G36 -> -90.853957 | H37: =H31-H36 -> 1069.0005 | I37: =I31-I36 -> 333.50753 | J37: =J31-J36 -> 376.43402 | ... M37: =M31-M36 -> 469.8652 | N37: FCF chuyển dương bền vững từ 2026F
B39: D. Valuation Summary (DCF Method)
B40: Chỉ tiêu | C40: Giá trị | D40: Nguồn / Logic
B41: Risk-free rate (Rf) | C41: =OD_Valuation!C7 -> 0.045 | D41: Lợi suất TPCP VN 10 năm
B42: Beta | C42: =OD_Valuation!C8 -> 1.05 | D42: SLOPE 246 ngày YEG vs VN-Index (5/2025-4/2026)
B43: Equity Risk Premium (ERP) | C43: =OD_Valuation!C9 -> 0.0911 | D43: Avg(Method 1 CDS, Method 2 Moody's, Damodaran)
B44: Cost of Equity (Ke) | C44: =OD_Valuation!C18 -> 0.140655 | D44: Rf + Beta × ERP
B45: Cost of Debt (Kd, after-tax) | C45: =OD_Valuation!C19 -> 0.088 | D45: Lãi vay bình quân × (1-tax)
B46: WACC | C46: =OD_Valuation!C20 -> 0.12222575 | D46: Weighted: Ke × E/(D+E) + Kd × D/(D+E)
B47: Terminal growth (g) | C47: =OD_Valuation!C13 -> 0.025 | D47: GDP VN dài hạn + lạm phát mục tiêu
B48: Enterprise Value (tỷ VND) | C48: =OD_Valuation!C40 -> 4207.5063 | D48: Sum PV(FCFF) + PV(Terminal Value)
B49: Equity Value (tỷ VND) | C49: =OD_Valuation!C46 -> 3821.7118 | D49: EV - Net Debt + Non-operating assets
B50: Số cổ phiếu (triệu) | C50: =OD_Valuation!C47 -> 191.80203 | D50: Shares outstanding
B51: Giá mục tiêu (VND/cp) | C51: =OD_Valuation!C48 -> 19925.293 | D51: Equity Value / Shares outstanding
B52: Giá hiện tại (24/4/2026) | C52: 9990 | D52: Giá đóng cửa HOSE
B53: Upside (%) | C53: =C51/C52-1 -> 0.99452387 | D53: Khuyến nghị: MUA
B55: E. Conclusion (Kết luận & Khuyến nghị)
B56: 1. Điểm mạnh (Strengths)
B57: Pivot thành công sang Premium Content: ATVNCG (concert + The Movie), Chị Đẹp Đạp Gió, Mẹ Siêu Nhân. Doanh thu 2024 +149% YoY (1,026 tỷ), 2025 +60% (1,639 tỷ) vượt kế hoạch ĐHCĐ.
B58: Lợi nhuận đột biến: NPAT 2024 +460%, 2025 +127% (82 tỷ). Kiểm toán EY đảm bảo chất lượng. Thủ tướng khen ngợi, tạo uy tín bền vững.
B59: IP hóa nội dung (concert lặp lại, movie spin-off, format MangoTV) đem lại operating leverage - GP% cải thiện từ 13% (2025) lên 22% (2031F).
B60: Pipeline 2025-2026 mạnh: Show It All (Techcombank đồng đầu tư), HAHA Farmer, ATVNCG concerts T6/2025, JV SYE Holdings (1/2026).
B61: Asset-light model: CapEx chỉ 4-6% revenue, ROA dự kiến tăng từ 2.7% (2025) lên 15% (2031F).
B63: 2. Điểm yếu / Rủi ro (Weaknesses & Risks)
B64: Phụ thuộc hit-driven: Doanh thu tập trung concert/show, rủi ro sản phẩm fail (concert không số đủ vé, format không được ưa chuộng).
B65: DSO lịch sử cao (290 ngày 2025): khoản phải thu chiếm ~80% doanh thu - rủi ro thanh khoản nếu khách hàng (TV/digital partner) chậm thanh toán.
B66: D/E cao trong 2026F (ST debt = balancing plug 1,635 tỷ) - cần theo dõi loại nợ cụ thể, có thể phải phát hành cổ phiếu/phân phối thêm để giảm áp lực.
B67: COGS% cao (87% 2025): chi phí sản xuất concert/show đắt. Mức cải thiện phụ thuộc khả năng monetize IP (movie, merchandise, lồng ghép quảng cáo).
... B71: 3. Định giá & Khuyến nghị (Valuation & Recommendation)
B72: ="Giá mục tiêu DCF: "&TEXT(C51,"#,##0")&" VND/cp vs giá hiện tại "&TEXT(C52,"#,##0")&" VND - Upside +"&TEXT(C53,"0%") -> Giá mục tiêu DCF: 19,925 VND/cp vs giá hiện tại 9,990 VND - Upside +99%
B73: WACC 9.63% phản ánh chi phí vốn hợp lý của doanh nghiệp VN (Beta 0.82, Rf 4.2%, ERP 8.11%). Terminal growth 4% sát với GDP VN dài hạn.
B74: Khuyến nghị: MUA (BUY) - cổ phiếu đang được định giá thấp so với tiềm năng growth từ Premium Content. Mục tiêu 12 tháng: ~31,000 VND.
B75: Catalysts ngắn hạn: KQKD Q2/2026 (concerts T6), công bố deal SYE Holdings, ra mắt Show It All / HAHA Farmer.
B76: Stop-loss: 8,500 VND (-15%) nếu doanh thu Q1-Q2/2026 không đạt 30% kế hoạch năm.
